{"月城丽景": {"plot_name": "月城丽景", "plot_url": "https://liangshan.ke.com/xiaoqu/8705132781339206/"}, "航天阳光": {"plot_name": "航天阳光", "plot_url": "https://liangshan.ke.com/xiaoqu/8705134619122588/"}, "悦城枫丹丽舍二期": {"plot_name": "悦城枫丹丽舍二期", "plot_url": "https://liangshan.ke.com/xiaoqu/8705132770854120/"}, "丽景豪庭": {"plot_name": "丽景豪庭", "plot_url": "https://liangshan.ke.com/xiaoqu/8705132779250430/"}, "航天道1号": {"plot_name": "航天道1号", "plot_url": "https://liangshan.ke.com/xiaoqu/8705132782393762/"}, "長宁小区": {"plot_name": "長宁小区", "plot_url": "https://liangshan.ke.com/xiaoqu/8705132791826755/"}, "长安花园一期": {"plot_name": "长安花园一期", "plot_url": "https://liangshan.ke.com/xiaoqu/8705132773996815/"}, "月城家园": {"plot_name": "月城家园", "plot_url": "https://liangshan.ke.com/xiaoqu/8705132785541095/"}, "长安小区": {"plot_name": "长安小区", "plot_url": "https://liangshan.ke.com/xiaoqu/87050000000067/"}, "中信国际花城": {"plot_name": "中信国际花城", "plot_url": "https://liangshan.ke.com/xiaoqu/8705132782386967/"}, "松香厂": {"plot_name": "松香厂", "plot_url": "https://liangshan.ke.com/xiaoqu/8705135530760787/"}, "长安花园二区": {"plot_name": "长安花园二区", "plot_url": "https://liangshan.ke.com/xiaoqu/8705132774000627/"}, "锦绣华都": {"plot_name": "锦绣华都", "plot_url": "https://liangshan.ke.com/xiaoqu/8705132776105619/"}, "锦绣花园": {"plot_name": "锦绣花园", "plot_url": "https://liangshan.ke.com/xiaoqu/8705132780298330/"}, "嘉月台": {"plot_name": "嘉月台", "plot_url": "https://liangshan.ke.com/xiaoqu/8705132789729397/"}, "警官花园": {"plot_name": "警官花园", "plot_url": "https://liangshan.ke.com/xiaoqu/8705134951601437/"}, "祥和路机电市场小区": {"plot_name": "祥和路机电市场小区", "plot_url": "https://liangshan.ke.com/xiaoqu/8705135426911260/"}, "欧典嘉园": {"plot_name": "欧典嘉园", "plot_url": "https://liangshan.ke.com/xiaoqu/8705132779246359/"}, "西源锦城": {"plot_name": "西源锦城", "plot_url": "https://liangshan.ke.com/xiaoqu/8705132780289365/"}, "公交家园": {"plot_name": "公交家园", "plot_url": "https://liangshan.ke.com/xiaoqu/8705132780296213/"}, "冕宁县中医院西昌住宅小区": {"plot_name": "冕宁县中医院西昌住宅小区", "plot_url": "https://liangshan.ke.com/xiaoqu/8705132784489856/"}, "兴景苑": {"plot_name": "兴景苑", "plot_url": "https://liangshan.ke.com/xiaoqu/8705132787632887/"}, "长安机械厂": {"plot_name": "长安机械厂", "plot_url": "https://liangshan.ke.com/xiaoqu/8705134803750504/"}, "301干休所": {"plot_name": "301干休所", "plot_url": "https://liangshan.ke.com/xiaoqu/8705135435321351/"}, "金晖家园": {"plot_name": "金晖家园", "plot_url": "https://liangshan.ke.com/xiaoqu/8705145738841208/"}, "公路局小车厂": {"plot_name": "公路局小车厂", "plot_url": "https://liangshan.ke.com/xiaoqu/87050000000007/"}, "长安粮站": {"plot_name": "长安粮站", "plot_url": "https://liangshan.ke.com/xiaoqu/87050000000103/"}, "林业规划设计院": {"plot_name": "林业规划设计院", "plot_url": "https://liangshan.ke.com/xiaoqu/87050000000192/"}, "航天大道一段": {"plot_name": "航天大道一段", "plot_url": "https://liangshan.ke.com/xiaoqu/87050000000413/"}, "西郊乡长安村四组44号": {"plot_name": "西郊乡长安村四组44号", "plot_url": "https://liangshan.ke.com/xiaoqu/87050000001054/"}, "兴康苑": {"plot_name": "兴康苑", "plot_url": "https://liangshan.ke.com/xiaoqu/8705132777151613/"}, "凯悦帝景": {"plot_name": "凯悦帝景", "plot_url": "https://liangshan.ke.com/xiaoqu/8705132780294952/"}, "馨苑": {"plot_name": "馨苑", "plot_url": "https://liangshan.ke.com/xiaoqu/8705132781337332/"}, "四川省地质矿产勘查开发局一〇二厂": {"plot_name": "四川省地质矿产勘查开发局一〇二厂", "plot_url": "https://liangshan.ke.com/xiaoqu/8705134611856620/"}, "轧钢厂": {"plot_name": "轧钢厂", "plot_url": "https://liangshan.ke.com/xiaoqu/8705134937965546/"}, "长安新华书店": {"plot_name": "长安新华书店", "plot_url": "https://liangshan.ke.com/xiaoqu/8705134986197995/"}, "建工小区": {"plot_name": "建工小区", "plot_url": "https://liangshan.ke.com/xiaoqu/8705135007164145/"}, "荞窝监狱驻西昌干休所": {"plot_name": "荞窝监狱驻西昌干休所", "plot_url": "https://liangshan.ke.com/xiaoqu/8705135379664368/"}, "西昌市盐业公司": {"plot_name": "西昌市盐业公司", "plot_url": "https://liangshan.ke.com/xiaoqu/8705135430056404/"}, "西运三公司家属院": {"plot_name": "西运三公司家属院", "plot_url": "https://liangshan.ke.com/xiaoqu/8705135449991754/"}, "四川凉山国家粮食储备库": {"plot_name": "四川凉山国家粮食储备库", "plot_url": "https://liangshan.ke.com/xiaoqu/8705135451041169/"}, "劳动职业技术学校新家属区": {"plot_name": "劳动职业技术学校新家属区", "plot_url": "https://liangshan.ke.com/xiaoqu/8705135452097729/"}, "林运小区": {"plot_name": "林运小区", "plot_url": "https://liangshan.ke.com/xiaoqu/8705135487769242/"}, "冕中办事处": {"plot_name": "冕中办事处", "plot_url": "https://liangshan.ke.com/xiaoqu/8705137463813232/"}, "建设北路2号": {"plot_name": "建设北路2号", "plot_url": "https://liangshan.ke.com/xiaoqu/8705139095833823/"}, "建设北路1号": {"plot_name": "建设北路1号", "plot_url": "https://liangshan.ke.com/xiaoqu/8705139980983189/"}, "工商局长安经济实用房": {"plot_name": "工商局长安经济实用房", "plot_url": "https://liangshan.ke.com/xiaoqu/8705141686269163/"}, "长安路155号": {"plot_name": "长安路155号", "plot_url": "https://liangshan.ke.com/xiaoqu/8705142494889509/"}, "建设北路6号": {"plot_name": "建设北路6号", "plot_url": "https://liangshan.ke.com/xiaoqu/8705144285200375/"}, "悦城枫丹丽舍一期": {"plot_name": "悦城枫丹丽舍一期", "plot_url": "https://liangshan.ke.com/xiaoqu/8705144312483833/"}, "建设北路5号": {"plot_name": "建设北路5号", "plot_url": "https://liangshan.ke.com/xiaoqu/8705145090685276/"}, "西郊乡长安村七组": {"plot_name": "西郊乡长安村七组", "plot_url": "https://liangshan.ke.com/xiaoqu/8705146169896451/"}, "西香国际住宅小区": {"plot_name": "西香国际住宅小区", "plot_url": "https://liangshan.ke.com/xiaoqu/8705150497991793/"}, "外滩16区": {"plot_name": "外滩16区", "plot_url": "https://liangshan.ke.com/xiaoqu/8705134606615521/"}, "南山国际社区": {"plot_name": "南山国际社区", "plot_url": "https://liangshan.ke.com/xiaoqu/8705132770854121/"}, "领地·阑台府": {"plot_name": "领地·阑台府", "plot_url": "https://liangshan.ke.com/xiaoqu/8705137362041750/"}, "碧海蓝天": {"plot_name": "碧海蓝天", "plot_url": "https://liangshan.ke.com/xiaoqu/8705132780296804/"}, "昌平建材小区": {"plot_name": "昌平建材小区", "plot_url": "https://liangshan.ke.com/xiaoqu/87050000000083/"}, "新城锦绣": {"plot_name": "新城锦绣", "plot_url": "https://liangshan.ke.com/xiaoqu/8705132786587386/"}, "海河帝景B区": {"plot_name": "海河帝景B区", "plot_url": "https://liangshan.ke.com/xiaoqu/8705132777153817/"}, "海河壹号": {"plot_name": "海河壹号", "plot_url": "https://liangshan.ke.com/xiaoqu/8705132780297318/"}, "海河帝景A区": {"plot_name": "海河帝景A区", "plot_url": "https://liangshan.ke.com/xiaoqu/8705132773997828/"}, "城南印象": {"plot_name": "城南印象", "plot_url": "https://liangshan.ke.com/xiaoqu/8705132779247668/"}, "世纪花园": {"plot_name": "世纪花园", "plot_url": "https://liangshan.ke.com/xiaoqu/8705132785539051/"}, "川林小区": {"plot_name": "川林小区", "plot_url": "https://liangshan.ke.com/xiaoqu/8705132775045689/"}, "合信南山别墅": {"plot_name": "合信南山别墅", "plot_url": "https://liangshan.ke.com/xiaoqu/8705138871235863/"}, "星光嘉苑": {"plot_name": "星光嘉苑", "plot_url": "https://liangshan.ke.com/xiaoqu/8705132772948377/"}, "四川省凉山州大桥水电开发总公司": {"plot_name": "四川省凉山州大桥水电开发总公司", "plot_url": "https://liangshan.ke.com/xiaoqu/8705134891819206/"}, "阳光路苑三期": {"plot_name": "阳光路苑三期", "plot_url": "https://liangshan.ke.com/xiaoqu/8705137257123025/"}, "南山国际社区御墅": {"plot_name": "南山国际社区御墅", "plot_url": "https://liangshan.ke.com/xiaoqu/8705141738679887/"}, "移动家属区": {"plot_name": "移动家属区", "plot_url": "https://liangshan.ke.com/xiaoqu/87050000000525/"}, "明珠花园": {"plot_name": "明珠花园", "plot_url": "https://liangshan.ke.com/xiaoqu/8705132773996910/"}, "西昌•中迪国际": {"plot_name": "西昌•中迪国际", "plot_url": "https://liangshan.ke.com/xiaoqu/8705132773998242/"}, "月中苑": {"plot_name": "月中苑", "plot_url": "https://liangshan.ke.com/xiaoqu/8705132777153863/"}, "元德园": {"plot_name": "元德园", "plot_url": "https://liangshan.ke.com/xiaoqu/8705132780298169/"}, "灵龙尚居": {"plot_name": "灵龙尚居", "plot_url": "https://liangshan.ke.com/xiaoqu/8705132785535978/"}, "碧海蓝天农行家属区": {"plot_name": "碧海蓝天农行家属区", "plot_url": "https://liangshan.ke.com/xiaoqu/8705135449994843/"}, "南山御墅A区": {"plot_name": "南山御墅A区", "plot_url": "https://liangshan.ke.com/xiaoqu/8705139298199423/"}, "航天商业广场": {"plot_name": "航天商业广场", "plot_url": "https://liangshan.ke.com/xiaoqu/87050000000122/"}, "康达花园": {"plot_name": "康达花园", "plot_url": "https://liangshan.ke.com/xiaoqu/8705132782389869/"}, "西昌阳光路苑A区": {"plot_name": "西昌阳光路苑A区", "plot_url": "https://liangshan.ke.com/xiaoqu/8705132787632886/"}, "猴王小区": {"plot_name": "猴王小区", "plot_url": "https://liangshan.ke.com/xiaoqu/8705134731397487/"}, "民体园": {"plot_name": "民体园", "plot_url": "https://liangshan.ke.com/xiaoqu/8705134816323412/"}, "宁南农资公司": {"plot_name": "宁南农资公司", "plot_url": "https://liangshan.ke.com/xiaoqu/8705135422726015/"}, "四川省凉山农业学校": {"plot_name": "四川省凉山农业学校", "plot_url": "https://liangshan.ke.com/xiaoqu/8705135430071695/"}, "凉山民族师范学校": {"plot_name": "凉山民族师范学校", "plot_url": "https://liangshan.ke.com/xiaoqu/8705135486736140/"}, "四川省地震局西昌地震中心站": {"plot_name": "四川省地震局西昌地震中心站", "plot_url": "https://liangshan.ke.com/xiaoqu/8705135551739525/"}, "西昌学院预科教育学院": {"plot_name": "西昌学院预科教育学院", "plot_url": "https://liangshan.ke.com/xiaoqu/8705139799423373/"}, "老海亭": {"plot_name": "老海亭", "plot_url": "https://liangshan.ke.com/xiaoqu/8705142767527235/"}, "邦泰御墅": {"plot_name": "邦泰御墅", "plot_url": "https://liangshan.ke.com/xiaoqu/87050000000982/"}, "合信·南山国际社区云墅": {"plot_name": "合信·南山国际社区云墅", "plot_url": "https://liangshan.ke.com/xiaoqu/87050000001717/"}, "西昌阳光路苑B区": {"plot_name": "西昌阳光路苑B区", "plot_url": "https://liangshan.ke.com/xiaoqu/8705132782395063/"}, "云影苑": {"plot_name": "云影苑", "plot_url": "https://liangshan.ke.com/xiaoqu/8705132783439169/"}, "海门渔村A区": {"plot_name": "海门渔村A区", "plot_url": "https://liangshan.ke.com/xiaoqu/8705132783444114/"}, "三岔口州国税局": {"plot_name": "三岔口州国税局", "plot_url": "https://liangshan.ke.com/xiaoqu/8705134797458993/"}, "翔龙苑小区": {"plot_name": "翔龙苑小区", "plot_url": "https://liangshan.ke.com/xiaoqu/8705135353456041/"}, "海门渔村B区": {"plot_name": "海门渔村B区", "plot_url": "https://liangshan.ke.com/xiaoqu/8705135526566471/"}, "兰台府": {"plot_name": "兰台府", "plot_url": "https://liangshan.ke.com/xiaoqu/8705148060675866/"}, "五十三号家园": {"plot_name": "五十三号家园", "plot_url": "https://liangshan.ke.com/xiaoqu/8705132784493145/"}, "州一医院家属区": {"plot_name": "州一医院家属区", "plot_url": "https://liangshan.ke.com/xiaoqu/8705136463312958/"}, "大水井公安局": {"plot_name": "大水井公安局", "plot_url": "https://liangshan.ke.com/xiaoqu/8705134955776167/"}, "山水印象": {"plot_name": "山水印象", "plot_url": "https://liangshan.ke.com/xiaoqu/8705143153573760/"}, "百货公司百货站生活区": {"plot_name": "百货公司百货站生活区", "plot_url": "https://liangshan.ke.com/xiaoqu/8705132776096174/"}, "四川省凉山监狱": {"plot_name": "四川省凉山监狱", "plot_url": "https://liangshan.ke.com/xiaoqu/8705134804800734/"}, "西昌市教育局住宅区": {"plot_name": "西昌市教育局住宅区", "plot_url": "https://liangshan.ke.com/xiaoqu/8705134872950058/"}, "仿古小区": {"plot_name": "仿古小区", "plot_url": "https://liangshan.ke.com/xiaoqu/8705135851792452/"}, "四川省凉山彝族自治州歌舞团": {"plot_name": "四川省凉山彝族自治州歌舞团", "plot_url": "https://liangshan.ke.com/xiaoqu/8705138769522657/"}, "西昌一中": {"plot_name": "西昌一中", "plot_url": "https://liangshan.ke.com/xiaoqu/8705142570392094/"}, "教育学院": {"plot_name": "教育学院", "plot_url": "https://liangshan.ke.com/xiaoqu/87050000000059/"}, "宁远桥公路局": {"plot_name": "宁远桥公路局", "plot_url": "https://liangshan.ke.com/xiaoqu/87050000000078/"}, "马水河农行家属区": {"plot_name": "马水河农行家属区", "plot_url": "https://liangshan.ke.com/xiaoqu/87050000000109/"}, "上顺城街129号": {"plot_name": "上顺城街129号", "plot_url": "https://liangshan.ke.com/xiaoqu/87050000001332/"}, "大巷口康华大药房": {"plot_name": "大巷口康华大药房", "plot_url": "https://liangshan.ke.com/xiaoqu/87050000001391/"}, "西昌一中凤凰小区": {"plot_name": "西昌一中凤凰小区", "plot_url": "https://liangshan.ke.com/xiaoqu/8705132775048038/"}, "西昌市地税局宁远小区职工住宅": {"plot_name": "西昌市地税局宁远小区职工住宅", "plot_url": "https://liangshan.ke.com/xiaoqu/8705132778202252/"}, "北苑公寓": {"plot_name": "北苑公寓", "plot_url": "https://liangshan.ke.com/xiaoqu/8705132778203070/"}, "宁远小区": {"plot_name": "宁远小区", "plot_url": "https://liangshan.ke.com/xiaoqu/8705132779248965/"}, "人大小区": {"plot_name": "人大小区", "plot_url": "https://liangshan.ke.com/xiaoqu/8705132781345927/"}, "世达·書香苑": {"plot_name": "世达·書香苑", "plot_url": "https://liangshan.ke.com/xiaoqu/8705132782392812/"}, "昭觉办事处": {"plot_name": "昭觉办事处", "plot_url": "https://liangshan.ke.com/xiaoqu/8705132785538900/"}, "水厂小区": {"plot_name": "水厂小区", "plot_url": "https://liangshan.ke.com/xiaoqu/8705132786586253/"}, "飞播林家园": {"plot_name": "飞播林家园", "plot_url": "https://liangshan.ke.com/xiaoqu/8705134640085159/"}, "胜利北路地税局": {"plot_name": "胜利北路地税局", "plot_url": "https://liangshan.ke.com/xiaoqu/8705134962081791/"}, "马水河农业银行": {"plot_name": "马水河农业银行", "plot_url": "https://liangshan.ke.com/xiaoqu/8705135006127263/"}, "省西昌二中": {"plot_name": "省西昌二中", "plot_url": "https://liangshan.ke.com/xiaoqu/8705135074284089/"}, "西昌市财政局": {"plot_name": "西昌市财政局", "plot_url": "https://liangshan.ke.com/xiaoqu/8705135095253114/"}, "凉山彝族自治州粮食局": {"plot_name": "凉山彝族自治州粮食局", "plot_url": "https://liangshan.ke.com/xiaoqu/8705135101535105/"}, "宁远桥房改办": {"plot_name": "宁远桥房改办", "plot_url": "https://liangshan.ke.com/xiaoqu/8705135375479126/"}, "宁远桥桥梁工程队家属区": {"plot_name": "宁远桥桥梁工程队家属区", "plot_url": "https://liangshan.ke.com/xiaoqu/8705135381757894/"}, "益门煤矿": {"plot_name": "益门煤矿", "plot_url": "https://liangshan.ke.com/xiaoqu/8705135384907498/"}, "宁远桥政府小区": {"plot_name": "宁远桥政府小区", "plot_url": "https://liangshan.ke.com/xiaoqu/8705135409086885/"}, "大水井市委": {"plot_name": "大水井市委", "plot_url": "https://liangshan.ke.com/xiaoqu/8705135857043861/"}, "商贸城商住楼": {"plot_name": "商贸城商住楼", "plot_url": "https://liangshan.ke.com/xiaoqu/8705136081429848/"}, "胜利北路181号": {"plot_name": "胜利北路181号", "plot_url": "https://liangshan.ke.com/xiaoqu/8705136174884032/"}, "印刷厂": {"plot_name": "印刷厂", "plot_url": "https://liangshan.ke.com/xiaoqu/8705136633225753/"}, "南街83号": {"plot_name": "南街83号", "plot_url": "https://liangshan.ke.com/xiaoqu/8705139729160516/"}, "西昌市经济局宿舍": {"plot_name": "西昌市经济局宿舍", "plot_url": "https://liangshan.ke.com/xiaoqu/8705140806336286/"}, "西昌市水利局宿舍": {"plot_name": "西昌市水利局宿舍", "plot_url": "https://liangshan.ke.com/xiaoqu/8705140806336341/"}, "西昌市农机局": {"plot_name": "西昌市农机局", "plot_url": "https://liangshan.ke.com/xiaoqu/8705141037085302/"}, "州政府小区": {"plot_name": "州政府小区", "plot_url": "https://liangshan.ke.com/xiaoqu/8705141156637807/"}, "上顺城街42号": {"plot_name": "上顺城街42号", "plot_url": "https://liangshan.ke.com/xiaoqu/8705141157698386/"}, "盐源县驻西昌市西河干休所": {"plot_name": "盐源县驻西昌市西河干休所", "plot_url": "https://liangshan.ke.com/xiaoqu/8705141160851025/"}, "南红苑": {"plot_name": "南红苑", "plot_url": "https://liangshan.ke.com/xiaoqu/8705141312881789/"}, "老西门街25号": {"plot_name": "老西门街25号", "plot_url": "https://liangshan.ke.com/xiaoqu/8705142068999036/"}, "西昌市公路管理局家属院": {"plot_name": "西昌市公路管理局家属院", "plot_url": "https://liangshan.ke.com/xiaoqu/8705144286238986/"}, "老山场坝巷56号": {"plot_name": "老山场坝巷56号", "plot_url": "https://liangshan.ke.com/xiaoqu/8705148156116089/"}, "陶家祠61号": {"plot_name": "陶家祠61号", "plot_url": "https://liangshan.ke.com/xiaoqu/8705148279827037/"}, "老西门街26号": {"plot_name": "老西门街26号", "plot_url": "https://liangshan.ke.com/xiaoqu/8705148431893499/"}, "中国人寿保险公司家属区": {"plot_name": "中国人寿保险公司家属区", "plot_url": "https://liangshan.ke.com/xiaoqu/8705148889230559/"}, "上大水沟17号": {"plot_name": "上大水沟17号", "plot_url": "https://liangshan.ke.com/xiaoqu/8705151904466303/"}, "宁远鑫阳楼": {"plot_name": "宁远鑫阳楼", "plot_url": "https://liangshan.ke.com/xiaoqu/8705135377568849/"}, "海成茗居": {"plot_name": "海成茗居", "plot_url": "https://liangshan.ke.com/xiaoqu/87050000000211/"}, "宁远航天家园": {"plot_name": "宁远航天家园", "plot_url": "https://liangshan.ke.com/xiaoqu/8705132777154372/"}, "出山大厦": {"plot_name": "出山大厦", "plot_url": "https://liangshan.ke.com/xiaoqu/87050000000139/"}, "宁远安居小区": {"plot_name": "宁远安居小区", "plot_url": "https://liangshan.ke.com/xiaoqu/8705132775045374/"}, "金阳县教师干休所": {"plot_name": "金阳县教师干休所", "plot_url": "https://liangshan.ke.com/xiaoqu/8705135378663722/"}, "领地.悦邛海": {"plot_name": "领地.悦邛海", "plot_url": "https://liangshan.ke.com/xiaoqu/8705137357877179/"}, "凉山审计局": {"plot_name": "凉山审计局", "plot_url": "https://liangshan.ke.com/xiaoqu/8705134855121992/"}, "鑫源阳光(北碧府路)": {"plot_name": "鑫源阳光(北碧府路)", "plot_url": "https://liangshan.ke.com/xiaoqu/87050000000029/"}, "生生苑": {"plot_name": "生生苑", "plot_url": "https://liangshan.ke.com/xiaoqu/87050000000115/"}, "航天路金阳干休所": {"plot_name": "航天路金阳干休所", "plot_url": "https://liangshan.ke.com/xiaoqu/87050000000163/"}, "石油公司": {"plot_name": "石油公司", "plot_url": "https://liangshan.ke.com/xiaoqu/87050000000167/"}, "居缘小区": {"plot_name": "居缘小区", "plot_url": "https://liangshan.ke.com/xiaoqu/8705132777142832/"}, "河东安置小区": {"plot_name": "河东安置小区", "plot_url": "https://liangshan.ke.com/xiaoqu/8705132781346058/"}, "凉山州人大": {"plot_name": "凉山州人大", "plot_url": "https://liangshan.ke.com/xiaoqu/8705134643242931/"}, "城南大道电信小区": {"plot_name": "城南大道电信小区", "plot_url": "https://liangshan.ke.com/xiaoqu/8705134881344533/"}, "胜利南路自来水公司": {"plot_name": "胜利南路自来水公司", "plot_url": "https://liangshan.ke.com/xiaoqu/8705134903359366/"}, "中共凉山州委党校": {"plot_name": "中共凉山州委党校", "plot_url": "https://liangshan.ke.com/xiaoqu/8705134969406332/"}, "园丁苑": {"plot_name": "园丁苑", "plot_url": "https://liangshan.ke.com/xiaoqu/8705135424829648/"}, "州委机关小院": {"plot_name": "州委机关小院", "plot_url": "https://liangshan.ke.com/xiaoqu/87050000000015/"}, "西昌一小": {"plot_name": "西昌一小", "plot_url": "https://liangshan.ke.com/xiaoqu/87050000000034/"}, "华景園": {"plot_name": "华景園", "plot_url": "https://liangshan.ke.com/xiaoqu/87050000000063/"}, "文汇东一区": {"plot_name": "文汇东一区", "plot_url": "https://liangshan.ke.com/xiaoqu/87050000000098/"}, "凉山彝族自治州农牧局": {"plot_name": "凉山彝族自治州农牧局", "plot_url": "https://liangshan.ke.com/xiaoqu/87050000000172/"}, "市政协家属区": {"plot_name": "市政协家属区", "plot_url": "https://liangshan.ke.com/xiaoqu/87050000000177/"}, "金昌苑": {"plot_name": "金昌苑", "plot_url": "https://liangshan.ke.com/xiaoqu/87050000000182/"}, "海河花园": {"plot_name": "海河花园", "plot_url": "https://liangshan.ke.com/xiaoqu/87050000000200/"}, "胜利东路物资局": {"plot_name": "胜利东路物资局", "plot_url": "https://liangshan.ke.com/xiaoqu/87050000000205/"}, "河东苑": {"plot_name": "河东苑", "plot_url": "https://liangshan.ke.com/xiaoqu/87050000000247/"}, "荣昌苑": {"plot_name": "荣昌苑", "plot_url": "https://liangshan.ke.com/xiaoqu/8705132773997652/"}, "福源居": {"plot_name": "福源居", "plot_url": "https://liangshan.ke.com/xiaoqu/8705132780297192/"}, "北部湾": {"plot_name": "北部湾", "plot_url": "https://liangshan.ke.com/xiaoqu/8705132781345437/"}, "星光苑C区": {"plot_name": "星光苑C区", "plot_url": "https://liangshan.ke.com/xiaoqu/8705132784489855/"}, "凉北小区": {"plot_name": "凉北小区", "plot_url": "https://liangshan.ke.com/xiaoqu/8705132784491412/"}, "瑞錦園": {"plot_name": "瑞錦園", "plot_url": "https://liangshan.ke.com/xiaoqu/8705132786587166/"}, "金英大厦": {"plot_name": "金英大厦", "plot_url": "https://liangshan.ke.com/xiaoqu/8705134572012411/"}, "汇通苑": {"plot_name": "汇通苑", "plot_url": "https://liangshan.ke.com/xiaoqu/8705134591842673/"}, "龙旺商业城": {"plot_name": "龙旺商业城", "plot_url": "https://liangshan.ke.com/xiaoqu/8705134670580908/"}, "同德颐恒苑": {"plot_name": "同德颐恒苑", "plot_url": "https://liangshan.ke.com/xiaoqu/8705134900211974/"}, "马水河财政局": {"plot_name": "马水河财政局", "plot_url": "https://liangshan.ke.com/xiaoqu/8705134939016001/"}, "凉山彝族自治州疾病预防控制中心": {"plot_name": "凉山彝族自治州疾病预防控制中心", "plot_url": "https://liangshan.ke.com/xiaoqu/8705134977812753/"}, "西昌市建筑勘测设计院": {"plot_name": "西昌市建筑勘测设计院", "plot_url": "https://liangshan.ke.com/xiaoqu/8705134977813132/"}, "凉山州州级机关第二幼儿园家属区": {"plot_name": "凉山州州级机关第二幼儿园家属区", "plot_url": "https://liangshan.ke.com/xiaoqu/8705134998781707/"}, "楠华小区": {"plot_name": "楠华小区", "plot_url": "https://liangshan.ke.com/xiaoqu/8705135006116507/"}, "月城广场经贸委家属区": {"plot_name": "月城广场经贸委家属区", "plot_url": "https://liangshan.ke.com/xiaoqu/8705135045968390/"}, "顺河路综合楼": {"plot_name": "顺河路综合楼", "plot_url": "https://liangshan.ke.com/xiaoqu/8705135134227070/"}, "长安东路金海岸商住楼": {"plot_name": "长安东路金海岸商住楼", "plot_url": "https://liangshan.ke.com/xiaoqu/8705135345066989/"}, "航天路西区": {"plot_name": "航天路西区", "plot_url": "https://liangshan.ke.com/xiaoqu/8705135385967611/"}, "西昌市公路管理局": {"plot_name": "西昌市公路管理局", "plot_url": "https://liangshan.ke.com/xiaoqu/8705135393352149/"}, "轻工苑": {"plot_name": "轻工苑", "plot_url": "https://liangshan.ke.com/xiaoqu/8705135426911375/"}, "金林郡景": {"plot_name": "金林郡景", "plot_url": "https://liangshan.ke.com/xiaoqu/8705135447883105/"}, "西昌长安布拖干休所": {"plot_name": "西昌长安布拖干休所", "plot_url": "https://liangshan.ke.com/xiaoqu/8705135478346407/"}, "四川省西昌长途线路局": {"plot_name": "四川省西昌长途线路局", "plot_url": "https://liangshan.ke.com/xiaoqu/8705135784580165/"}, "长安中路52号": {"plot_name": "长安中路52号", "plot_url": "https://liangshan.ke.com/xiaoqu/8705136401439601/"}, "商业街二段99号": {"plot_name": "商业街二段99号", "plot_url": "https://liangshan.ke.com/xiaoqu/8705139095834391/"}, "三岔口西巷50号": {"plot_name": "三岔口西巷50号", "plot_url": "https://liangshan.ke.com/xiaoqu/8705139152454366/"}, "西昌市税务局家属院": {"plot_name": "西昌市税务局家属院", "plot_url": "https://liangshan.ke.com/xiaoqu/8705139549845864/"}, "凉山州农行干休所": {"plot_name": "凉山州农行干休所", "plot_url": "https://liangshan.ke.com/xiaoqu/8705139654705475/"}, "文体局家属区": {"plot_name": "文体局家属区", "plot_url": "https://liangshan.ke.com/xiaoqu/8705139973640528/"}, "西昌七小": {"plot_name": "西昌七小", "plot_url": "https://liangshan.ke.com/xiaoqu/8705140806345311/"}, "西昌市西郊乡龙眼井村": {"plot_name": "西昌市西郊乡龙眼井村", "plot_url": "https://liangshan.ke.com/xiaoqu/8705142793729257/"}, "碧桂园领地.南山府": {"plot_name": "碧桂园领地.南山府", "plot_url": "https://liangshan.ke.com/xiaoqu/8705146165715211/"}, "红旗幼儿园职工住宅": {"plot_name": "红旗幼儿园职工住宅", "plot_url": "https://liangshan.ke.com/xiaoqu/8705147855159680/"}, "中药材公司宿舍": {"plot_name": "中药材公司宿舍", "plot_url": "https://liangshan.ke.com/xiaoqu/87050000000010/"}, "健康路公安局": {"plot_name": "健康路公安局", "plot_url": "https://liangshan.ke.com/xiaoqu/87050000000012/"}, "张家巷": {"plot_name": "张家巷", "plot_url": "https://liangshan.ke.com/xiaoqu/87050000000017/"}, "281五交化": {"plot_name": "281五交化", "plot_url": "https://liangshan.ke.com/xiaoqu/87050000000032/"}, "步行街经贸委": {"plot_name": "步行街经贸委", "plot_url": "https://liangshan.ke.com/xiaoqu/87050000000039/"}, "阳光大厦": {"plot_name": "阳光大厦", "plot_url": "https://liangshan.ke.com/xiaoqu/87050000000048/"}, "吉祥路疾控中心": {"plot_name": "吉祥路疾控中心", "plot_url": "https://liangshan.ke.com/xiaoqu/87050000000049/"}, "胜利路国土局": {"plot_name": "胜利路国土局", "plot_url": "https://liangshan.ke.com/xiaoqu/87050000000050/"}, "南街防疫站": {"plot_name": "南街防疫站", "plot_url": "https://liangshan.ke.com/xiaoqu/87050000000054/"}, "海能公寓": {"plot_name": "海能公寓", "plot_url": "https://liangshan.ke.com/xiaoqu/87050000000058/"}, "聚宝楼": {"plot_name": "聚宝楼", "plot_url": "https://liangshan.ke.com/xiaoqu/87050000000071/"}, "消防队单位房": {"plot_name": "消防队单位房", "plot_url": "https://liangshan.ke.com/xiaoqu/87050000000077/"}, "西街粮食局": {"plot_name": "西街粮食局", "plot_url": "https://liangshan.ke.com/xiaoqu/87050000000104/"}, "宁远桥食品厂": {"plot_name": "宁远桥食品厂", "plot_url": "https://liangshan.ke.com/xiaoqu/87050000000120/"}, "凉山大学": {"plot_name": "凉山大学", "plot_url": "https://liangshan.ke.com/xiaoqu/87050000000127/"}, "凉山州财政局职工住宅楼": {"plot_name": "凉山州财政局职工住宅楼", "plot_url": "https://liangshan.ke.com/xiaoqu/87050000000132/"}, "长安转盘农行小区": {"plot_name": "长安转盘农行小区", "plot_url": "https://liangshan.ke.com/xiaoqu/87050000000144/"}, "西昌市公安局北城派出所家属区": {"plot_name": "西昌市公安局北城派出所家属区", "plot_url": "https://liangshan.ke.com/xiaoqu/87050000000145/"}, "西门坡19队家属区": {"plot_name": "西门坡19队家属区", "plot_url": "https://liangshan.ke.com/xiaoqu/87050000000149/"}, "航天置业建设集团": {"plot_name": "航天置业建设集团", "plot_url": "https://liangshan.ke.com/xiaoqu/87050000000150/"}, "市林产公司家属区": {"plot_name": "市林产公司家属区", "plot_url": "https://liangshan.ke.com/xiaoqu/87050000000152/"}, "西运司": {"plot_name": "西运司", "plot_url": "https://liangshan.ke.com/xiaoqu/87050000000155/"}, "星光苑B区": {"plot_name": "星光苑B区", "plot_url": "https://liangshan.ke.com/xiaoqu/87050000000159/"}, "三岔口东路市农牧局": {"plot_name": "三岔口东路市农牧局", "plot_url": "https://liangshan.ke.com/xiaoqu/87050000000164/"}, "胜利南路物价局家属小区": {"plot_name": "胜利南路物价局家属小区", "plot_url": "https://liangshan.ke.com/xiaoqu/87050000000170/"}, "老达达超市木里干休所": {"plot_name": "老达达超市木里干休所", "plot_url": "https://liangshan.ke.com/xiaoqu/87050000000171/"}, "胜利北路凉山州地方税务局": {"plot_name": "胜利北路凉山州地方税务局", "plot_url": "https://liangshan.ke.com/xiaoqu/87050000000175/"}, "朱家巷4号": {"plot_name": "朱家巷4号", "plot_url": "https://liangshan.ke.com/xiaoqu/87050000000197/"}, "西昌市餐饮服务部住房": {"plot_name": "西昌市餐饮服务部住房", "plot_url": "https://liangshan.ke.com/xiaoqu/87050000000201/"}, "胜利南路282": {"plot_name": "胜利南路282", "plot_url": "https://liangshan.ke.com/xiaoqu/87050000000202/"}, "化工小区": {"plot_name": "化工小区", "plot_url": "https://liangshan.ke.com/xiaoqu/87050000000209/"}, "西昌市胜利北路181号城北小区安居园": {"plot_name": "西昌市胜利北路181号城北小区安居园", "plot_url": "https://liangshan.ke.com/xiaoqu/87050000000251/"}, "府街文化局": {"plot_name": "府街文化局", "plot_url": "https://liangshan.ke.com/xiaoqu/87050000000269/"}, "滨河路二段55号": {"plot_name": "滨河路二段55号", "plot_url": "https://liangshan.ke.com/xiaoqu/87050000000311/"}, "马水河巷商业步行街": {"plot_name": "马水河巷商业步行街", "plot_url": "https://liangshan.ke.com/xiaoqu/87050000000371/"}, "新华书店": {"plot_name": "新华书店", "plot_url": "https://liangshan.ke.com/xiaoqu/87050000000398/"}, "新世界大厦": {"plot_name": "新世界大厦", "plot_url": "https://liangshan.ke.com/xiaoqu/87050000000430/"}, "西昌市仓街43号": {"plot_name": "西昌市仓街43号", "plot_url": "https://liangshan.ke.com/xiaoqu/87050000000461/"}, "宁远巷102号": {"plot_name": "宁远巷102号", "plot_url": "https://liangshan.ke.com/xiaoqu/87050000000497/"}, "名轩商务酒店": {"plot_name": "名轩商务酒店", "plot_url": "https://liangshan.ke.com/xiaoqu/87050000000499/"}, "长安派出所家属院": {"plot_name": "长安派出所家属院", "plot_url": "https://liangshan.ke.com/xiaoqu/87050000000549/"}, "福临家园": {"plot_name": "福临家园", "plot_url": "https://liangshan.ke.com/xiaoqu/87050000000553/"}, "西昌市司法局": {"plot_name": "西昌市司法局", "plot_url": "https://liangshan.ke.com/xiaoqu/87050000000555/"}, "昌平建材市场": {"plot_name": "昌平建材市场", "plot_url": "https://liangshan.ke.com/xiaoqu/87050000000568/"}, "武装部家属区": {"plot_name": "武装部家属区", "plot_url": "https://liangshan.ke.com/xiaoqu/87050000000569/"}, "鑫达金阁": {"plot_name": "鑫达金阁", "plot_url": "https://liangshan.ke.com/xiaoqu/87050000000581/"}, "达达购物广场": {"plot_name": "达达购物广场", "plot_url": "https://liangshan.ke.com/xiaoqu/87050000000597/"}, "西门坡街66号": {"plot_name": "西门坡街66号", "plot_url": "https://liangshan.ke.com/xiaoqu/87050000000617/"}, "健康路": {"plot_name": "健康路", "plot_url": "https://liangshan.ke.com/xiaoqu/87050000000623/"}, "晏兴佳园": {"plot_name": "晏兴佳园", "plot_url": "https://liangshan.ke.com/xiaoqu/87050000000637/"}, "商业街二段25号": {"plot_name": "商业街二段25号", "plot_url": "https://liangshan.ke.com/xiaoqu/87050000000641/"}, "海河西路": {"plot_name": "海河西路", "plot_url": "https://liangshan.ke.com/xiaoqu/87050000000678/"}, "钟楼上苑": {"plot_name": "钟楼上苑", "plot_url": "https://liangshan.ke.com/xiaoqu/87050000000718/"}, "广播电视剧家属区": {"plot_name": "广播电视剧家属区", "plot_url": "https://liangshan.ke.com/xiaoqu/87050000000790/"}, "黄家巷48号西昌市广播局": {"plot_name": "黄家巷48号西昌市广播局", "plot_url": "https://liangshan.ke.com/xiaoqu/87050000000791/"}, "商业街二段": {"plot_name": "商业街二段", "plot_url": "https://liangshan.ke.com/xiaoqu/87050000000794/"}, "大水井28号": {"plot_name": "大水井28号", "plot_url": "https://liangshan.ke.com/xiaoqu/87050000000802/"}, "琦洋商业广场": {"plot_name": "琦洋商业广场", "plot_url": "https://liangshan.ke.com/xiaoqu/87050000000814/"}, "风情园中路": {"plot_name": "风情园中路", "plot_url": "https://liangshan.ke.com/xiaoqu/87050000000984/"}, "文艺家苑": {"plot_name": "文艺家苑", "plot_url": "https://liangshan.ke.com/xiaoqu/87050000001013/"}, "会东办事处一区": {"plot_name": "会东办事处一区", "plot_url": "https://liangshan.ke.com/xiaoqu/87050000001018/"}, "龙辉街13附21号": {"plot_name": "龙辉街13附21号", "plot_url": "https://liangshan.ke.com/xiaoqu/87050000001056/"}, "航天大道一段326号": {"plot_name": "航天大道一段326号", "plot_url": "https://liangshan.ke.com/xiaoqu/87050000001193/"}, "益民旧城改造开发有限公司职工住宅": {"plot_name": "益民旧城改造开发有限公司职工住宅", "plot_url": "https://liangshan.ke.com/xiaoqu/87050000001510/"}, "西眼井南巷10号": {"plot_name": "西眼井南巷10号", "plot_url": "https://liangshan.ke.com/xiaoqu/87050000001948/"}, "五交化小区": {"plot_name": "五交化小区", "plot_url": "https://liangshan.ke.com/xiaoqu/8705132770854119/"}, "银杏苑": {"plot_name": "银杏苑", "plot_url": "https://liangshan.ke.com/xiaoqu/8705132772947987/"}, "建兴锦苑小区": {"plot_name": "建兴锦苑小区", "plot_url": "https://liangshan.ke.com/xiaoqu/8705132772948845/"}, "二八一小区": {"plot_name": "二八一小区", "plot_url": "https://liangshan.ke.com/xiaoqu/8705132772950054/"}, "梨园小区": {"plot_name": "梨园小区", "plot_url": "https://liangshan.ke.com/xiaoqu/8705132773997489/"}, "城南大道公路局小区": {"plot_name": "城南大道公路局小区", "plot_url": "https://liangshan.ke.com/xiaoqu/8705132773997905/"}, "晋鼎小区": {"plot_name": "晋鼎小区", "plot_url": "https://liangshan.ke.com/xiaoqu/8705132773998905/"}, "公安局胜利北路二宿舍区": {"plot_name": "公安局胜利北路二宿舍区", "plot_url": "https://liangshan.ke.com/xiaoqu/8705132775046531/"}, "化学工业公司宿舍": {"plot_name": "化学工业公司宿舍", "plot_url": "https://liangshan.ke.com/xiaoqu/8705132775046735/"}, "西昌市广电局广播电视台宿舍": {"plot_name": "西昌市广电局广播电视台宿舍", "plot_url": "https://liangshan.ke.com/xiaoqu/8705132775047322/"}, "美林小区": {"plot_name": "美林小区", "plot_url": "https://liangshan.ke.com/xiaoqu/8705132775047342/"}, "维格斯港": {"plot_name": "维格斯港", "plot_url": "https://liangshan.ke.com/xiaoqu/8705132775048099/"}, "西警苑": {"plot_name": "西警苑", "plot_url": "https://liangshan.ke.com/xiaoqu/8705132775048379/"}, "索马家园": {"plot_name": "索马家园", "plot_url": "https://liangshan.ke.com/xiaoqu/8705132776094101/"}, "大箐林场住宅区": {"plot_name": "大箐林场住宅区", "plot_url": "https://liangshan.ke.com/xiaoqu/8705132776095256/"}, "华宁苑": {"plot_name": "华宁苑", "plot_url": "https://liangshan.ke.com/xiaoqu/8705132776097115/"}, "美姑县教师安居小区": {"plot_name": "美姑县教师安居小区", "plot_url": "https://liangshan.ke.com/xiaoqu/8705132776097285/"}, "清和苑": {"plot_name": "清和苑", "plot_url": "https://liangshan.ke.com/xiaoqu/8705132776105618/"}, "北门新村": {"plot_name": "北门新村", "plot_url": "https://liangshan.ke.com/xiaoqu/8705132777142827/"}, "月城公寓二区": {"plot_name": "月城公寓二区", "plot_url": "https://liangshan.ke.com/xiaoqu/8705132778200422/"}, "西昌市水泥厂小区": {"plot_name": "西昌市水泥厂小区", "plot_url": "https://liangshan.ke.com/xiaoqu/8705132779248711/"}, "物价局职工宿舍": {"plot_name": "物价局职工宿舍", "plot_url": "https://liangshan.ke.com/xiaoqu/8705132779251595/"}, "水晶城": {"plot_name": "水晶城", "plot_url": "https://liangshan.ke.com/xiaoqu/8705132780297877/"}, "鑫合阳光": {"plot_name": "鑫合阳光", "plot_url": "https://liangshan.ke.com/xiaoqu/8705132781340690/"}, "锅炉厂宏茂南苑": {"plot_name": "锅炉厂宏茂南苑", "plot_url": "https://liangshan.ke.com/xiaoqu/8705132781343703/"}, "西河苑": {"plot_name": "西河苑", "plot_url": "https://liangshan.ke.com/xiaoqu/8705132781345207/"}, "西昌家园": {"plot_name": "西昌家园", "plot_url": "https://liangshan.ke.com/xiaoqu/8705132781347438/"}, "凉山州农机公司第二小区": {"plot_name": "凉山州农机公司第二小区", "plot_url": "https://liangshan.ke.com/xiaoqu/8705132782393551/"}, "宁星小区": {"plot_name": "宁星小区", "plot_url": "https://liangshan.ke.com/xiaoqu/8705132782395427/"}, "锦都苑": {"plot_name": "锦都苑", "plot_url": "https://liangshan.ke.com/xiaoqu/8705132783438216/"}, "凉山公安局胜利北路一宿舍区": {"plot_name": "凉山公安局胜利北路一宿舍区", "plot_url": "https://liangshan.ke.com/xiaoqu/8705132785537846/"}, "胜利小区B区": {"plot_name": "胜利小区B区", "plot_url": "https://liangshan.ke.com/xiaoqu/8705132785538514/"}, "煤疗小区": {"plot_name": "煤疗小区", "plot_url": "https://liangshan.ke.com/xiaoqu/8705132786583981/"}, "顺河路公安局生活区": {"plot_name": "顺河路公安局生活区", "plot_url": "https://liangshan.ke.com/xiaoqu/8705132789730794/"}, "月城公寓一区": {"plot_name": "月城公寓一区", "plot_url": "https://liangshan.ke.com/xiaoqu/8705132792877909/"}, "拉拉铜矿顺河路小区": {"plot_name": "拉拉铜矿顺河路小区", "plot_url": "https://liangshan.ke.com/xiaoqu/8705132826427661/"}, "广平市场": {"plot_name": "广平市场", "plot_url": "https://liangshan.ke.com/xiaoqu/8705134597168707/"}, "金辉苑": {"plot_name": "金辉苑", "plot_url": "https://liangshan.ke.com/xiaoqu/8705134624443853/"}, "凉山彝族自治州民族宗教事务委员会": {"plot_name": "凉山彝族自治州民族宗教事务委员会", "plot_url": "https://liangshan.ke.com/xiaoqu/8705134625416351/"}, "顺河路州设计院": {"plot_name": "顺河路州设计院", "plot_url": "https://liangshan.ke.com/xiaoqu/8705134754446627/"}, "宁远桥街双定小区": {"plot_name": "宁远桥街双定小区", "plot_url": "https://liangshan.ke.com/xiaoqu/8705134756565495/"}, "凉山宾馆家属小区": {"plot_name": "凉山宾馆家属小区", "plot_url": "https://liangshan.ke.com/xiaoqu/8705134867708065/"}, "四川西昌红旗印务有限公司": {"plot_name": "四川西昌红旗印务有限公司", "plot_url": "https://liangshan.ke.com/xiaoqu/8705134873988325/"}, "健康路森源大厦": {"plot_name": "健康路森源大厦", "plot_url": "https://liangshan.ke.com/xiaoqu/8705134885525285/"}, "健康路运管所": {"plot_name": "健康路运管所", "plot_url": "https://liangshan.ke.com/xiaoqu/8705134886588821/"}, "三岔口市交警队": {"plot_name": "三岔口市交警队", "plot_url": "https://liangshan.ke.com/xiaoqu/8705134893916885/"}, "凉山彝族自治州发展和改革委员会": {"plot_name": "凉山彝族自治州发展和改革委员会", "plot_url": "https://liangshan.ke.com/xiaoqu/8705134898102307/"}, "三岔口市工商局": {"plot_name": "三岔口市工商局", "plot_url": "https://liangshan.ke.com/xiaoqu/8705134903344787/"}, "金阳县政府驻昌第二干休所": {"plot_name": "金阳县政府驻昌第二干休所", "plot_url": "https://liangshan.ke.com/xiaoqu/8705134913835965/"}, "西昌市公路局管路家属区": {"plot_name": "西昌市公路局管路家属区", "plot_url": "https://liangshan.ke.com/xiaoqu/8705134928517696/"}, "凉山州长兴建筑有限责任公司": {"plot_name": "凉山州长兴建筑有限责任公司", "plot_url": "https://liangshan.ke.com/xiaoqu/8705134934815156/"}, "西昌市第九小学": {"plot_name": "西昌市第九小学", "plot_url": "https://liangshan.ke.com/xiaoqu/8705134936919877/"}, "普格干休所": {"plot_name": "普格干休所", "plot_url": "https://liangshan.ke.com/xiaoqu/8705134940047624/"}, "三岔口司法局经济适用房": {"plot_name": "三岔口司法局经济适用房", "plot_url": "https://liangshan.ke.com/xiaoqu/8705134941109068/"}, "东风幼儿园": {"plot_name": "东风幼儿园", "plot_url": "https://liangshan.ke.com/xiaoqu/8705134941111619/"}, "凉山彝族自治州民族体育馆": {"plot_name": "凉山彝族自治州民族体育馆", "plot_url": "https://liangshan.ke.com/xiaoqu/8705134944254546/"}, "胜利北路电力公司": {"plot_name": "胜利北路电力公司", "plot_url": "https://liangshan.ke.com/xiaoqu/8705134963132486/"}, "三岔口国税局": {"plot_name": "三岔口国税局", "plot_url": "https://liangshan.ke.com/xiaoqu/8705134964181822/"}, "西昌市移民局": {"plot_name": "西昌市移民局", "plot_url": "https://liangshan.ke.com/xiaoqu/8705134965219144/"}, "胜利路蔬菜公司": {"plot_name": "胜利路蔬菜公司", "plot_url": "https://liangshan.ke.com/xiaoqu/8705134975709517/"}, "滨河路菜市场": {"plot_name": "滨河路菜市场", "plot_url": "https://liangshan.ke.com/xiaoqu/8705134986183031/"}, "西眼井小区": {"plot_name": "西眼井小区", "plot_url": "https://liangshan.ke.com/xiaoqu/8705135029192102/"}, "宏信证券": {"plot_name": "宏信证券", "plot_url": "https://liangshan.ke.com/xiaoqu/8705135032318861/"}, "长安人民法庭": {"plot_name": "长安人民法庭", "plot_url": "https://liangshan.ke.com/xiaoqu/8705135048053443/"}, "四川省彝文学校": {"plot_name": "四川省彝文学校", "plot_url": "https://liangshan.ke.com/xiaoqu/8705135076372827/"}, "西昌市文化宫": {"plot_name": "西昌市文化宫", "plot_url": "https://liangshan.ke.com/xiaoqu/8705135130013368/"}, "商业街州食品公司": {"plot_name": "商业街州食品公司", "plot_url": "https://liangshan.ke.com/xiaoqu/8705135130020512/"}, "西昌市中医医院": {"plot_name": "西昌市中医医院", "plot_url": "https://liangshan.ke.com/xiaoqu/8705135130020576/"}, "马水河文化馆": {"plot_name": "马水河文化馆", "plot_url": "https://liangshan.ke.com/xiaoqu/8705135131063545/"}, "胜利路一号煤建公司": {"plot_name": "胜利路一号煤建公司", "plot_url": "https://liangshan.ke.com/xiaoqu/8705135133178533/"}, "第一初级中学": {"plot_name": "第一初级中学", "plot_url": "https://liangshan.ke.com/xiaoqu/8705135142599285/"}, "西郊派出所": {"plot_name": "西郊派出所", "plot_url": "https://liangshan.ke.com/xiaoqu/8705135168809726/"}, "点园小区": {"plot_name": "点园小区", "plot_url": "https://liangshan.ke.com/xiaoqu/8705135168811695/"}, "凉山监狱干休所": {"plot_name": "凉山监狱干休所", "plot_url": "https://liangshan.ke.com/xiaoqu/8705135229635260/"}, "武警支队家属院": {"plot_name": "武警支队家属院", "plot_url": "https://liangshan.ke.com/xiaoqu/8705135352398258/"}, "教工宿舍": {"plot_name": "教工宿舍", "plot_url": "https://liangshan.ke.com/xiaoqu/8705135354510640/"}, "凉山州农资公司宿舍": {"plot_name": "凉山州农资公司宿舍", "plot_url": "https://liangshan.ke.com/xiaoqu/8705135354516559/"}, "雅馨苑": {"plot_name": "雅馨苑", "plot_url": "https://liangshan.ke.com/xiaoqu/8705135369191164/"}, "世纪锦苑": {"plot_name": "世纪锦苑", "plot_url": "https://liangshan.ke.com/xiaoqu/8705135375474895/"}, "胜利东路发改委": {"plot_name": "胜利东路发改委", "plot_url": "https://liangshan.ke.com/xiaoqu/8705135377575355/"}, "全新火锅": {"plot_name": "全新火锅", "plot_url": "https://liangshan.ke.com/xiaoqu/8705135378670065/"}, "西昌市风景园林绿化管理处": {"plot_name": "西昌市风景园林绿化管理处", "plot_url": "https://liangshan.ke.com/xiaoqu/8705135380714584/"}, "州建四处": {"plot_name": "州建四处", "plot_url": "https://liangshan.ke.com/xiaoqu/8705135380716251/"}, "城管家园": {"plot_name": "城管家园", "plot_url": "https://liangshan.ke.com/xiaoqu/8705135381767570/"}, "西昌市审计局家属区": {"plot_name": "西昌市审计局家属区", "plot_url": "https://liangshan.ke.com/xiaoqu/8705135381772527/"}, "凉山州计划生育协会": {"plot_name": "凉山州计划生育协会", "plot_url": "https://liangshan.ke.com/xiaoqu/8705135382815141/"}, "西郊人民法庭": {"plot_name": "西郊人民法庭", "plot_url": "https://liangshan.ke.com/xiaoqu/8705135383860965/"}, "凉山州食品药品检验所": {"plot_name": "凉山州食品药品检验所", "plot_url": "https://liangshan.ke.com/xiaoqu/8705135383867090/"}, "正义路106号": {"plot_name": "正义路106号", "plot_url": "https://liangshan.ke.com/xiaoqu/8705135384908145/"}, "清迈足道": {"plot_name": "清迈足道", "plot_url": "https://liangshan.ke.com/xiaoqu/8705135387007872/"}, "凉山民师校干休所": {"plot_name": "凉山民师校干休所", "plot_url": "https://liangshan.ke.com/xiaoqu/8705135388058887/"}, "州工会家属区": {"plot_name": "州工会家属区", "plot_url": "https://liangshan.ke.com/xiaoqu/8705135401751985/"}, "西昌交通学校": {"plot_name": "西昌交通学校", "plot_url": "https://liangshan.ke.com/xiaoqu/8705135405947931/"}, "橄榄花园": {"plot_name": "橄榄花园", "plot_url": "https://liangshan.ke.com/xiaoqu/8705135406999382/"}, "吉祥路民政局小区": {"plot_name": "吉祥路民政局小区", "plot_url": "https://liangshan.ke.com/xiaoqu/8705135413286662/"}, "布拖驻西昌干休所": {"plot_name": "布拖驻西昌干休所", "plot_url": "https://liangshan.ke.com/xiaoqu/8705135416436522/"}, "复烤厂小区": {"plot_name": "复烤厂小区", "plot_url": "https://liangshan.ke.com/xiaoqu/8705135417484817/"}, "安宁小区B区": {"plot_name": "安宁小区B区", "plot_url": "https://liangshan.ke.com/xiaoqu/8705135419584634/"}, "草原站": {"plot_name": "草原站", "plot_url": "https://liangshan.ke.com/xiaoqu/8705135422735679/"}, "胜利南路医药公司家属区": {"plot_name": "胜利南路医药公司家属区", "plot_url": "https://liangshan.ke.com/xiaoqu/8705135426934734/"}, "西昌市百货集团公司职工住宅(通海南巷)": {"plot_name": "西昌市百货集团公司职工住宅(通海南巷)", "plot_url": "https://liangshan.ke.com/xiaoqu/8705135430057676/"}, "腾达建司": {"plot_name": "腾达建司", "plot_url": "https://liangshan.ke.com/xiaoqu/8705135431116688/"}, "凉山州三岔口经委小区": {"plot_name": "凉山州三岔口经委小区", "plot_url": "https://liangshan.ke.com/xiaoqu/8705135431122949/"}, "州档案局": {"plot_name": "州档案局", "plot_url": "https://liangshan.ke.com/xiaoqu/8705135434251773/"}, "农行宿舍": {"plot_name": "农行宿舍", "plot_url": "https://liangshan.ke.com/xiaoqu/8705135448934553/"}, "长安电信小区": {"plot_name": "长安电信小区", "plot_url": "https://liangshan.ke.com/xiaoqu/8705135448941433/"}, "农商银行家属区": {"plot_name": "农商银行家属区", "plot_url": "https://liangshan.ke.com/xiaoqu/8705135449994143/"}, "木里县林业局干休所": {"plot_name": "木里县林业局干休所", "plot_url": "https://liangshan.ke.com/xiaoqu/8705135453149086/"}, "国家教育招生办家属区": {"plot_name": "国家教育招生办家属区", "plot_url": "https://liangshan.ke.com/xiaoqu/8705135490938444/"}, "建兴景苑（小高层）": {"plot_name": "建兴景苑（小高层）", "plot_url": "https://liangshan.ke.com/xiaoqu/8705135491978465/"}, "大巷口居民小区": {"plot_name": "大巷口居民小区", "plot_url": "https://liangshan.ke.com/xiaoqu/8705135531827080/"}, "益民小区": {"plot_name": "益民小区", "plot_url": "https://liangshan.ke.com/xiaoqu/8705135555932563/"}, "凉山州恒力建筑公司": {"plot_name": "凉山州恒力建筑公司", "plot_url": "https://liangshan.ke.com/xiaoqu/8705135564328045/"}, "北城小区": {"plot_name": "北城小区", "plot_url": "https://liangshan.ke.com/xiaoqu/8705135570655075/"}, "凉山州工业技工学校干休所": {"plot_name": "凉山州工业技工学校干休所", "plot_url": "https://liangshan.ke.com/xiaoqu/8705135573799365/"}, "凉山中心血站家属区": {"plot_name": "凉山中心血站家属区", "plot_url": "https://liangshan.ke.com/xiaoqu/8705135576935483/"}, "凉山州社会福利服务中心": {"plot_name": "凉山州社会福利服务中心", "plot_url": "https://liangshan.ke.com/xiaoqu/8705135577977640/"}, "老城区道沟就业局": {"plot_name": "老城区道沟就业局", "plot_url": "https://liangshan.ke.com/xiaoqu/8705135603146266/"}, "西昌市国土局": {"plot_name": "西昌市国土局", "plot_url": "https://liangshan.ke.com/xiaoqu/8705135627275495/"}, "张家巷独栋": {"plot_name": "张家巷独栋", "plot_url": "https://liangshan.ke.com/xiaoqu/8705135697552830/"}, "文汇南路263附1号": {"plot_name": "文汇南路263附1号", "plot_url": "https://liangshan.ke.com/xiaoqu/8705135764674032/"}, "凉山州化工建材公司": {"plot_name": "凉山州化工建材公司", "plot_url": "https://liangshan.ke.com/xiaoqu/8705135823465105/"}, "文汇南路169号": {"plot_name": "文汇南路169号", "plot_url": "https://liangshan.ke.com/xiaoqu/8705135825575622/"}, "西郊乡张家屯村三组": {"plot_name": "西郊乡张家屯村三组", "plot_url": "https://liangshan.ke.com/xiaoqu/8705135936729459/"}, "西昌市人民检察院": {"plot_name": "西昌市人民检察院", "plot_url": "https://liangshan.ke.com/xiaoqu/8705136158096318/"}, "交警队家属区": {"plot_name": "交警队家属区", "plot_url": "https://liangshan.ke.com/xiaoqu/8705136206331134/"}, "晏家巷2号": {"plot_name": "晏家巷2号", "plot_url": "https://liangshan.ke.com/xiaoqu/8705136254568090/"}, "健康路246号": {"plot_name": "健康路246号", "plot_url": "https://liangshan.ke.com/xiaoqu/8705136254576021/"}, "黄家巷78号工会小区": {"plot_name": "黄家巷78号工会小区", "plot_url": "https://liangshan.ke.com/xiaoqu/8705136353208479/"}, "左营巷1号": {"plot_name": "左营巷1号", "plot_url": "https://liangshan.ke.com/xiaoqu/8705136426601722/"}, "胜利南路个体一条街": {"plot_name": "胜利南路个体一条街", "plot_url": "https://liangshan.ke.com/xiaoqu/8705136430800225/"}, "一环路国税小区": {"plot_name": "一环路国税小区", "plot_url": "https://liangshan.ke.com/xiaoqu/8705136457029187/"}, "名店街": {"plot_name": "名店街", "plot_url": "https://liangshan.ke.com/xiaoqu/8705136485364864/"}, "小天地公寓": {"plot_name": "小天地公寓", "plot_url": "https://liangshan.ke.com/xiaoqu/8705136490620609/"}, "三衙街18号": {"plot_name": "三衙街18号", "plot_url": "https://liangshan.ke.com/xiaoqu/8705136535696532/"}, "花园路2号": {"plot_name": "花园路2号", "plot_url": "https://liangshan.ke.com/xiaoqu/8705136537800201/"}, "文汇南路175号": {"plot_name": "文汇南路175号", "plot_url": "https://liangshan.ke.com/xiaoqu/8705136806243472/"}, "四宁巷14号": {"plot_name": "四宁巷14号", "plot_url": "https://liangshan.ke.com/xiaoqu/8705136838735262/"}, "农科路2号": {"plot_name": "农科路2号", "plot_url": "https://liangshan.ke.com/xiaoqu/8705136854468839/"}, "祁家屯巷16号": {"plot_name": "祁家屯巷16号", "plot_url": "https://liangshan.ke.com/xiaoqu/8705137004428831/"}, "领地·海月里": {"plot_name": "领地·海月里", "plot_url": "https://liangshan.ke.com/xiaoqu/8705137385110485/"}, "三岔口西路75号": {"plot_name": "三岔口西路75号", "plot_url": "https://liangshan.ke.com/xiaoqu/8705137387269952/"}, "吉祥路20号": {"plot_name": "吉祥路20号", "plot_url": "https://liangshan.ke.com/xiaoqu/8705137487942501/"}, "三岔口西巷雷波干休所": {"plot_name": "三岔口西巷雷波干休所", "plot_url": "https://liangshan.ke.com/xiaoqu/8705137640056589/"}, "南街137号": {"plot_name": "南街137号", "plot_url": "https://liangshan.ke.com/xiaoqu/8705137665241329/"}, "乡镇企业宿舍": {"plot_name": "乡镇企业宿舍", "plot_url": "https://liangshan.ke.com/xiaoqu/8705138018605569/"}, "道沟22号": {"plot_name": "道沟22号", "plot_url": "https://liangshan.ke.com/xiaoqu/8705138018607799/"}, "健康路木里干休所": {"plot_name": "健康路木里干休所", "plot_url": "https://liangshan.ke.com/xiaoqu/8705138042719638/"}, "道沟43号统计局": {"plot_name": "道沟43号统计局", "plot_url": "https://liangshan.ke.com/xiaoqu/8705138064746383/"}, "喜昌电梯公寓": {"plot_name": "喜昌电梯公寓", "plot_url": "https://liangshan.ke.com/xiaoqu/8705138067896274/"}, "大巷口上街18号": {"plot_name": "大巷口上街18号", "plot_url": "https://liangshan.ke.com/xiaoqu/8705138291301440/"}, "机电校宿舍家属区": {"plot_name": "机电校宿舍家属区", "plot_url": "https://liangshan.ke.com/xiaoqu/8705138317510942/"}, "汇通宁远小区": {"plot_name": "汇通宁远小区", "plot_url": "https://liangshan.ke.com/xiaoqu/8705138343743134/"}, "马水河交通局": {"plot_name": "马水河交通局", "plot_url": "https://liangshan.ke.com/xiaoqu/8705138438177999/"}, "老山厂坝117号": {"plot_name": "老山厂坝117号", "plot_url": "https://liangshan.ke.com/xiaoqu/8705138593382589/"}, "胜利北路3号": {"plot_name": "胜利北路3号", "plot_url": "https://liangshan.ke.com/xiaoqu/8705138614344967/"}, "下西街123号": {"plot_name": "下西街123号", "plot_url": "https://liangshan.ke.com/xiaoqu/8705138615399156/"}, "晏家巷3号": {"plot_name": "晏家巷3号", "plot_url": "https://liangshan.ke.com/xiaoqu/8705138664674204/"}, "马水河街55号": {"plot_name": "马水河街55号", "plot_url": "https://liangshan.ke.com/xiaoqu/8705138668861780/"}, "州政协小区": {"plot_name": "州政协小区", "plot_url": "https://liangshan.ke.com/xiaoqu/8705138741230244/"}, "宁远桥村六组": {"plot_name": "宁远桥村六组", "plot_url": "https://liangshan.ke.com/xiaoqu/8705138774767171/"}, "轻工小区": {"plot_name": "轻工小区", "plot_url": "https://liangshan.ke.com/xiaoqu/8705138792598569/"}, "胜利南路一段289号": {"plot_name": "胜利南路一段289号", "plot_url": "https://liangshan.ke.com/xiaoqu/8705138901660512/"}, "群星楼": {"plot_name": "群星楼", "plot_url": "https://liangshan.ke.com/xiaoqu/8705138999351581/"}, "四川省凉北林业局": {"plot_name": "四川省凉北林业局", "plot_url": "https://liangshan.ke.com/xiaoqu/8705139070646737/"}, "四川省凉山州黄金公司": {"plot_name": "四川省凉山州黄金公司", "plot_url": "https://liangshan.ke.com/xiaoqu/8705139074857600/"}, "食品厂小区": {"plot_name": "食品厂小区", "plot_url": "https://liangshan.ke.com/xiaoqu/8705139094773696/"}, "三岔口西巷农资公司": {"plot_name": "三岔口西巷农资公司", "plot_url": "https://liangshan.ke.com/xiaoqu/8705139094774915/"}, "北街": {"plot_name": "北街", "plot_url": "https://liangshan.ke.com/xiaoqu/8705139268844004/"}, "西郊乡龙眼井村六组": {"plot_name": "西郊乡龙眼井村六组", "plot_url": "https://liangshan.ke.com/xiaoqu/8705139345381852/"}, "西昌市烟草工作办公室": {"plot_name": "西昌市烟草工作办公室", "plot_url": "https://liangshan.ke.com/xiaoqu/8705139372647218/"}, "州肉联厂": {"plot_name": "州肉联厂", "plot_url": "https://liangshan.ke.com/xiaoqu/8705139503727133/"}, "四川省凉山州公路管理局": {"plot_name": "四川省凉山州公路管理局", "plot_url": "https://liangshan.ke.com/xiaoqu/8705139575027320/"}, "名店街54号": {"plot_name": "名店街54号", "plot_url": "https://liangshan.ke.com/xiaoqu/8705139604379293/"}, "朱家巷9号": {"plot_name": "朱家巷9号", "plot_url": "https://liangshan.ke.com/xiaoqu/8705139648431000/"}, "马水河小区": {"plot_name": "马水河小区", "plot_url": "https://liangshan.ke.com/xiaoqu/8705139698766338/"}, "核桃村安置小区": {"plot_name": "核桃村安置小区", "plot_url": "https://liangshan.ke.com/xiaoqu/8705139749087969/"}, "凉山州西昌铁路高级技工学校": {"plot_name": "凉山州西昌铁路高级技工学校", "plot_url": "https://liangshan.ke.com/xiaoqu/8705139799428578/"}, "北碧府路125号": {"plot_name": "北碧府路125号", "plot_url": "https://liangshan.ke.com/xiaoqu/8705140000900641/"}, "四方苑": {"plot_name": "四方苑", "plot_url": "https://liangshan.ke.com/xiaoqu/8705140104698645/"}, "凉山州博物馆办公区": {"plot_name": "凉山州博物馆办公区", "plot_url": "https://liangshan.ke.com/xiaoqu/8705140155040068/"}, "凉山州公共卫生信息中心": {"plot_name": "凉山州公共卫生信息中心", "plot_url": "https://liangshan.ke.com/xiaoqu/8705140310245618/"}, "正义路1号": {"plot_name": "正义路1号", "plot_url": "https://liangshan.ke.com/xiaoqu/8705140330174585/"}, "梨园巷2附4号": {"plot_name": "梨园巷2附4号", "plot_url": "https://liangshan.ke.com/xiaoqu/8705140404633909/"}, "城南中路17号": {"plot_name": "城南中路17号", "plot_url": "https://liangshan.ke.com/xiaoqu/8705140578793110/"}, "春城西路200号": {"plot_name": "春城西路200号", "plot_url": "https://liangshan.ke.com/xiaoqu/8705140581940686/"}, "凉山州煤建公司": {"plot_name": "凉山州煤建公司", "plot_url": "https://liangshan.ke.com/xiaoqu/8705140585104854/"}, "文馨苑": {"plot_name": "文馨苑", "plot_url": "https://liangshan.ke.com/xiaoqu/8705140629126666/"}, "魏家湾西巷12号": {"plot_name": "魏家湾西巷12号", "plot_url": "https://liangshan.ke.com/xiaoqu/8705140685753261/"}, "宁远巷78号": {"plot_name": "宁远巷78号", "plot_url": "https://liangshan.ke.com/xiaoqu/8705140730849849/"}, "航宇中路83号": {"plot_name": "航宇中路83号", "plot_url": "https://liangshan.ke.com/xiaoqu/8705140737142839/"}, "航宇中路85号": {"plot_name": "航宇中路85号", "plot_url": "https://liangshan.ke.com/xiaoqu/8705140836762346/"}, "泸山森林职工宿舍": {"plot_name": "泸山森林职工宿舍", "plot_url": "https://liangshan.ke.com/xiaoqu/8705140905955678/"}, "凉山州电影公司宿舍": {"plot_name": "凉山州电影公司宿舍", "plot_url": "https://liangshan.ke.com/xiaoqu/8705141007664853/"}, "福兴家园": {"plot_name": "福兴家园", "plot_url": "https://liangshan.ke.com/xiaoqu/8705141009775985/"}, "花园路98号": {"plot_name": "花园路98号", "plot_url": "https://liangshan.ke.com/xiaoqu/8705141014026824/"}, "中共西昌市委党校职工住宅楼": {"plot_name": "中共西昌市委党校职工住宅楼", "plot_url": "https://liangshan.ke.com/xiaoqu/8705141089540367/"}, "胜利南路一段295号": {"plot_name": "胜利南路一段295号", "plot_url": "https://liangshan.ke.com/xiaoqu/8705141135666329/"}, "永宁巷33号": {"plot_name": "永宁巷33号", "plot_url": "https://liangshan.ke.com/xiaoqu/8705141160839636/"}, "天福宾馆": {"plot_name": "天福宾馆", "plot_url": "https://liangshan.ke.com/xiaoqu/8705141263607995/"}, "西郊乡龙眼井村一组": {"plot_name": "西郊乡龙眼井村一组", "plot_url": "https://liangshan.ke.com/xiaoqu/8705141357965325/"}, "物贸中心宿舍": {"plot_name": "物贸中心宿舍", "plot_url": "https://liangshan.ke.com/xiaoqu/8705141409356060/"}, "龙眼井街59附8号": {"plot_name": "龙眼井街59附8号", "plot_url": "https://liangshan.ke.com/xiaoqu/8705141640136602/"}, "陶家祠17号": {"plot_name": "陶家祠17号", "plot_url": "https://liangshan.ke.com/xiaoqu/8705141667387084/"}, "老西门街9号": {"plot_name": "老西门街9号", "plot_url": "https://liangshan.ke.com/xiaoqu/8705141741826220/"}, "龙辉街13附27号": {"plot_name": "龙辉街13附27号", "plot_url": "https://liangshan.ke.com/xiaoqu/8705141789016031/"}, "丰源酒店": {"plot_name": "丰源酒店", "plot_url": "https://liangshan.ke.com/xiaoqu/8705141892822843/"}, "集贤社区": {"plot_name": "集贤社区", "plot_url": "https://liangshan.ke.com/xiaoqu/8705141919040661/"}, "月海苑": {"plot_name": "月海苑", "plot_url": "https://liangshan.ke.com/xiaoqu/8705142014477481/"}, "老山场坝巷93附1号": {"plot_name": "老山场坝巷93附1号", "plot_url": "https://liangshan.ke.com/xiaoqu/8705142043824989/"}, "宁远桥街10号": {"plot_name": "宁远桥街10号", "plot_url": "https://liangshan.ke.com/xiaoqu/8705142093115204/"}, "海丰村": {"plot_name": "海丰村", "plot_url": "https://liangshan.ke.com/xiaoqu/8705142222094788/"}, "海滨中路36号": {"plot_name": "海滨中路36号", "plot_url": "https://liangshan.ke.com/xiaoqu/8705142243053303/"}, "三岔口东路21号": {"plot_name": "三岔口东路21号", "plot_url": "https://liangshan.ke.com/xiaoqu/8705142548374539/"}, "浅语花开": {"plot_name": "浅语花开", "plot_url": "https://liangshan.ke.com/xiaoqu/8705142695183101/"}, "滴水岩街13号": {"plot_name": "滴水岩街13号", "plot_url": "https://liangshan.ke.com/xiaoqu/8705142797923415/"}, "城南中路18号": {"plot_name": "城南中路18号", "plot_url": "https://liangshan.ke.com/xiaoqu/8705142850456561/"}, "马水河街41号": {"plot_name": "马水河街41号", "plot_url": "https://liangshan.ke.com/xiaoqu/8705142943813507/"}, "宁远东路信用社小区": {"plot_name": "宁远东路信用社小区", "plot_url": "https://liangshan.ke.com/xiaoqu/8705142968970023/"}, "宁远桥街31号": {"plot_name": "宁远桥街31号", "plot_url": "https://liangshan.ke.com/xiaoqu/8705142975261178/"}, "陶家祠5号": {"plot_name": "陶家祠5号", "plot_url": "https://liangshan.ke.com/xiaoqu/8705143228014541/"}, "中医药材宿舍": {"plot_name": "中医药材宿舍", "plot_url": "https://liangshan.ke.com/xiaoqu/8705143756712036/"}, "都司堂巷44号": {"plot_name": "都司堂巷44号", "plot_url": "https://liangshan.ke.com/xiaoqu/8705143952797168/"}, "宁远巷108号": {"plot_name": "宁远巷108号", "plot_url": "https://liangshan.ke.com/xiaoqu/8705144030408103/"}, "健康路税务局": {"plot_name": "健康路税务局", "plot_url": "https://liangshan.ke.com/xiaoqu/8705144031436377/"}, "龙眼井295号": {"plot_name": "龙眼井295号", "plot_url": "https://liangshan.ke.com/xiaoqu/8705144125825835/"}, "老山厂坝4号": {"plot_name": "老山厂坝4号", "plot_url": "https://liangshan.ke.com/xiaoqu/8705144279951963/"}, "粮油公司": {"plot_name": "粮油公司", "plot_url": "https://liangshan.ke.com/xiaoqu/8705144285198418/"}, "长安村一组86号": {"plot_name": "长安村一组86号", "plot_url": "https://liangshan.ke.com/xiaoqu/8705144555882497/"}, "长安村三组": {"plot_name": "长安村三组", "plot_url": "https://liangshan.ke.com/xiaoqu/8705144608335996/"}, "龙眼井街53号": {"plot_name": "龙眼井街53号", "plot_url": "https://liangshan.ke.com/xiaoqu/8705145065511007/"}, "下西街109号": {"plot_name": "下西街109号", "plot_url": "https://liangshan.ke.com/xiaoqu/8705145291047083/"}, "西昌金信村镇银行写字楼": {"plot_name": "西昌金信村镇银行写字楼", "plot_url": "https://liangshan.ke.com/xiaoqu/8705145315167721/"}, "老统部巷41附2号": {"plot_name": "老统部巷41附2号", "plot_url": "https://liangshan.ke.com/xiaoqu/8705145770299816/"}, "长富路120附1号": {"plot_name": "长富路120附1号", "plot_url": "https://liangshan.ke.com/xiaoqu/8705146143675672/"}, "黄家巷44号": {"plot_name": "黄家巷44号", "plot_url": "https://liangshan.ke.com/xiaoqu/8705147505915450/"}, "龙辉街13附90号": {"plot_name": "龙辉街13附90号", "plot_url": "https://liangshan.ke.com/xiaoqu/8705147827910200/"}, "长安北路131号": {"plot_name": "长安北路131号", "plot_url": "https://liangshan.ke.com/xiaoqu/8705147830002106/"}, "邛海公园家属区": {"plot_name": "邛海公园家属区", "plot_url": "https://liangshan.ke.com/xiaoqu/8705148085841369/"}, "老西门街11号": {"plot_name": "老西门街11号", "plot_url": "https://liangshan.ke.com/xiaoqu/8705148607115673/"}, "联合安置小区": {"plot_name": "联合安置小区", "plot_url": "https://liangshan.ke.com/xiaoqu/8705148614479176/"}, "中国移动小区": {"plot_name": "中国移动小区", "plot_url": "https://liangshan.ke.com/xiaoqu/8705148707804004/"}, "海滨北路73号": {"plot_name": "海滨北路73号", "plot_url": "https://liangshan.ke.com/xiaoqu/8705148815816469/"}, "航天大道一段35号": {"plot_name": "航天大道一段35号", "plot_url": "https://liangshan.ke.com/xiaoqu/8705149116837423/"}, "健康路42号": {"plot_name": "健康路42号", "plot_url": "https://liangshan.ke.com/xiaoqu/8705149188163016/"}, "一环路凉山州森林公安局小区": {"plot_name": "一环路凉山州森林公安局小区", "plot_url": "https://liangshan.ke.com/xiaoqu/8705149295115558/"}, "三衙街15号": {"plot_name": "三衙街15号", "plot_url": "https://liangshan.ke.com/xiaoqu/8705149340209772/"}, "宁远桥村三组": {"plot_name": "宁远桥村三组", "plot_url": "https://liangshan.ke.com/xiaoqu/8705149563599245/"}, "西郊乡北门村七组": {"plot_name": "西郊乡北门村七组", "plot_url": "https://liangshan.ke.com/xiaoqu/8705149636992117/"}, "高枧家园": {"plot_name": "高枧家园", "plot_url": "https://liangshan.ke.com/xiaoqu/8705150090067764/"}, "吉祥路47号": {"plot_name": "吉祥路47号", "plot_url": "https://liangshan.ke.com/xiaoqu/8705150097401682/"}, "健康路综合楼": {"plot_name": "健康路综合楼", "plot_url": "https://liangshan.ke.com/xiaoqu/8705150116276848/"}, "魏家湾东巷25号": {"plot_name": "魏家湾东巷25号", "plot_url": "https://liangshan.ke.com/xiaoqu/8705150224281363/"}, "西昌市房地产建筑有限责任公司住宅区": {"plot_name": "西昌市房地产建筑有限责任公司住宅区", "plot_url": "https://liangshan.ke.com/xiaoqu/8705151250062863/"}, "鑫海国际": {"plot_name": "鑫海国际", "plot_url": "https://liangshan.ke.com/xiaoqu/8705132779241253/"}, "鹭洲·威尼斯半岛": {"plot_name": "鹭洲·威尼斯半岛", "plot_url": "https://liangshan.ke.com/xiaoqu/8705132778191151/"}, "公園2018": {"plot_name": "公園2018", "plot_url": "https://liangshan.ke.com/xiaoqu/8705132776093774/"}, "领地.凯旋国际公馆": {"plot_name": "领地.凯旋国际公馆", "plot_url": "https://liangshan.ke.com/xiaoqu/8705132787634010/"}, "彩云府": {"plot_name": "彩云府", "plot_url": "https://liangshan.ke.com/xiaoqu/8705132787635219/"}, "威尼斯B区": {"plot_name": "威尼斯B区", "plot_url": "https://liangshan.ke.com/xiaoqu/8705142017621260/"}, "盛世建昌": {"plot_name": "盛世建昌", "plot_url": "https://liangshan.ke.com/xiaoqu/8705132782388742/"}, "乐荟城·海云墅": {"plot_name": "乐荟城·海云墅", "plot_url": "https://liangshan.ke.com/xiaoqu/8705144611264801/"}, "山水阳光新城": {"plot_name": "山水阳光新城", "plot_url": "https://liangshan.ke.com/xiaoqu/8705132787633940/"}, "邛海湾·长岛": {"plot_name": "邛海湾·长岛", "plot_url": "https://liangshan.ke.com/xiaoqu/8705137028523606/"}, "合信邛海湾B区": {"plot_name": "合信邛海湾B区", "plot_url": "https://liangshan.ke.com/xiaoqu/8705145164174735/"}, "南苑钰楼": {"plot_name": "南苑钰楼", "plot_url": "https://liangshan.ke.com/xiaoqu/8705134933773499/"}, "健康小区": {"plot_name": "健康小区", "plot_url": "https://liangshan.ke.com/xiaoqu/8705134741885110/"}, "健康路公路局家属区": {"plot_name": "健康路公路局家属区", "plot_url": "https://liangshan.ke.com/xiaoqu/87050000000191/"}, "铁投·邛海壹号": {"plot_name": "铁投·邛海壹号", "plot_url": "https://liangshan.ke.com/xiaoqu/87050000001499/"}, "春生雅苑": {"plot_name": "春生雅苑", "plot_url": "https://liangshan.ke.com/xiaoqu/8705132783441933/"}, "南苑小区A区": {"plot_name": "南苑小区A区", "plot_url": "https://liangshan.ke.com/xiaoqu/8705132787633166/"}, "健康苑小区": {"plot_name": "健康苑小区", "plot_url": "https://liangshan.ke.com/xiaoqu/8705134928526351/"}, "三岔口汽车十八队": {"plot_name": "三岔口汽车十八队", "plot_url": "https://liangshan.ke.com/xiaoqu/8705134953676739/"}, "州政府大院": {"plot_name": "州政府大院", "plot_url": "https://liangshan.ke.com/xiaoqu/8705134956840813/"}, "攀西地质队南院": {"plot_name": "攀西地质队南院", "plot_url": "https://liangshan.ke.com/xiaoqu/8705136184306213/"}, "兰台府青沄": {"plot_name": "兰台府青沄", "plot_url": "https://liangshan.ke.com/xiaoqu/8705144560080904/"}, "合信邛海湾A区": {"plot_name": "合信邛海湾A区", "plot_url": "https://liangshan.ke.com/xiaoqu/8705149864620554/"}, "三岔口民政局机关大院": {"plot_name": "三岔口民政局机关大院", "plot_url": "https://liangshan.ke.com/xiaoqu/87050000000101/"}, "阳光家园B区": {"plot_name": "阳光家园B区", "plot_url": "https://liangshan.ke.com/xiaoqu/8705132782394852/"}, "金地丽都": {"plot_name": "金地丽都", "plot_url": "https://liangshan.ke.com/xiaoqu/8705132785536902/"}, "中所安置小区": {"plot_name": "中所安置小区", "plot_url": "https://liangshan.ke.com/xiaoqu/8705132788682339/"}, "尤佳小区": {"plot_name": "尤佳小区", "plot_url": "https://liangshan.ke.com/xiaoqu/8705132918706245/"}, "三岔口南路州农行家属区": {"plot_name": "三岔口南路州农行家属区", "plot_url": "https://liangshan.ke.com/xiaoqu/8705134916984098/"}, "柳树林政府小区": {"plot_name": "柳树林政府小区", "plot_url": "https://liangshan.ke.com/xiaoqu/8705134936910261/"}, "三岔口州工商局": {"plot_name": "三岔口州工商局", "plot_url": "https://liangshan.ke.com/xiaoqu/8705134947406701/"}, "凉山州经信委健康路住宅小区": {"plot_name": "凉山州经信委健康路住宅小区", "plot_url": "https://liangshan.ke.com/xiaoqu/8705134955776478/"}, "健康路州林业公司": {"plot_name": "健康路州林业公司", "plot_url": "https://liangshan.ke.com/xiaoqu/8705135007170862/"}, "健康路民航站家属区": {"plot_name": "健康路民航站家属区", "plot_url": "https://liangshan.ke.com/xiaoqu/8705135372324713/"}, "春生雅苑北区": {"plot_name": "春生雅苑北区", "plot_url": "https://liangshan.ke.com/xiaoqu/8705135424823261/"}, "卷烟厂南坛烟厂生活区": {"plot_name": "卷烟厂南坛烟厂生活区", "plot_url": "https://liangshan.ke.com/xiaoqu/8705135427975071/"}, "凉山州中西结合医院": {"plot_name": "凉山州中西结合医院", "plot_url": "https://liangshan.ke.com/xiaoqu/8705135532861130/"}, "春生雅苑西区": {"plot_name": "春生雅苑西区", "plot_url": "https://liangshan.ke.com/xiaoqu/8705135554884965/"}, "健康路质监局": {"plot_name": "健康路质监局", "plot_url": "https://liangshan.ke.com/xiaoqu/87050000000068/"}, "州委机关宿舍": {"plot_name": "州委机关宿舍", "plot_url": "https://liangshan.ke.com/xiaoqu/8705132775047341/"}, "中国银行住宅": {"plot_name": "中国银行住宅", "plot_url": "https://liangshan.ke.com/xiaoqu/8705132775048084/"}, "审计局家属小区": {"plot_name": "审计局家属小区", "plot_url": "https://liangshan.ke.com/xiaoqu/8705132776095255/"}, "龙腾小区": {"plot_name": "龙腾小区", "plot_url": "https://liangshan.ke.com/xiaoqu/8705132779251074/"}, "月都花园小区": {"plot_name": "月都花园小区", "plot_url": "https://liangshan.ke.com/xiaoqu/8705132780297029/"}, "四0四地质队顺河路生活区": {"plot_name": "四0四地质队顺河路生活区", "plot_url": "https://liangshan.ke.com/xiaoqu/8705132781345759/"}, "凉山州农机事业管理局家属院": {"plot_name": "凉山州农机事业管理局家属院", "plot_url": "https://liangshan.ke.com/xiaoqu/8705132781348110/"}, "凉山州第二人民医院二宿舍区": {"plot_name": "凉山州第二人民医院二宿舍区", "plot_url": "https://liangshan.ke.com/xiaoqu/8705132786587268/"}, "尤家屯安置小区": {"plot_name": "尤家屯安置小区", "plot_url": "https://liangshan.ke.com/xiaoqu/8705132789730971/"}, "凉山州五交化有限责任公司": {"plot_name": "凉山州五交化有限责任公司", "plot_url": "https://liangshan.ke.com/xiaoqu/8705134686293712/"}, "凉山卫生学校": {"plot_name": "凉山卫生学校", "plot_url": "https://liangshan.ke.com/xiaoqu/8705134807928960/"}, "凉山州气象家园": {"plot_name": "凉山州气象家园", "plot_url": "https://liangshan.ke.com/xiaoqu/8705134843595423/"}, "金财大厦": {"plot_name": "金财大厦", "plot_url": "https://liangshan.ke.com/xiaoqu/8705134844640994/"}, "西昌农专第二教学区": {"plot_name": "西昌农专第二教学区", "plot_url": "https://liangshan.ke.com/xiaoqu/8705134896020789/"}, "凉山彝族自治州广播电视台": {"plot_name": "凉山彝族自治州广播电视台", "plot_url": "https://liangshan.ke.com/xiaoqu/8705134918038365/"}, "喜德县驻西昌第二干休所": {"plot_name": "喜德县驻西昌第二干休所", "plot_url": "https://liangshan.ke.com/xiaoqu/8705134924317310/"}, "西昌市民政小区": {"plot_name": "西昌市民政小区", "plot_url": "https://liangshan.ke.com/xiaoqu/8705134927475308/"}, "建昌苑": {"plot_name": "建昌苑", "plot_url": "https://liangshan.ke.com/xiaoqu/8705134929571369/"}, "昭觉县教师退休所": {"plot_name": "昭觉县教师退休所", "plot_url": "https://liangshan.ke.com/xiaoqu/8705135002981907/"}, "春生苑东区": {"plot_name": "春生苑东区", "plot_url": "https://liangshan.ke.com/xiaoqu/8705135385973440/"}, "南苑小区C区": {"plot_name": "南苑小区C区", "plot_url": "https://liangshan.ke.com/xiaoqu/8705135404903760/"}, "会东办事处二区": {"plot_name": "会东办事处二区", "plot_url": "https://liangshan.ke.com/xiaoqu/8705135431107185/"}, "荣昌小区二区": {"plot_name": "荣昌小区二区", "plot_url": "https://liangshan.ke.com/xiaoqu/8705135458381041/"}, "凉山彝族自治州彝文图书馆": {"plot_name": "凉山彝族自治州彝文图书馆", "plot_url": "https://liangshan.ke.com/xiaoqu/8705135532859072/"}, "南坛小区A区": {"plot_name": "南坛小区A区", "plot_url": "https://liangshan.ke.com/xiaoqu/8705135606286011/"}, "三岔口东路51号": {"plot_name": "三岔口东路51号", "plot_url": "https://liangshan.ke.com/xiaoqu/8705135854926257/"}, "越西县二干所": {"plot_name": "越西县二干所", "plot_url": "https://liangshan.ke.com/xiaoqu/8705136110782830/"}, "凉山州中西医结合医院改善型经济适用住房": {"plot_name": "凉山州中西医结合医院改善型经济适用住房", "plot_url": "https://liangshan.ke.com/xiaoqu/8705136937320196/"}, "健康路川粮驾照家属区": {"plot_name": "健康路川粮驾照家属区", "plot_url": "https://liangshan.ke.com/xiaoqu/8705138567159022/"}, "三岔口东路百姓大药房": {"plot_name": "三岔口东路百姓大药房", "plot_url": "https://liangshan.ke.com/xiaoqu/8705138697184959/"}, "紫云台": {"plot_name": "紫云台", "plot_url": "https://liangshan.ke.com/xiaoqu/8705144612314539/"}, "邛海1号院": {"plot_name": "邛海1号院", "plot_url": "https://liangshan.ke.com/xiaoqu/8705145087589135/"}, "树高·翡丽华府": {"plot_name": "树高·翡丽华府", "plot_url": "https://liangshan.ke.com/xiaoqu/8705146292603915/"}, "健康苑": {"plot_name": "健康苑", "plot_url": "https://liangshan.ke.com/xiaoqu/87050000000008/"}, "西昌水电工程公司": {"plot_name": "西昌水电工程公司", "plot_url": "https://liangshan.ke.com/xiaoqu/87050000000092/"}, "州民政局机关大院": {"plot_name": "州民政局机关大院", "plot_url": "https://liangshan.ke.com/xiaoqu/87050000000136/"}, "新仓库变电站": {"plot_name": "新仓库变电站", "plot_url": "https://liangshan.ke.com/xiaoqu/87050000000138/"}, "交通局第二宿舍": {"plot_name": "交通局第二宿舍", "plot_url": "https://liangshan.ke.com/xiaoqu/87050000000190/"}, "南坛花园小区": {"plot_name": "南坛花园小区", "plot_url": "https://liangshan.ke.com/xiaoqu/87050000000356/"}, "三岔口东路建宁巷": {"plot_name": "三岔口东路建宁巷", "plot_url": "https://liangshan.ke.com/xiaoqu/87050000000359/"}, "春天阳光": {"plot_name": "春天阳光", "plot_url": "https://liangshan.ke.com/xiaoqu/87050000000474/"}, "西昌市农业农村局": {"plot_name": "西昌市农业农村局", "plot_url": "https://liangshan.ke.com/xiaoqu/87050000002002/"}, "第二人民医院宿舍": {"plot_name": "第二人民医院宿舍", "plot_url": "https://liangshan.ke.com/xiaoqu/8705132775047294/"}, "福乐园小区": {"plot_name": "福乐园小区", "plot_url": "https://liangshan.ke.com/xiaoqu/8705132776096112/"}, "西昌市质监局南坛家属院": {"plot_name": "西昌市质监局南坛家属院", "plot_url": "https://liangshan.ke.com/xiaoqu/8705132778192815/"}, "健康花园": {"plot_name": "健康花园", "plot_url": "https://liangshan.ke.com/xiaoqu/8705132779251184/"}, "城东教师新区": {"plot_name": "城东教师新区", "plot_url": "https://liangshan.ke.com/xiaoqu/8705132781338236/"}, "西昌市河东幸福家园": {"plot_name": "西昌市河东幸福家园", "plot_url": "https://liangshan.ke.com/xiaoqu/8705132781343799/"}, "惠民家园": {"plot_name": "惠民家园", "plot_url": "https://liangshan.ke.com/xiaoqu/8705132781345982/"}, "芳华苑": {"plot_name": "芳华苑", "plot_url": "https://liangshan.ke.com/xiaoqu/8705132781347895/"}, "南坛小区C区": {"plot_name": "南坛小区C区", "plot_url": "https://liangshan.ke.com/xiaoqu/8705132781348069/"}, "粮食小区": {"plot_name": "粮食小区", "plot_url": "https://liangshan.ke.com/xiaoqu/8705132782395676/"}, "州林业局南桥小区": {"plot_name": "州林业局南桥小区", "plot_url": "https://liangshan.ke.com/xiaoqu/8705132785532290/"}, "一环小区": {"plot_name": "一环小区", "plot_url": "https://liangshan.ke.com/xiaoqu/8705132785537747/"}, "凉山州公路管理处三号大院": {"plot_name": "凉山州公路管理处三号大院", "plot_url": "https://liangshan.ke.com/xiaoqu/8705132785537845/"}, "人民政府驻昌干部住宿小区": {"plot_name": "人民政府驻昌干部住宿小区", "plot_url": "https://liangshan.ke.com/xiaoqu/8705132786584977/"}, "新華苑": {"plot_name": "新華苑", "plot_url": "https://liangshan.ke.com/xiaoqu/8705132787633013/"}, "阳光家园A区": {"plot_name": "阳光家园A区", "plot_url": "https://liangshan.ke.com/xiaoqu/8705132789731432/"}, "西昌市林业局苗圃": {"plot_name": "西昌市林业局苗圃", "plot_url": "https://liangshan.ke.com/xiaoqu/8705132789732682/"}, "西昌红烛苑": {"plot_name": "西昌红烛苑", "plot_url": "https://liangshan.ke.com/xiaoqu/8705132791826874/"}, "南坛小区": {"plot_name": "南坛小区", "plot_url": "https://liangshan.ke.com/xiaoqu/8705134699931612/"}, "西昌市百货集团公司职工住宅(三岔口西巷)": {"plot_name": "西昌市百货集团公司职工住宅(三岔口西巷)", "plot_url": "https://liangshan.ke.com/xiaoqu/8705134725105168/"}, "州有色金属工业公司": {"plot_name": "州有色金属工业公司", "plot_url": "https://liangshan.ke.com/xiaoqu/8705134754468385/"}, "西昌市第六中学校教师保障性住房": {"plot_name": "西昌市第六中学校教师保障性住房", "plot_url": "https://liangshan.ke.com/xiaoqu/8705134772286995/"}, "南坛国土局家属区": {"plot_name": "南坛国土局家属区", "plot_url": "https://liangshan.ke.com/xiaoqu/8705134774372133/"}, "四零四地质队": {"plot_name": "四零四地质队", "plot_url": "https://liangshan.ke.com/xiaoqu/8705134843574911/"}, "美教干所": {"plot_name": "美教干所", "plot_url": "https://liangshan.ke.com/xiaoqu/8705134847775335/"}, "西昌市妇幼保健院": {"plot_name": "西昌市妇幼保健院", "plot_url": "https://liangshan.ke.com/xiaoqu/8705134854063860/"}, "南苑小区": {"plot_name": "南苑小区", "plot_url": "https://liangshan.ke.com/xiaoqu/8705134859306021/"}, "南坛发展银行": {"plot_name": "南坛发展银行", "plot_url": "https://liangshan.ke.com/xiaoqu/8705134872950894/"}, "南苑B区": {"plot_name": "南苑B区", "plot_url": "https://liangshan.ke.com/xiaoqu/8705134899170913/"}, "中国人民银行凉山州中心支行土城西路家属院": {"plot_name": "中国人民银行凉山州中心支行土城西路家属院", "plot_url": "https://liangshan.ke.com/xiaoqu/8705134901253302/"}, "凉山彝族自治州环境保护局": {"plot_name": "凉山彝族自治州环境保护局", "plot_url": "https://liangshan.ke.com/xiaoqu/8705134914896182/"}, "西昌六中": {"plot_name": "西昌六中", "plot_url": "https://liangshan.ke.com/xiaoqu/8705134915949948/"}, "健康小区农行家属区": {"plot_name": "健康小区农行家属区", "plot_url": "https://liangshan.ke.com/xiaoqu/8705134919077348/"}, "会理锌矿生活基地": {"plot_name": "会理锌矿生活基地", "plot_url": "https://liangshan.ke.com/xiaoqu/8705134922219104/"}, "南苑小区东楼": {"plot_name": "南苑小区东楼", "plot_url": "https://liangshan.ke.com/xiaoqu/8705134923266553/"}, "凉山州农牧局": {"plot_name": "凉山州农牧局", "plot_url": "https://liangshan.ke.com/xiaoqu/8705134953695282/"}, "西昌汽车东站": {"plot_name": "西昌汽车东站", "plot_url": "https://liangshan.ke.com/xiaoqu/8705134954740376/"}, "南坛国质监局": {"plot_name": "南坛国质监局", "plot_url": "https://liangshan.ke.com/xiaoqu/8705134971509380/"}, "州卫生局": {"plot_name": "州卫生局", "plot_url": "https://liangshan.ke.com/xiaoqu/8705134982007108/"}, "凉山彝族自治州食品药品监督管理局": {"plot_name": "凉山彝族自治州食品药品监督管理局", "plot_url": "https://liangshan.ke.com/xiaoqu/8705135350299089/"}, "凉山州林海公司": {"plot_name": "凉山州林海公司", "plot_url": "https://liangshan.ke.com/xiaoqu/8705135381773326/"}, "普格县驻西昌办事处": {"plot_name": "普格县驻西昌办事处", "plot_url": "https://liangshan.ke.com/xiaoqu/8705135382814128/"}, "三岔口州电力公司": {"plot_name": "三岔口州电力公司", "plot_url": "https://liangshan.ke.com/xiaoqu/8705135396507826/"}, "三岔口西巷物资局": {"plot_name": "三岔口西巷物资局", "plot_url": "https://liangshan.ke.com/xiaoqu/8705135398613019/"}, "康铜小区": {"plot_name": "康铜小区", "plot_url": "https://liangshan.ke.com/xiaoqu/8705135400717912/"}, "凉山州商业银行": {"plot_name": "凉山州商业银行", "plot_url": "https://liangshan.ke.com/xiaoqu/8705135403851270/"}, "木里藏族自治县卫生局驻昌干休所": {"plot_name": "木里藏族自治县卫生局驻昌干休所", "plot_url": "https://liangshan.ke.com/xiaoqu/8705135406999183/"}, "西昌烟草": {"plot_name": "西昌烟草", "plot_url": "https://liangshan.ke.com/xiaoqu/8705135408039808/"}, "正义路州人事局家属区": {"plot_name": "正义路州人事局家属区", "plot_url": "https://liangshan.ke.com/xiaoqu/8705135413283611/"}, "昭觉县驻西昌第二干休所": {"plot_name": "昭觉县驻西昌第二干休所", "plot_url": "https://liangshan.ke.com/xiaoqu/8705135421685551/"}, "宁南县人民政府驻西昌办事处改善型经济适用住房工程": {"plot_name": "宁南县人民政府驻西昌办事处改善型经济适用住房工程", "plot_url": "https://liangshan.ke.com/xiaoqu/8705135433204075/"}, "沿河路有色金属工业公司": {"plot_name": "沿河路有色金属工业公司", "plot_url": "https://liangshan.ke.com/xiaoqu/8705135438455253/"}, "农机公司家属区": {"plot_name": "农机公司家属区", "plot_url": "https://liangshan.ke.com/xiaoqu/8705135448944874/"}, "南坛安置小区": {"plot_name": "南坛安置小区", "plot_url": "https://liangshan.ke.com/xiaoqu/8705135495131882/"}, "新仓库国安局": {"plot_name": "新仓库国安局", "plot_url": "https://liangshan.ke.com/xiaoqu/8705135556998386/"}, "凉山州扶贫和移民工作局南坛小区": {"plot_name": "凉山州扶贫和移民工作局南坛小区", "plot_url": "https://liangshan.ke.com/xiaoqu/8705135577978423/"}, "四0四地质队土城巷十一号生活区": {"plot_name": "四0四地质队土城巷十一号生活区", "plot_url": "https://liangshan.ke.com/xiaoqu/8705135679726416/"}, "凉山彝族自治州烟草专卖局": {"plot_name": "凉山彝族自治州烟草专卖局", "plot_url": "https://liangshan.ke.com/xiaoqu/8705135779342729/"}, "美姑林卫干休所": {"plot_name": "美姑林卫干休所", "plot_url": "https://liangshan.ke.com/xiaoqu/8705136955130521/"}, "启华.金色夏威夷": {"plot_name": "启华.金色夏威夷", "plot_url": "https://liangshan.ke.com/xiaoqu/8705137343168806/"}, "三岔口东路468号": {"plot_name": "三岔口东路468号", "plot_url": "https://liangshan.ke.com/xiaoqu/8705138087810188/"}, "凉山彝族自治州公安局公路巡逻警察支队家属区": {"plot_name": "凉山彝族自治州公安局公路巡逻警察支队家属区", "plot_url": "https://liangshan.ke.com/xiaoqu/8705138239932206/"}, "美姑教师干休所": {"plot_name": "美姑教师干休所", "plot_url": "https://liangshan.ke.com/xiaoqu/8705138317518358/"}, "易智大厦": {"plot_name": "易智大厦", "plot_url": "https://liangshan.ke.com/xiaoqu/8705138445516373/"}, "东西河林场家属区": {"plot_name": "东西河林场家属区", "plot_url": "https://liangshan.ke.com/xiaoqu/8705139025567142/"}, "山海苑": {"plot_name": "山海苑", "plot_url": "https://liangshan.ke.com/xiaoqu/8705139225854729/"}, "西昌市林业和草原局": {"plot_name": "西昌市林业和草原局", "plot_url": "https://liangshan.ke.com/xiaoqu/8705139773208500/"}, "南坛路39号": {"plot_name": "南坛路39号", "plot_url": "https://liangshan.ke.com/xiaoqu/8705139948468706/"}, "四川广播电视台505发射传播台": {"plot_name": "四川广播电视台505发射传播台", "plot_url": "https://liangshan.ke.com/xiaoqu/8705140030263275/"}, "烟草家属区": {"plot_name": "烟草家属区", "plot_url": "https://liangshan.ke.com/xiaoqu/8705140587180855/"}, "高枧乡合盐路158号州检察院": {"plot_name": "高枧乡合盐路158号州检察院", "plot_url": "https://liangshan.ke.com/xiaoqu/8705140685768119/"}, "花间桃园": {"plot_name": "花间桃园", "plot_url": "https://liangshan.ke.com/xiaoqu/8705140757052174/"}, "中国工商银行家属区": {"plot_name": "中国工商银行家属区", "plot_url": "https://liangshan.ke.com/xiaoqu/8705141641166198/"}, "凉山彝族自治州经济和信息化局": {"plot_name": "凉山彝族自治州经济和信息化局", "plot_url": "https://liangshan.ke.com/xiaoqu/8705141816282679/"}, "健康路132号附8号": {"plot_name": "健康路132号附8号", "plot_url": "https://liangshan.ke.com/xiaoqu/8705142338572279/"}, "木衣汽修厂家属区": {"plot_name": "木衣汽修厂家属区", "plot_url": "https://liangshan.ke.com/xiaoqu/8705142642748784/"}, "东南街二段38号": {"plot_name": "东南街二段38号", "plot_url": "https://liangshan.ke.com/xiaoqu/8705143177710996/"}, "兴坛公司家属院": {"plot_name": "兴坛公司家属院", "plot_url": "https://liangshan.ke.com/xiaoqu/8705144152030530/"}, "西昌市农业局小区": {"plot_name": "西昌市农业局小区", "plot_url": "https://liangshan.ke.com/xiaoqu/8705144183501968/"}, "荷香苑": {"plot_name": "荷香苑", "plot_url": "https://liangshan.ke.com/xiaoqu/8705145420008974/"}, "佳禾苑": {"plot_name": "佳禾苑", "plot_url": "https://liangshan.ke.com/xiaoqu/8705146248548325/"}, "凉山州经信委家属院": {"plot_name": "凉山州经信委家属院", "plot_url": "https://liangshan.ke.com/xiaoqu/8705148385738679/"}, "三岔口西巷109号": {"plot_name": "三岔口西巷109号", "plot_url": "https://liangshan.ke.com/xiaoqu/8705148713040558/"}, "正义路23号": {"plot_name": "正义路23号", "plot_url": "https://liangshan.ke.com/xiaoqu/8705149468128421/"}, "一环路南一段141号": {"plot_name": "一环路南一段141号", "plot_url": "https://liangshan.ke.com/xiaoqu/8705149613922397/"}, "甘洛干休所": {"plot_name": "甘洛干休所", "plot_url": "https://liangshan.ke.com/xiaoqu/8705150096354687/"}, "三岔口西巷48号": {"plot_name": "三岔口西巷48号", "plot_url": "https://liangshan.ke.com/xiaoqu/8705152306094701/"}, "金厦攀星花園": {"plot_name": "金厦攀星花園", "plot_url": "https://liangshan.ke.com/xiaoqu/8705133294108610/"}, "水岸国际花城B区": {"plot_name": "水岸国际花城B区", "plot_url": "https://liangshan.ke.com/xiaoqu/8705132785536219/"}, "长安国际": {"plot_name": "长安国际", "plot_url": "https://liangshan.ke.com/xiaoqu/8705134582408988/"}, "佳信阳光": {"plot_name": "佳信阳光", "plot_url": "https://liangshan.ke.com/xiaoqu/8705132779251336/"}, "大昌小区北区": {"plot_name": "大昌小区北区", "plot_url": "https://liangshan.ke.com/xiaoqu/8705132788681986/"}, "龙眼井检察院": {"plot_name": "龙眼井检察院", "plot_url": "https://liangshan.ke.com/xiaoqu/8705134979897987/"}, "阳光城市花园": {"plot_name": "阳光城市花园", "plot_url": "https://liangshan.ke.com/xiaoqu/8705132772948249/"}, "鑫海花園": {"plot_name": "鑫海花園", "plot_url": "https://liangshan.ke.com/xiaoqu/8705132784494000/"}, "达达春天百货": {"plot_name": "达达春天百货", "plot_url": "https://liangshan.ke.com/xiaoqu/87050000000006/"}, "琦洋名都": {"plot_name": "琦洋名都", "plot_url": "https://liangshan.ke.com/xiaoqu/8705132771903077/"}, "华电苑": {"plot_name": "华电苑", "plot_url": "https://liangshan.ke.com/xiaoqu/8705132772949824/"}, "金龙家园": {"plot_name": "金龙家园", "plot_url": "https://liangshan.ke.com/xiaoqu/8705134572012839/"}, "紫薇星座": {"plot_name": "紫薇星座", "plot_url": "https://liangshan.ke.com/xiaoqu/8705134595076700/"}, "帝皇公馆": {"plot_name": "帝皇公馆", "plot_url": "https://liangshan.ke.com/xiaoqu/8705134782780907/"}, "星光苑A区": {"plot_name": "星光苑A区", "plot_url": "https://liangshan.ke.com/xiaoqu/8705135502449395/"}, "名店街交通局": {"plot_name": "名店街交通局", "plot_url": "https://liangshan.ke.com/xiaoqu/87050000000004/"}, "西郊信用社商住楼": {"plot_name": "西郊信用社商住楼", "plot_url": "https://liangshan.ke.com/xiaoqu/87050000000053/"}, "文汇路一小区": {"plot_name": "文汇路一小区", "plot_url": "https://liangshan.ke.com/xiaoqu/8705132764545300/"}, "庆华景城": {"plot_name": "庆华景城", "plot_url": "https://liangshan.ke.com/xiaoqu/8705132772948376/"}, "水岸国际花城A区": {"plot_name": "水岸国际花城A区", "plot_url": "https://liangshan.ke.com/xiaoqu/8705132778191121/"}, "金地华府": {"plot_name": "金地华府", "plot_url": "https://liangshan.ke.com/xiaoqu/8705134572011665/"}, "时代广场": {"plot_name": "时代广场", "plot_url": "https://liangshan.ke.com/xiaoqu/8705134735579221/"}, "大成空中花园": {"plot_name": "大成空中花园", "plot_url": "https://liangshan.ke.com/xiaoqu/8705134858259002/"}, "州教育局": {"plot_name": "州教育局", "plot_url": "https://liangshan.ke.com/xiaoqu/8705135382817536/"}, "市农行家属区": {"plot_name": "市农行家属区", "plot_url": "https://liangshan.ke.com/xiaoqu/8705135431127828/"}, "凉山彝族自治州城乡规划建设和住房保障局": {"plot_name": "凉山彝族自治州城乡规划建设和住房保障局", "plot_url": "https://liangshan.ke.com/xiaoqu/8705135773059188/"}, "西运小区": {"plot_name": "西运小区", "plot_url": "https://liangshan.ke.com/xiaoqu/87050000000002/"}, "凉山彝族自治州毛牛山广播电视转播台": {"plot_name": "凉山彝族自治州毛牛山广播电视转播台", "plot_url": "https://liangshan.ke.com/xiaoqu/87050000000020/"}, "楠桦大厦": {"plot_name": "楠桦大厦", "plot_url": "https://liangshan.ke.com/xiaoqu/87050000000028/"}, "大成商业广场": {"plot_name": "大成商业广场", "plot_url": "https://liangshan.ke.com/xiaoqu/87050000000056/"}, "同德建司": {"plot_name": "同德建司", "plot_url": "https://liangshan.ke.com/xiaoqu/87050000000061/"}, "乾隆大厦": {"plot_name": "乾隆大厦", "plot_url": "https://liangshan.ke.com/xiaoqu/87050000000116/"}, "会东地税局": {"plot_name": "会东地税局", "plot_url": "https://liangshan.ke.com/xiaoqu/87050000000126/"}, "茗居园": {"plot_name": "茗居园", "plot_url": "https://liangshan.ke.com/xiaoqu/8705132772950809/"}, "铁路家园": {"plot_name": "铁路家园", "plot_url": "https://liangshan.ke.com/xiaoqu/8705132775047661/"}, "安宁小区": {"plot_name": "安宁小区", "plot_url": "https://liangshan.ke.com/xiaoqu/8705132777151614/"}, "宁远巷住宅小区": {"plot_name": "宁远巷住宅小区", "plot_url": "https://liangshan.ke.com/xiaoqu/8705132777154220/"}, "大昌小区南村": {"plot_name": "大昌小区南村", "plot_url": "https://liangshan.ke.com/xiaoqu/8705132781341092/"}, "光彩·城市风景小区": {"plot_name": "光彩·城市风景小区", "plot_url": "https://liangshan.ke.com/xiaoqu/8705132782385478/"}, "邮政苑": {"plot_name": "邮政苑", "plot_url": "https://liangshan.ke.com/xiaoqu/8705132783439511/"}, "龙旺": {"plot_name": "龙旺", "plot_url": "https://liangshan.ke.com/xiaoqu/8705134857228524/"}, "人和公寓": {"plot_name": "人和公寓", "plot_url": "https://liangshan.ke.com/xiaoqu/8705134862467457/"}, "航天路小区东区": {"plot_name": "航天路小区东区", "plot_url": "https://liangshan.ke.com/xiaoqu/8705134867710222/"}, "鑫海小区": {"plot_name": "鑫海小区", "plot_url": "https://liangshan.ke.com/xiaoqu/8705134892874956/"}, "文汇北路州建行": {"plot_name": "文汇北路州建行", "plot_url": "https://liangshan.ke.com/xiaoqu/8705134897057519/"}, "长安中路州建设三处": {"plot_name": "长安中路州建设三处", "plot_url": "https://liangshan.ke.com/xiaoqu/8705134922218720/"}, "楠华商厦小区": {"plot_name": "楠华商厦小区", "plot_url": "https://liangshan.ke.com/xiaoqu/8705134958925349/"}, "党校建行家属区": {"plot_name": "党校建行家属区", "plot_url": "https://liangshan.ke.com/xiaoqu/8705135002981204/"}, "越西县驻西昌干休所": {"plot_name": "越西县驻西昌干休所", "plot_url": "https://liangshan.ke.com/xiaoqu/8705135385971354/"}, "凉山彝文教材编译室": {"plot_name": "凉山彝文教材编译室", "plot_url": "https://liangshan.ke.com/xiaoqu/8705135419574577/"}, "凉钢干休所": {"plot_name": "凉钢干休所", "plot_url": "https://liangshan.ke.com/xiaoqu/8705135490931013/"}, "一医院家属区": {"plot_name": "一医院家属区", "plot_url": "https://liangshan.ke.com/xiaoqu/8705135502458739/"}, "长安中路43号": {"plot_name": "长安中路43号", "plot_url": "https://liangshan.ke.com/xiaoqu/8705136248262433/"}, "西昌市粮食局住宅楼": {"plot_name": "西昌市粮食局住宅楼", "plot_url": "https://liangshan.ke.com/xiaoqu/8705136309129086/"}, "凉山州蔬菜公司": {"plot_name": "凉山州蔬菜公司", "plot_url": "https://liangshan.ke.com/xiaoqu/8705137284398878/"}, "农行小区": {"plot_name": "农行小区", "plot_url": "https://liangshan.ke.com/xiaoqu/87050000000005/"}, "胜利北路医药公司": {"plot_name": "胜利北路医药公司", "plot_url": "https://liangshan.ke.com/xiaoqu/87050000000072/"}, "二轻公司": {"plot_name": "二轻公司", "plot_url": "https://liangshan.ke.com/xiaoqu/87050000000086/"}, "州食品公司家属区": {"plot_name": "州食品公司家属区", "plot_url": "https://liangshan.ke.com/xiaoqu/87050000000088/"}, "变压器厂": {"plot_name": "变压器厂", "plot_url": "https://liangshan.ke.com/xiaoqu/87050000000108/"}, "梨园巷宁南糖厂干休所": {"plot_name": "梨园巷宁南糖厂干休所", "plot_url": "https://liangshan.ke.com/xiaoqu/87050000000118/"}, "阳光公司": {"plot_name": "阳光公司", "plot_url": "https://liangshan.ke.com/xiaoqu/87050000000124/"}, "糖酒大楼": {"plot_name": "糖酒大楼", "plot_url": "https://liangshan.ke.com/xiaoqu/87050000000125/"}, "西昌市下西街个体大厦": {"plot_name": "西昌市下西街个体大厦", "plot_url": "https://liangshan.ke.com/xiaoqu/87050000000131/"}, "矿业公司": {"plot_name": "矿业公司", "plot_url": "https://liangshan.ke.com/xiaoqu/87050000000154/"}, "鑫森府邸": {"plot_name": "鑫森府邸", "plot_url": "https://liangshan.ke.com/xiaoqu/87050000000187/"}, "市工商局宿舍": {"plot_name": "市工商局宿舍", "plot_url": "https://liangshan.ke.com/xiaoqu/87050000000189/"}, "西昌饭店家属区": {"plot_name": "西昌饭店家属区", "plot_url": "https://liangshan.ke.com/xiaoqu/87050000000203/"}, "城南大道B-9综合楼": {"plot_name": "城南大道B-9综合楼", "plot_url": "https://liangshan.ke.com/xiaoqu/87050000000208/"}, "胜利路72号": {"plot_name": "胜利路72号", "plot_url": "https://liangshan.ke.com/xiaoqu/87050000000575/"}, "驰骋汽贸住宅区": {"plot_name": "驰骋汽贸住宅区", "plot_url": "https://liangshan.ke.com/xiaoqu/87050000001309/"}, "西门坡街45号": {"plot_name": "西门坡街45号", "plot_url": "https://liangshan.ke.com/xiaoqu/87050000001330/"}, "胜利路99号凉山州农资公司宿舍": {"plot_name": "胜利路99号凉山州农资公司宿舍", "plot_url": "https://liangshan.ke.com/xiaoqu/87050000001351/"}, "下顺城街5号": {"plot_name": "下顺城街5号", "plot_url": "https://liangshan.ke.com/xiaoqu/87050000001383/"}, "马水河经信局": {"plot_name": "马水河经信局", "plot_url": "https://liangshan.ke.com/xiaoqu/87050000001944/"}, "龙辉街13附205": {"plot_name": "龙辉街13附205", "plot_url": "https://liangshan.ke.com/xiaoqu/87050000002012/"}, "文汇二区": {"plot_name": "文汇二区", "plot_url": "https://liangshan.ke.com/xiaoqu/8705132772951424/"}, "人和苑": {"plot_name": "人和苑", "plot_url": "https://liangshan.ke.com/xiaoqu/8705132775046239/"}, "卷烟厂胜利东路生活区": {"plot_name": "卷烟厂胜利东路生活区", "plot_url": "https://liangshan.ke.com/xiaoqu/8705132775046629/"}, "西昌绸厂住宿区": {"plot_name": "西昌绸厂住宿区", "plot_url": "https://liangshan.ke.com/xiaoqu/8705132778202440/"}, "胜利小区A区": {"plot_name": "胜利小区A区", "plot_url": "https://liangshan.ke.com/xiaoqu/8705132780297977/"}, "梨园巷凉山州金属材料公司宿舍": {"plot_name": "梨园巷凉山州金属材料公司宿舍", "plot_url": "https://liangshan.ke.com/xiaoqu/8705132782392616/"}, "长安中路小区": {"plot_name": "长安中路小区", "plot_url": "https://liangshan.ke.com/xiaoqu/8705132783439512/"}, "鑫海苑": {"plot_name": "鑫海苑", "plot_url": "https://liangshan.ke.com/xiaoqu/8705134753415981/"}, "凉山水务": {"plot_name": "凉山水务", "plot_url": "https://liangshan.ke.com/xiaoqu/8705134859321855/"}, "名店街邮政局": {"plot_name": "名店街邮政局", "plot_url": "https://liangshan.ke.com/xiaoqu/8705134863504653/"}, "木里教育干休所": {"plot_name": "木里教育干休所", "plot_url": "https://liangshan.ke.com/xiaoqu/8705134894956208/"}, "凉山广播电视大学": {"plot_name": "凉山广播电视大学", "plot_url": "https://liangshan.ke.com/xiaoqu/8705134936913445/"}, "凉山州农科所": {"plot_name": "凉山州农科所", "plot_url": "https://liangshan.ke.com/xiaoqu/8705134941109744/"}, "281皮防站": {"plot_name": "281皮防站", "plot_url": "https://liangshan.ke.com/xiaoqu/8705134942157973/"}, "州民中初中部": {"plot_name": "州民中初中部", "plot_url": "https://liangshan.ke.com/xiaoqu/8705134948446046/"}, "顺兴楼商务公寓": {"plot_name": "顺兴楼商务公寓", "plot_url": "https://liangshan.ke.com/xiaoqu/8705134955775954/"}, "汇宁小区A幢": {"plot_name": "汇宁小区A幢", "plot_url": "https://liangshan.ke.com/xiaoqu/8705134961019542/"}, "大成物资局": {"plot_name": "大成物资局", "plot_url": "https://liangshan.ke.com/xiaoqu/8705134962070121/"}, "农科路药材公司": {"plot_name": "农科路药材公司", "plot_url": "https://liangshan.ke.com/xiaoqu/8705134970459763/"}, "凉山州经委44号胜利东路住宅小区": {"plot_name": "凉山州经委44号胜利东路住宅小区", "plot_url": "https://liangshan.ke.com/xiaoqu/8705134997721125/"}, "杨天药业": {"plot_name": "杨天药业", "plot_url": "https://liangshan.ke.com/xiaoqu/8705135001909974/"}, "糖酒公司": {"plot_name": "糖酒公司", "plot_url": "https://liangshan.ke.com/xiaoqu/8705135055409725/"}, "西昌轻工机械厂生活区东区": {"plot_name": "西昌轻工机械厂生活区东区", "plot_url": "https://liangshan.ke.com/xiaoqu/8705135057507401/"}, "房管局家属区": {"plot_name": "房管局家属区", "plot_url": "https://liangshan.ke.com/xiaoqu/8705135144700848/"}, "凉山州水利电力勘测设计研究院": {"plot_name": "凉山州水利电力勘测设计研究院", "plot_url": "https://liangshan.ke.com/xiaoqu/8705135153100912/"}, "开发办住宅小区": {"plot_name": "开发办住宅小区", "plot_url": "https://liangshan.ke.com/xiaoqu/8705135350299184/"}, "西昌市卫生和计划生育局": {"plot_name": "西昌市卫生和计划生育局", "plot_url": "https://liangshan.ke.com/xiaoqu/8705135352398282/"}, "农机局家属区": {"plot_name": "农机局家属区", "plot_url": "https://liangshan.ke.com/xiaoqu/8705135356599840/"}, "幸福家园": {"plot_name": "幸福家园", "plot_url": "https://liangshan.ke.com/xiaoqu/8705135369188304/"}, "凉山彝族自治州妇幼保健院": {"plot_name": "凉山彝族自治州妇幼保健院", "plot_url": "https://liangshan.ke.com/xiaoqu/8705135371288091/"}, "汇宁小区B区": {"plot_name": "汇宁小区B区", "plot_url": "https://liangshan.ke.com/xiaoqu/8705135377568812/"}, "西门坡建行": {"plot_name": "西门坡建行", "plot_url": "https://liangshan.ke.com/xiaoqu/8705135380710458/"}, "林产品公司": {"plot_name": "林产品公司", "plot_url": "https://liangshan.ke.com/xiaoqu/8705135387008766/"}, "凉山州公路运输管理处": {"plot_name": "凉山州公路运输管理处", "plot_url": "https://liangshan.ke.com/xiaoqu/8705135408042676/"}, "长安中路小区盐业公司": {"plot_name": "长安中路小区盐业公司", "plot_url": "https://liangshan.ke.com/xiaoqu/8705135425872353/"}, "水文站小区": {"plot_name": "水文站小区", "plot_url": "https://liangshan.ke.com/xiaoqu/8705135445801066/"}, "胜利路石油公司": {"plot_name": "胜利路石油公司", "plot_url": "https://liangshan.ke.com/xiaoqu/8705135485673582/"}, "吉祥路冷冻厂": {"plot_name": "吉祥路冷冻厂", "plot_url": "https://liangshan.ke.com/xiaoqu/8705135489871825/"}, "航天路北路盐源干休所": {"plot_name": "航天路北路盐源干休所", "plot_url": "https://liangshan.ke.com/xiaoqu/8705135604195887/"}, "文汇路商业银行小区": {"plot_name": "文汇路商业银行小区", "plot_url": "https://liangshan.ke.com/xiaoqu/8705135770951461/"}, "州建筑公司": {"plot_name": "州建筑公司", "plot_url": "https://liangshan.ke.com/xiaoqu/8705135848656680/"}, "长安小车厂": {"plot_name": "长安小车厂", "plot_url": "https://liangshan.ke.com/xiaoqu/8705135989957351/"}, "汽车十九队家属区": {"plot_name": "汽车十九队家属区", "plot_url": "https://liangshan.ke.com/xiaoqu/8705136124535215/"}, "凉山州西昌轻工机械厂生活区西区": {"plot_name": "凉山州西昌轻工机械厂生活区西区", "plot_url": "https://liangshan.ke.com/xiaoqu/8705136664686880/"}, "长安中路338号": {"plot_name": "长安中路338号", "plot_url": "https://liangshan.ke.com/xiaoqu/8705136912132877/"}, "西昌市干休所": {"plot_name": "西昌市干休所", "plot_url": "https://liangshan.ke.com/xiaoqu/8705137113474754/"}, "中医院住宅家属区": {"plot_name": "中医院住宅家属区", "plot_url": "https://liangshan.ke.com/xiaoqu/8705137186861846/"}, "龙眼井州房管局家属区": {"plot_name": "龙眼井州房管局家属区", "plot_url": "https://liangshan.ke.com/xiaoqu/8705137312704176/"}, "张家屯巷": {"plot_name": "张家屯巷", "plot_url": "https://liangshan.ke.com/xiaoqu/8705137485831107/"}, "上西街": {"plot_name": "上西街", "plot_url": "https://liangshan.ke.com/xiaoqu/8705137688305763/"}, "西昌特种钢管厂": {"plot_name": "西昌特种钢管厂", "plot_url": "https://liangshan.ke.com/xiaoqu/8705138590217108/"}, "凉山州昭觉县农行干休所": {"plot_name": "凉山州昭觉县农行干休所", "plot_url": "https://liangshan.ke.com/xiaoqu/8705139023462234/"}, "西昌市大巷口商场职工住宅": {"plot_name": "西昌市大巷口商场职工住宅", "plot_url": "https://liangshan.ke.com/xiaoqu/8705139127292514/"}, "普格县教体局干休所": {"plot_name": "普格县教体局干休所", "plot_url": "https://liangshan.ke.com/xiaoqu/8705139223741343/"}, "新市场小区": {"plot_name": "新市场小区", "plot_url": "https://liangshan.ke.com/xiaoqu/8705139420878864/"}, "西昌市纪委监委": {"plot_name": "西昌市纪委监委", "plot_url": "https://liangshan.ke.com/xiaoqu/8705139600184044/"}, "中医药材宿舍公司": {"plot_name": "中医药材宿舍公司", "plot_url": "https://liangshan.ke.com/xiaoqu/8705139625359606/"}, "平川铁矿驻西昌办事处": {"plot_name": "平川铁矿驻西昌办事处", "plot_url": "https://liangshan.ke.com/xiaoqu/8705140525216397/"}, "马水河街71号": {"plot_name": "马水河街71号", "plot_url": "https://liangshan.ke.com/xiaoqu/8705140983546717/"}, "四川路径矿业咨询有限责任公司": {"plot_name": "四川路径矿业咨询有限责任公司", "plot_url": "https://liangshan.ke.com/xiaoqu/8705142016552994/"}, "马水河街39号": {"plot_name": "马水河街39号", "plot_url": "https://liangshan.ke.com/xiaoqu/8705142944852306/"}, "胜利南路财政局住宿楼": {"plot_name": "胜利南路财政局住宿楼", "plot_url": "https://liangshan.ke.com/xiaoqu/8705144709012013/"}, "胜利南路209号": {"plot_name": "胜利南路209号", "plot_url": "https://liangshan.ke.com/xiaoqu/8705146046160952/"}, "建工大厦": {"plot_name": "建工大厦", "plot_url": "https://liangshan.ke.com/xiaoqu/8705148304995479/"}, "下马水河街": {"plot_name": "下马水河街", "plot_url": "https://liangshan.ke.com/xiaoqu/8705148833642415/"}, "龙眼井街73号": {"plot_name": "龙眼井街73号", "plot_url": "https://liangshan.ke.com/xiaoqu/8705149639108200/"}, "龙眼井街81号": {"plot_name": "龙眼井街81号", "plot_url": "https://liangshan.ke.com/xiaoqu/8705149640151364/"}, "胜利路99号": {"plot_name": "胜利路99号", "plot_url": "https://liangshan.ke.com/xiaoqu/8705149644338090/"}, "商业街三段74附5号": {"plot_name": "商业街三段74附5号", "plot_url": "https://liangshan.ke.com/xiaoqu/8705151000399179/"}, "张家屯巷55附11号": {"plot_name": "张家屯巷55附11号", "plot_url": "https://liangshan.ke.com/xiaoqu/8705151428367762/"}, "天一楼": {"plot_name": "天一楼", "plot_url": "https://liangshan.ke.com/xiaoqu/8705151602443635/"}, "金色极地": {"plot_name": "金色极地", "plot_url": "https://liangshan.ke.com/xiaoqu/8705132792875878/"}, "月城丽景二期": {"plot_name": "月城丽景二期", "plot_url": "https://liangshan.ke.com/xiaoqu/8705132778192895/"}, "邦泰花园城": {"plot_name": "邦泰花园城", "plot_url": "https://liangshan.ke.com/xiaoqu/87050000001370/"}, "西部新城幸福家园小区": {"plot_name": "西部新城幸福家园小区", "plot_url": "https://liangshan.ke.com/xiaoqu/8705135413289544/"}, "蓝润.春风九里": {"plot_name": "蓝润.春风九里", "plot_url": "https://liangshan.ke.com/xiaoqu/8705144611267965/"}, "正黄金色学府": {"plot_name": "正黄金色学府", "plot_url": "https://liangshan.ke.com/xiaoqu/8705145845821909/"}, "德馨苑": {"plot_name": "德馨苑", "plot_url": "https://liangshan.ke.com/xiaoqu/8705132777145614/"}, "青林㭎国企小区": {"plot_name": "青林㭎国企小区", "plot_url": "https://liangshan.ke.com/xiaoqu/8705140258877086/"}, "桂苑": {"plot_name": "桂苑", "plot_url": "https://liangshan.ke.com/xiaoqu/87050000000591/"}, "攀西国际商贸城": {"plot_name": "攀西国际商贸城", "plot_url": "https://liangshan.ke.com/xiaoqu/87050000000992/"}, "阳光城文澜府": {"plot_name": "阳光城文澜府", "plot_url": "https://liangshan.ke.com/xiaoqu/8705140035484556/"}, "青㭎林国企小区": {"plot_name": "青㭎林国企小区", "plot_url": "https://liangshan.ke.com/xiaoqu/8705140478025024/"}, "华弹糖厂": {"plot_name": "华弹糖厂", "plot_url": "https://liangshan.ke.com/xiaoqu/8705142116170716/"}, "邦泰花熙府": {"plot_name": "邦泰花熙府", "plot_url": "https://liangshan.ke.com/xiaoqu/8705146165715743/"}, "攀西春天": {"plot_name": "攀西春天", "plot_url": "https://liangshan.ke.com/xiaoqu/8705147784884503/"}}