{"甘露园西里": {"plot_name": "甘露园西里", "plot_url": "/xiaoqu/249750.html"}, "盛地雅正": {"plot_name": "盛地雅正", "plot_url": "/xiaoqu/249417.html"}, "花家地北里": {"plot_name": "花家地北里", "plot_url": "/xiaoqu/249309.html"}, "金福家园": {"plot_name": "金福家园", "plot_url": "/xiaoqu/248872.html"}, "中广宜景湾": {"plot_name": "中广宜景湾", "plot_url": "/xiaoqu/248704.html"}, "新华联丽景": {"plot_name": "新华联丽景", "plot_url": "/xiaoqu/248635.html"}, "富贵名苑": {"plot_name": "富贵名苑", "plot_url": "/xiaoqu/248382.html"}, "润泽公馆": {"plot_name": "润泽公馆", "plot_url": "/xiaoqu/247998.html"}, "劲松八区": {"plot_name": "劲松八区", "plot_url": "/xiaoqu/247942.html"}, "惠新西街甲15号院": {"plot_name": "惠新西街甲15号院", "plot_url": "/xiaoqu/247828.html"}, "朝青知筑": {"plot_name": "朝青知筑", "plot_url": "/xiaoqu/247650.html"}, "望京新城": {"plot_name": "望京新城", "plot_url": "/xiaoqu/247438.html"}, "长岛澜桥": {"plot_name": "长岛澜桥", "plot_url": "/xiaoqu/247008.html"}, "省中行小区": {"plot_name": "省中行小区", "plot_url": "/xiaoqu/246938.html"}, "豪威嘉园": {"plot_name": "豪威嘉园", "plot_url": "/xiaoqu/246754.html"}, "御翠湾(别墅)": {"plot_name": "御翠湾(别墅)", "plot_url": "/xiaoqu/246643.html"}, "外馆东街50号院": {"plot_name": "外馆东街50号院", "plot_url": "/xiaoqu/246558.html"}, "筑华年": {"plot_name": "筑华年", "plot_url": "/xiaoqu/246135.html"}, "首开琅樾": {"plot_name": "首开琅樾", "plot_url": "/xiaoqu/246129.html"}, "世纪东方嘉园(南区)": {"plot_name": "世纪东方嘉园(南区)", "plot_url": "/xiaoqu/246116.html"}, "新时尚花园": {"plot_name": "新时尚花园", "plot_url": "/xiaoqu/245937.html"}, "安慧里一区": {"plot_name": "安慧里一区", "plot_url": "/xiaoqu/245644.html"}, "农光南路小区": {"plot_name": "农光南路小区", "plot_url": "/xiaoqu/245145.html"}, "小黄庄前街13号院": {"plot_name": "小黄庄前街13号院", "plot_url": "/xiaoqu/244916.html"}, "新城国际公寓二期雯园": {"plot_name": "新城国际公寓二期雯园", "plot_url": "/xiaoqu/244853.html"}, "北花园小区(1号院)": {"plot_name": "北花园小区(1号院)", "plot_url": "/xiaoqu/244851.html"}, "酒仙桥七街坊": {"plot_name": "酒仙桥七街坊", "plot_url": "/xiaoqu/244790.html"}, "厂坡小区": {"plot_name": "厂坡小区", "plot_url": "/xiaoqu/244772.html"}, "绣菊园北区": {"plot_name": "绣菊园北区", "plot_url": "/xiaoqu/244227.html"}, "慧谷阳光": {"plot_name": "慧谷阳光", "plot_url": "/xiaoqu/244147.html"}, "793厂宿舍": {"plot_name": "793厂宿舍", "plot_url": "/xiaoqu/244045.html"}, "朝外外交部宿舍": {"plot_name": "朝外外交部宿舍", "plot_url": "/xiaoqu/243915.html"}, "双桥温泉东里小区北区": {"plot_name": "双桥温泉东里小区北区", "plot_url": "/xiaoqu/243413.html"}, "甜水园东里": {"plot_name": "甜水园东里", "plot_url": "/xiaoqu/243336.html"}, "苹果社区(南区)": {"plot_name": "苹果社区(南区)", "plot_url": "/xiaoqu/243088.html"}, "劲松九区": {"plot_name": "劲松九区", "plot_url": "/xiaoqu/243019.html"}, "CLASS果岭里": {"plot_name": "CLASS果岭里", "plot_url": "/xiaoqu/242472.html"}, "圣馨家园": {"plot_name": "圣馨家园", "plot_url": "/xiaoqu/242349.html"}, "大山子西里": {"plot_name": "大山子西里", "plot_url": "/xiaoqu/242224.html"}, "东直门外斜街8号院": {"plot_name": "东直门外斜街8号院", "plot_url": "/xiaoqu/242075.html"}, "嘉铭园": {"plot_name": "嘉铭园", "plot_url": "/xiaoqu/241861.html"}, "京旺家园四区": {"plot_name": "京旺家园四区", "plot_url": "/xiaoqu/241844.html"}, "爱这城一期": {"plot_name": "爱这城一期", "plot_url": "/xiaoqu/241404.html"}, "八里庄南里小区": {"plot_name": "八里庄南里小区", "plot_url": "/xiaoqu/241336.html"}, "霞光里35号院": {"plot_name": "霞光里35号院", "plot_url": "/xiaoqu/240974.html"}, "US联邦公寓": {"plot_name": "US联邦公寓", "plot_url": "/xiaoqu/240516.html"}, "万红里甲31号院": {"plot_name": "万红里甲31号院", "plot_url": "/xiaoqu/240232.html"}, "团结湖三四条小区": {"plot_name": "团结湖三四条小区", "plot_url": "/xiaoqu/240109.html"}, "酒仙桥五街坊": {"plot_name": "酒仙桥五街坊", "plot_url": "/xiaoqu/239901.html"}, "御辰上院": {"plot_name": "御辰上院", "plot_url": "/xiaoqu/239425.html"}, "安贞西里三区": {"plot_name": "安贞西里三区", "plot_url": "/xiaoqu/239141.html"}, "华腾国际": {"plot_name": "华腾国际", "plot_url": "/xiaoqu/238265.html"}, "平乐园小区": {"plot_name": "平乐园小区", "plot_url": "/xiaoqu/237867.html"}, "绿丰家园": {"plot_name": "绿丰家园", "plot_url": "/xiaoqu/237745.html"}, "酒仙桥十二街坊": {"plot_name": "酒仙桥十二街坊", "plot_url": "/xiaoqu/237590.html"}, "甘露园小区": {"plot_name": "甘露园小区", "plot_url": "/xiaoqu/237588.html"}, "富力又一城A区": {"plot_name": "富力又一城A区", "plot_url": "/xiaoqu/237576.html"}, "北京财富中心公寓": {"plot_name": "北京财富中心公寓", "plot_url": "/xiaoqu/237528.html"}, "安慧北里小区": {"plot_name": "安慧北里小区", "plot_url": "/xiaoqu/237049.html"}, "广渠金茂府西区": {"plot_name": "广渠金茂府西区", "plot_url": "/xiaoqu/236993.html"}, "紫庐": {"plot_name": "紫庐", "plot_url": "/xiaoqu/236981.html"}, "朗庭大厦": {"plot_name": "朗庭大厦", "plot_url": "/xiaoqu/234738.html"}, "泓鑫家园": {"plot_name": "泓鑫家园", "plot_url": "/xiaoqu/233749.html"}, "海航荣御": {"plot_name": "海航荣御", "plot_url": "/xiaoqu/233282.html"}, "安苑里": {"plot_name": "安苑里", "plot_url": "/xiaoqu/232947.html"}, "朝丰家园(6号院)": {"plot_name": "朝丰家园(6号院)", "plot_url": "/xiaoqu/232514.html"}, "立水桥北里": {"plot_name": "立水桥北里", "plot_url": "/xiaoqu/231611.html"}, "海华堂": {"plot_name": "海华堂", "plot_url": "/xiaoqu/231533.html"}, "名人公寓": {"plot_name": "名人公寓", "plot_url": "/xiaoqu/231530.html"}, "光辉南里小区": {"plot_name": "光辉南里小区", "plot_url": "/xiaoqu/231406.html"}, "绿雅阁": {"plot_name": "绿雅阁", "plot_url": "/xiaoqu/231383.html"}, "盛嘉新城": {"plot_name": "盛嘉新城", "plot_url": "/xiaoqu/231363.html"}, "双柳巷小区": {"plot_name": "双柳巷小区", "plot_url": "/xiaoqu/231239.html"}, "东直门外大街24号小区": {"plot_name": "东直门外大街24号小区", "plot_url": "/xiaoqu/230600.html"}, "建外三道街小区": {"plot_name": "建外三道街小区", "plot_url": "/xiaoqu/230283.html"}, "北花园小区(2号院)": {"plot_name": "北花园小区(2号院)", "plot_url": "/xiaoqu/229793.html"}, "益田硅谷新城": {"plot_name": "益田硅谷新城", "plot_url": "/xiaoqu/229622.html"}, "后现代城B区": {"plot_name": "后现代城B区", "plot_url": "/xiaoqu/229546.html"}, "金泰丽富嘉园(30号院)": {"plot_name": "金泰丽富嘉园(30号院)", "plot_url": "/xiaoqu/228526.html"}, "都市经典家园": {"plot_name": "都市经典家园", "plot_url": "/xiaoqu/228095.html"}, "左家庄三区": {"plot_name": "左家庄三区", "plot_url": "/xiaoqu/227677.html"}, "红庙北里": {"plot_name": "红庙北里", "plot_url": "/xiaoqu/227661.html"}, "双合南街2号院": {"plot_name": "双合南街2号院", "plot_url": "/xiaoqu/227076.html"}, "澳海澜苑": {"plot_name": "澳海澜苑", "plot_url": "/xiaoqu/227018.html"}, "酒仙桥路7号院": {"plot_name": "酒仙桥路7号院", "plot_url": "/xiaoqu/226858.html"}, "双惠苑": {"plot_name": "双惠苑", "plot_url": "/xiaoqu/226853.html"}, "甘露西园": {"plot_name": "甘露西园", "plot_url": "/xiaoqu/226849.html"}, "管庄新村": {"plot_name": "管庄新村", "plot_url": "/xiaoqu/226765.html"}, "世茂奥临花园": {"plot_name": "世茂奥临花园", "plot_url": "/xiaoqu/226217.html"}, "团结湖南三条小区": {"plot_name": "团结湖南三条小区", "plot_url": "/xiaoqu/226201.html"}, "北京中佰公寓(传媒大学店)": {"plot_name": "北京中佰公寓(传媒大学店)", "plot_url": "/xiaoqu/225978.html"}, "邮电学院家属楼": {"plot_name": "邮电学院家属楼", "plot_url": "/xiaoqu/225908.html"}, "甘露园南里一区": {"plot_name": "甘露园南里一区", "plot_url": "/xiaoqu/225745.html"}, "澳洲康都": {"plot_name": "澳洲康都", "plot_url": "/xiaoqu/225722.html"}, "大地文苑": {"plot_name": "大地文苑", "plot_url": "/xiaoqu/225713.html"}, "旺座中心(商住楼)": {"plot_name": "旺座中心(商住楼)", "plot_url": "/xiaoqu/224818.html"}, "垡头南里": {"plot_name": "垡头南里", "plot_url": "/xiaoqu/224361.html"}, "北京市电机总厂": {"plot_name": "北京市电机总厂", "plot_url": "/xiaoqu/224182.html"}, "阳光飘亮广场": {"plot_name": "阳光飘亮广场", "plot_url": "/xiaoqu/224104.html"}, "北苑路3号院": {"plot_name": "北苑路3号院", "plot_url": "/xiaoqu/223960.html"}, "富苑盛世城": {"plot_name": "富苑盛世城", "plot_url": "/xiaoqu/223645.html"}, "东山墅": {"plot_name": "东山墅", "plot_url": "/xiaoqu/223632.html"}, "亮马桥外交公寓B区": {"plot_name": "亮马桥外交公寓B区", "plot_url": "/xiaoqu/223567.html"}, "丽都职工宿舍": {"plot_name": "丽都职工宿舍", "plot_url": "/xiaoqu/223447.html"}, "圣海翠湖园": {"plot_name": "圣海翠湖园", "plot_url": "/xiaoqu/223269.html"}, "尚8里文创园": {"plot_name": "尚8里文创园", "plot_url": "/xiaoqu/223095.html"}, "华阳公寓": {"plot_name": "华阳公寓", "plot_url": "/xiaoqu/222629.html"}, "京泰自主城": {"plot_name": "京泰自主城", "plot_url": "/xiaoqu/222610.html"}, "金盏嘉园D区": {"plot_name": "金盏嘉园D区", "plot_url": "/xiaoqu/222483.html"}, "长飞小区": {"plot_name": "长飞小区", "plot_url": "/xiaoqu/221936.html"}, "上东8号": {"plot_name": "上东8号", "plot_url": "/xiaoqu/221806.html"}, "水郡长安二号院": {"plot_name": "水郡长安二号院", "plot_url": "/xiaoqu/221781.html"}, "南湖渠三巷6号院": {"plot_name": "南湖渠三巷6号院", "plot_url": "/xiaoqu/221196.html"}, "朝阳嘉园(京棉新城三期)": {"plot_name": "朝阳嘉园(京棉新城三期)", "plot_url": "/xiaoqu/221066.html"}, "怡思苑": {"plot_name": "怡思苑", "plot_url": "/xiaoqu/220793.html"}, "力鸿花园": {"plot_name": "力鸿花园", "plot_url": "/xiaoqu/220107.html"}, "前进住宅小区": {"plot_name": "前进住宅小区", "plot_url": "/xiaoqu/218767.html"}, "水碓子东里": {"plot_name": "水碓子东里", "plot_url": "/xiaoqu/217567.html"}, "科学园南里三区": {"plot_name": "科学园南里三区", "plot_url": "/xiaoqu/217259.html"}, "飞悦经典": {"plot_name": "飞悦经典", "plot_url": "/xiaoqu/217168.html"}, "北辰福第中区": {"plot_name": "北辰福第中区", "plot_url": "/xiaoqu/217122.html"}, "珠江罗马嘉园(西区)": {"plot_name": "珠江罗马嘉园(西区)", "plot_url": "/xiaoqu/217075.html"}, "康营家园23期": {"plot_name": "康营家园23期", "plot_url": "/xiaoqu/216883.html"}, "御花苑公寓": {"plot_name": "御花苑公寓", "plot_url": "/xiaoqu/215317.html"}, "世奥国际中心": {"plot_name": "世奥国际中心", "plot_url": "/xiaoqu/214312.html"}, "新华路公安局宿舍": {"plot_name": "新华路公安局宿舍", "plot_url": "/xiaoqu/214004.html"}, "东架松": {"plot_name": "东架松", "plot_url": "/xiaoqu/213807.html"}, "新源南路7号小区": {"plot_name": "新源南路7号小区", "plot_url": "/xiaoqu/213729.html"}, "国美第一城3号院": {"plot_name": "国美第一城3号院", "plot_url": "/xiaoqu/213717.html"}, "富力城A区": {"plot_name": "富力城A区", "plot_url": "/xiaoqu/213601.html"}, "奥林匹克花园(三期)": {"plot_name": "奥林匹克花园(三期)", "plot_url": "/xiaoqu/213258.html"}, "柏林爱乐(四期)": {"plot_name": "柏林爱乐(四期)", "plot_url": "/xiaoqu/213206.html"}, "天盛名都": {"plot_name": "天盛名都", "plot_url": "/xiaoqu/212135.html"}, "吉庆里小区": {"plot_name": "吉庆里小区", "plot_url": "/xiaoqu/212064.html"}, "佳兴园": {"plot_name": "佳兴园", "plot_url": "/xiaoqu/211617.html"}, "金越逸墅蓝湾(别墅)": {"plot_name": "金越逸墅蓝湾(别墅)", "plot_url": "/xiaoqu/211577.html"}, "奥林匹克花园(二期)": {"plot_name": "奥林匹克花园(二期)", "plot_url": "/xiaoqu/211478.html"}, "和平街西苑": {"plot_name": "和平街西苑", "plot_url": "/xiaoqu/210779.html"}, "育慧街2号院": {"plot_name": "育慧街2号院", "plot_url": "/xiaoqu/210778.html"}, "柳芳南里社区": {"plot_name": "柳芳南里社区", "plot_url": "/xiaoqu/210043.html"}, "高新区科苑社区": {"plot_name": "高新区科苑社区", "plot_url": "/xiaoqu/209935.html"}, "华海苑": {"plot_name": "华海苑", "plot_url": "/xiaoqu/208355.html"}, "三里屯北小街小区": {"plot_name": "三里屯北小街小区", "plot_url": "/xiaoqu/208106.html"}, "龙欣苑": {"plot_name": "龙欣苑", "plot_url": "/xiaoqu/207763.html"}, "长春工大住宅": {"plot_name": "长春工大住宅", "plot_url": "/xiaoqu/207306.html"}, "逸翠园": {"plot_name": "逸翠园", "plot_url": "/xiaoqu/206671.html"}, "北京Golf公寓": {"plot_name": "北京Golf公寓", "plot_url": "/xiaoqu/206484.html"}, "新源里西小区": {"plot_name": "新源里西小区", "plot_url": "/xiaoqu/206455.html"}, "永利国际": {"plot_name": "永利国际", "plot_url": "/xiaoqu/206290.html"}, "林苑雅居": {"plot_name": "林苑雅居", "plot_url": "/xiaoqu/205885.html"}, "阿曼寓所": {"plot_name": "阿曼寓所", "plot_url": "/xiaoqu/205853.html"}, "东直门外大街30号小区": {"plot_name": "东直门外大街30号小区", "plot_url": "/xiaoqu/205101.html"}, "枫桦美地": {"plot_name": "枫桦美地", "plot_url": "/xiaoqu/204975.html"}, "工大家园": {"plot_name": "工大家园", "plot_url": "/xiaoqu/204969.html"}, "景龙国际": {"plot_name": "景龙国际", "plot_url": "/xiaoqu/204932.html"}, "拉洛小区": {"plot_name": "拉洛小区", "plot_url": "/xiaoqu/204680.html"}, "骏豪中央公园广场": {"plot_name": "骏豪中央公园广场", "plot_url": "/xiaoqu/204011.html"}, "泛海国际香海园": {"plot_name": "泛海国际香海园", "plot_url": "/xiaoqu/203982.html"}, "瑞祥里小区13号楼": {"plot_name": "瑞祥里小区13号楼", "plot_url": "/xiaoqu/203952.html"}, "吉港小区": {"plot_name": "吉港小区", "plot_url": "/xiaoqu/203838.html"}, "育慧北里": {"plot_name": "育慧北里", "plot_url": "/xiaoqu/203837.html"}, "太阳公元南区": {"plot_name": "太阳公元南区", "plot_url": "/xiaoqu/203821.html"}, "金石美苑": {"plot_name": "金石美苑", "plot_url": "/xiaoqu/203225.html"}, "乐成公馆": {"plot_name": "乐成公馆", "plot_url": "/xiaoqu/202960.html"}, "华威西里": {"plot_name": "华威西里", "plot_url": "/xiaoqu/202556.html"}, "天茂湖三期温莎园": {"plot_name": "天茂湖三期温莎园", "plot_url": "/xiaoqu/202528.html"}, "天籁轩": {"plot_name": "天籁轩", "plot_url": "/xiaoqu/202285.html"}, "周庄嘉园B区": {"plot_name": "周庄嘉园B区", "plot_url": "/xiaoqu/202206.html"}, "华贸城(东区)": {"plot_name": "华贸城(东区)", "plot_url": "/xiaoqu/201688.html"}, "媒体村天畅园": {"plot_name": "媒体村天畅园", "plot_url": "/xiaoqu/201635.html"}, "嘉华世纪": {"plot_name": "嘉华世纪", "plot_url": "/xiaoqu/201564.html"}, "中海城风情苑南区": {"plot_name": "中海城风情苑南区", "plot_url": "/xiaoqu/201527.html"}, "西坝河北里": {"plot_name": "西坝河北里", "plot_url": "/xiaoqu/201464.html"}, "朝阳新华小区": {"plot_name": "朝阳新华小区", "plot_url": "/xiaoqu/201429.html"}, "南波大厦": {"plot_name": "南波大厦", "plot_url": "/xiaoqu/201342.html"}, "吉林大学科技园": {"plot_name": "吉林大学科技园", "plot_url": "/xiaoqu/200987.html"}, "垂杨柳东里": {"plot_name": "垂杨柳东里", "plot_url": "/xiaoqu/200981.html"}, "芍药居4号院": {"plot_name": "芍药居4号院", "plot_url": "/xiaoqu/200628.html"}, "华严北里1号院": {"plot_name": "华严北里1号院", "plot_url": "/xiaoqu/200557.html"}, "大成国际公寓": {"plot_name": "大成国际公寓", "plot_url": "/xiaoqu/200182.html"}, "垡头翠成馨园(C区112-144号)": {"plot_name": "垡头翠成馨园(C区112-144号)", "plot_url": "/xiaoqu/199825.html"}, "复地首府": {"plot_name": "复地首府", "plot_url": "/xiaoqu/199410.html"}, "住欣家园(西区)": {"plot_name": "住欣家园(西区)", "plot_url": "/xiaoqu/198544.html"}, "省委党校职工宿舍": {"plot_name": "省委党校职工宿舍", "plot_url": "/xiaoqu/197810.html"}, "静安东里": {"plot_name": "静安东里", "plot_url": "/xiaoqu/197336.html"}, "惠新东街甲3号小区": {"plot_name": "惠新东街甲3号小区", "plot_url": "/xiaoqu/197243.html"}, "前卫医院家属楼": {"plot_name": "前卫医院家属楼", "plot_url": "/xiaoqu/197169.html"}, "吉港南湖名家": {"plot_name": "吉港南湖名家", "plot_url": "/xiaoqu/196926.html"}, "吉洁小区": {"plot_name": "吉洁小区", "plot_url": "/xiaoqu/196450.html"}, "和光尘樾(别墅)": {"plot_name": "和光尘樾(别墅)", "plot_url": "/xiaoqu/196402.html"}, "甜水西园": {"plot_name": "甜水西园", "plot_url": "/xiaoqu/196226.html"}, "东旭花园(别墅)": {"plot_name": "东旭花园(别墅)", "plot_url": "/xiaoqu/195659.html"}, "农业部宿舍（农展南里）": {"plot_name": "农业部宿舍（农展南里）", "plot_url": "/xiaoqu/195180.html"}, "江南山水(别墅)": {"plot_name": "江南山水(别墅)", "plot_url": "/xiaoqu/195166.html"}, "少角村142号院": {"plot_name": "少角村142号院", "plot_url": "/xiaoqu/195128.html"}, "大羊坊甲4号院": {"plot_name": "大羊坊甲4号院", "plot_url": "/xiaoqu/194984.html"}, "康营家园5区": {"plot_name": "康营家园5区", "plot_url": "/xiaoqu/194789.html"}, "建工双合家园D区": {"plot_name": "建工双合家园D区", "plot_url": "/xiaoqu/194287.html"}, "熙悦尚郡": {"plot_name": "熙悦尚郡", "plot_url": "/xiaoqu/194168.html"}, "周庄嘉园7号院": {"plot_name": "周庄嘉园7号院", "plot_url": "/xiaoqu/194025.html"}, "远洋商务": {"plot_name": "远洋商务", "plot_url": "/xiaoqu/193866.html"}, "浩鸿园": {"plot_name": "浩鸿园", "plot_url": "/xiaoqu/193378.html"}, "枣营西里": {"plot_name": "枣营西里", "plot_url": "/xiaoqu/193286.html"}, "世纪村(三区)": {"plot_name": "世纪村(三区)", "plot_url": "/xiaoqu/193206.html"}, "管庄新村D区": {"plot_name": "管庄新村D区", "plot_url": "/xiaoqu/192912.html"}, "富康花园小区": {"plot_name": "富康花园小区", "plot_url": "/xiaoqu/192728.html"}, "京友公寓": {"plot_name": "京友公寓", "plot_url": "/xiaoqu/192524.html"}, "安外北苑2号院": {"plot_name": "安外北苑2号院", "plot_url": "/xiaoqu/192412.html"}, "建工双合家园C区": {"plot_name": "建工双合家园C区", "plot_url": "/xiaoqu/191955.html"}, "FESCO国际公寓": {"plot_name": "FESCO国际公寓", "plot_url": "/xiaoqu/191754.html"}, "东星时尚广场": {"plot_name": "东星时尚广场", "plot_url": "/xiaoqu/191643.html"}, "农丰里": {"plot_name": "农丰里", "plot_url": "/xiaoqu/191100.html"}, "华贸天地": {"plot_name": "华贸天地", "plot_url": "/xiaoqu/190680.html"}, "晨光家园A区": {"plot_name": "晨光家园A区", "plot_url": "/xiaoqu/190582.html"}, "博雅国际中心": {"plot_name": "博雅国际中心", "plot_url": "/xiaoqu/190468.html"}, "光华路小区": {"plot_name": "光华路小区", "plot_url": "/xiaoqu/190401.html"}, "天泰苑三期A8区)": {"plot_name": "天泰苑三期A8区)", "plot_url": "/xiaoqu/190008.html"}, "御翠尚府": {"plot_name": "御翠尚府", "plot_url": "/xiaoqu/189938.html"}, "悠唐麒麟公馆": {"plot_name": "悠唐麒麟公馆", "plot_url": "/xiaoqu/189863.html"}, "观音景园(西区)": {"plot_name": "观音景园(西区)", "plot_url": "/xiaoqu/189693.html"}, "定福家园南里3号院": {"plot_name": "定福家园南里3号院", "plot_url": "/xiaoqu/189228.html"}, "育慧里一区": {"plot_name": "育慧里一区", "plot_url": "/xiaoqu/189122.html"}, "宜家7080": {"plot_name": "宜家7080", "plot_url": "/xiaoqu/188943.html"}, "三源里北小街小区": {"plot_name": "三源里北小街小区", "plot_url": "/xiaoqu/188738.html"}, "东亚望京中心": {"plot_name": "东亚望京中心", "plot_url": "/xiaoqu/187670.html"}, "朝庭公寓": {"plot_name": "朝庭公寓", "plot_url": "/xiaoqu/187665.html"}, "欧风花园": {"plot_name": "欧风花园", "plot_url": "/xiaoqu/187605.html"}, "城市绿洲家园": {"plot_name": "城市绿洲家园", "plot_url": "/xiaoqu/187472.html"}, "六里屯东里": {"plot_name": "六里屯东里", "plot_url": "/xiaoqu/187416.html"}, "中纺里": {"plot_name": "中纺里", "plot_url": "/xiaoqu/187039.html"}, "益田国际公寓": {"plot_name": "益田国际公寓", "plot_url": "/xiaoqu/186512.html"}, "亚运新新家园": {"plot_name": "亚运新新家园", "plot_url": "/xiaoqu/186091.html"}, "关东店6号小区": {"plot_name": "关东店6号小区", "plot_url": "/xiaoqu/186041.html"}, "鸿博家园": {"plot_name": "鸿博家园", "plot_url": "/xiaoqu/185978.html"}, "公交红旗小区": {"plot_name": "公交红旗小区", "plot_url": "/xiaoqu/185948.html"}, "鸿博家园一期B区": {"plot_name": "鸿博家园一期B区", "plot_url": "/xiaoqu/185882.html"}, "新兴红旗嘉园": {"plot_name": "新兴红旗嘉园", "plot_url": "/xiaoqu/185857.html"}, "东旭公寓": {"plot_name": "东旭公寓", "plot_url": "/xiaoqu/185791.html"}, "保利嘉园3号院": {"plot_name": "保利嘉园3号院", "plot_url": "/xiaoqu/185177.html"}, "胜古家园": {"plot_name": "胜古家园", "plot_url": "/xiaoqu/184709.html"}, "丝竹园": {"plot_name": "丝竹园", "plot_url": "/xiaoqu/184603.html"}, "双桥六号井小区": {"plot_name": "双桥六号井小区", "plot_url": "/xiaoqu/184509.html"}, "朝来家园广华居": {"plot_name": "朝来家园广华居", "plot_url": "/xiaoqu/184498.html"}, "望京路3号院": {"plot_name": "望京路3号院", "plot_url": "/xiaoqu/184013.html"}, "华业玫瑰东方": {"plot_name": "华业玫瑰东方", "plot_url": "/xiaoqu/183993.html"}, "欧陆大厦": {"plot_name": "欧陆大厦", "plot_url": "/xiaoqu/183861.html"}, "亚泰豪苑": {"plot_name": "亚泰豪苑", "plot_url": "/xiaoqu/182671.html"}, "道家村": {"plot_name": "道家村", "plot_url": "/xiaoqu/182368.html"}, "富力爱丁堡公馆": {"plot_name": "富力爱丁堡公馆", "plot_url": "/xiaoqu/181520.html"}, "合生霄云路8号": {"plot_name": "合生霄云路8号", "plot_url": "/xiaoqu/181268.html"}, "柒号大厦": {"plot_name": "柒号大厦", "plot_url": "/xiaoqu/180828.html"}, "芍药居小区": {"plot_name": "芍药居小区", "plot_url": "/xiaoqu/179578.html"}, "安慧北里秀园": {"plot_name": "安慧北里秀园", "plot_url": "/xiaoqu/179500.html"}, "亮马河公寓": {"plot_name": "亮马河公寓", "plot_url": "/xiaoqu/179472.html"}, "凌云名苑": {"plot_name": "凌云名苑", "plot_url": "/xiaoqu/179279.html"}, "天泰定福苑": {"plot_name": "天泰定福苑", "plot_url": "/xiaoqu/179271.html"}, "山水文园西园(别墅)": {"plot_name": "山水文园西园(别墅)", "plot_url": "/xiaoqu/178835.html"}, "东八里庄新区": {"plot_name": "东八里庄新区", "plot_url": "/xiaoqu/178647.html"}, "光大名筑": {"plot_name": "光大名筑", "plot_url": "/xiaoqu/178643.html"}, "双桥五号井小区": {"plot_name": "双桥五号井小区", "plot_url": "/xiaoqu/178168.html"}, "南三里屯小区": {"plot_name": "南三里屯小区", "plot_url": "/xiaoqu/177954.html"}, "裕民路3号院": {"plot_name": "裕民路3号院", "plot_url": "/xiaoqu/177611.html"}, "美然动力街区A3区": {"plot_name": "美然动力街区A3区", "plot_url": "/xiaoqu/177512.html"}, "双井富力城(A区)": {"plot_name": "双井富力城(A区)", "plot_url": "/xiaoqu/177407.html"}, "金辉家园": {"plot_name": "金辉家园", "plot_url": "/xiaoqu/177286.html"}, "工体南里": {"plot_name": "工体南里", "plot_url": "/xiaoqu/177279.html"}, "佰汇古玩珠宝城A座商业": {"plot_name": "佰汇古玩珠宝城A座商业", "plot_url": "/xiaoqu/177125.html"}, "大西洋新城F区": {"plot_name": "大西洋新城F区", "plot_url": "/xiaoqu/176830.html"}, "北沙滩6号院": {"plot_name": "北沙滩6号院", "plot_url": "/xiaoqu/176779.html"}, "华盛乐章": {"plot_name": "华盛乐章", "plot_url": "/xiaoqu/176628.html"}, "艺术学院宿舍": {"plot_name": "艺术学院宿舍", "plot_url": "/xiaoqu/176076.html"}, "泰福苑二区": {"plot_name": "泰福苑二区", "plot_url": "/xiaoqu/175955.html"}, "万科金阳国际公寓": {"plot_name": "万科金阳国际公寓", "plot_url": "/xiaoqu/175561.html"}, "双桥东路6号院": {"plot_name": "双桥东路6号院", "plot_url": "/xiaoqu/174994.html"}, "百环家园": {"plot_name": "百环家园", "plot_url": "/xiaoqu/174794.html"}, "双桥中路10号北院": {"plot_name": "双桥中路10号北院", "plot_url": "/xiaoqu/174628.html"}, "高原街7号院": {"plot_name": "高原街7号院", "plot_url": "/xiaoqu/174123.html"}, "星海明珠": {"plot_name": "星海明珠", "plot_url": "/xiaoqu/173410.html"}, "裕民路1号院": {"plot_name": "裕民路1号院", "plot_url": "/xiaoqu/173334.html"}, "一品红城": {"plot_name": "一品红城", "plot_url": "/xiaoqu/173319.html"}, "京棉新城": {"plot_name": "京棉新城", "plot_url": "/xiaoqu/172897.html"}, "望京路4号院": {"plot_name": "望京路4号院", "plot_url": "/xiaoqu/172890.html"}, "润泽庄园": {"plot_name": "润泽庄园", "plot_url": "/xiaoqu/172850.html"}, "北沙滩8号院": {"plot_name": "北沙滩8号院", "plot_url": "/xiaoqu/172380.html"}, "华业国际公寓": {"plot_name": "华业国际公寓", "plot_url": "/xiaoqu/172219.html"}, "朝阳旺角": {"plot_name": "朝阳旺角", "plot_url": "/xiaoqu/171780.html"}, "康静里小区": {"plot_name": "康静里小区", "plot_url": "/xiaoqu/171597.html"}, "农光里中社": {"plot_name": "农光里中社", "plot_url": "/xiaoqu/171048.html"}, "泰利明苑": {"plot_name": "泰利明苑", "plot_url": "/xiaoqu/170837.html"}, "京水商务公寓": {"plot_name": "京水商务公寓", "plot_url": "/xiaoqu/170788.html"}, "弘善家园A区": {"plot_name": "弘善家园A区", "plot_url": "/xiaoqu/170737.html"}, "新星宇之新观邸": {"plot_name": "新星宇之新观邸", "plot_url": "/xiaoqu/170073.html"}, "天安第一城(别墅)": {"plot_name": "天安第一城(别墅)", "plot_url": "/xiaoqu/169515.html"}, "永安里煤炭部宿舍": {"plot_name": "永安里煤炭部宿舍", "plot_url": "/xiaoqu/168789.html"}, "八里庄北里小区": {"plot_name": "八里庄北里小区", "plot_url": "/xiaoqu/168210.html"}, "慧谷时空": {"plot_name": "慧谷时空", "plot_url": "/xiaoqu/168119.html"}, "香榭舍": {"plot_name": "香榭舍", "plot_url": "/xiaoqu/167758.html"}, "青荷里晨风园": {"plot_name": "青荷里晨风园", "plot_url": "/xiaoqu/167684.html"}, "集安小区": {"plot_name": "集安小区", "plot_url": "/xiaoqu/167645.html"}, "东三环南路46号小区": {"plot_name": "东三环南路46号小区", "plot_url": "/xiaoqu/167611.html"}, "望京中环南路11号院": {"plot_name": "望京中环南路11号院", "plot_url": "/xiaoqu/167514.html"}, "朝廷公寓": {"plot_name": "朝廷公寓", "plot_url": "/xiaoqu/167423.html"}, "劲松六区": {"plot_name": "劲松六区", "plot_url": "/xiaoqu/167001.html"}, "华发颐园": {"plot_name": "华发颐园", "plot_url": "/xiaoqu/166794.html"}, "慧苑华侨公寓": {"plot_name": "慧苑华侨公寓", "plot_url": "/xiaoqu/166467.html"}, "亚北新区鑫兆丽园": {"plot_name": "亚北新区鑫兆丽园", "plot_url": "/xiaoqu/166214.html"}, "商务厅宿舍": {"plot_name": "商务厅宿舍", "plot_url": "/xiaoqu/166086.html"}, "新源南路小区(8-12号(双号))": {"plot_name": "新源南路小区(8-12号(双号))", "plot_url": "/xiaoqu/166042.html"}, "安慧里二区": {"plot_name": "安慧里二区", "plot_url": "/xiaoqu/165846.html"}, "远洋新干线": {"plot_name": "远洋新干线", "plot_url": "/xiaoqu/165666.html"}, "名苑雅居": {"plot_name": "名苑雅居", "plot_url": "/xiaoqu/165631.html"}, "通惠家园惠生园": {"plot_name": "通惠家园惠生园", "plot_url": "/xiaoqu/165603.html"}, "吕家营": {"plot_name": "吕家营", "plot_url": "/xiaoqu/165511.html"}, "杰座大厦": {"plot_name": "杰座大厦", "plot_url": "/xiaoqu/164144.html"}, "新城国际公寓一期": {"plot_name": "新城国际公寓一期", "plot_url": "/xiaoqu/163420.html"}, "后现代城C区": {"plot_name": "后现代城C区", "plot_url": "/xiaoqu/162371.html"}, "亚运豪庭": {"plot_name": "亚运豪庭", "plot_url": "/xiaoqu/162348.html"}, "天乐园": {"plot_name": "天乐园", "plot_url": "/xiaoqu/162292.html"}, "广外南社区": {"plot_name": "广外南社区", "plot_url": "/xiaoqu/162285.html"}, "红璞双合青年社区": {"plot_name": "红璞双合青年社区", "plot_url": "/xiaoqu/162236.html"}, "美景东方": {"plot_name": "美景东方", "plot_url": "/xiaoqu/161306.html"}, "观典琥珀堡": {"plot_name": "观典琥珀堡", "plot_url": "/xiaoqu/161110.html"}, "京城雅居": {"plot_name": "京城雅居", "plot_url": "/xiaoqu/161079.html"}, "三五零四宿舍": {"plot_name": "三五零四宿舍", "plot_url": "/xiaoqu/161057.html"}, "劲松三区": {"plot_name": "劲松三区", "plot_url": "/xiaoqu/161056.html"}, "慧谷金色家园(一期)": {"plot_name": "慧谷金色家园(一期)", "plot_url": "/xiaoqu/160661.html"}, "上东双子座": {"plot_name": "上东双子座", "plot_url": "/xiaoqu/160415.html"}, "康营家园A区": {"plot_name": "康营家园A区", "plot_url": "/xiaoqu/160215.html"}, "惠新里": {"plot_name": "惠新里", "plot_url": "/xiaoqu/159960.html"}, "金茂府(望京)": {"plot_name": "金茂府(望京)", "plot_url": "/xiaoqu/159906.html"}, "万浦小镇B区": {"plot_name": "万浦小镇B区", "plot_url": "/xiaoqu/159702.html"}, "湖光壹号": {"plot_name": "湖光壹号", "plot_url": "/xiaoqu/159656.html"}, "工人体育场东路小区": {"plot_name": "工人体育场东路小区", "plot_url": "/xiaoqu/159650.html"}, "观巢": {"plot_name": "观巢", "plot_url": "/xiaoqu/159630.html"}, "华贸公寓": {"plot_name": "华贸公寓", "plot_url": "/xiaoqu/159230.html"}, "隆礼嘉园": {"plot_name": "隆礼嘉园", "plot_url": "/xiaoqu/158517.html"}, "华瀚福园(D区)": {"plot_name": "华瀚福园(D区)", "plot_url": "/xiaoqu/157990.html"}, "新星宇福苑二期": {"plot_name": "新星宇福苑二期", "plot_url": "/xiaoqu/157917.html"}, "瑞祥里西区": {"plot_name": "瑞祥里西区", "plot_url": "/xiaoqu/157799.html"}, "金台西路2号院": {"plot_name": "金台西路2号院", "plot_url": "/xiaoqu/157710.html"}, "光熙家园": {"plot_name": "光熙家园", "plot_url": "/xiaoqu/157197.html"}, "倚澜观邸(二期)": {"plot_name": "倚澜观邸(二期)", "plot_url": "/xiaoqu/157168.html"}, "信达龙湾": {"plot_name": "信达龙湾", "plot_url": "/xiaoqu/157140.html"}, "南湖东园(一区)": {"plot_name": "南湖东园(一区)", "plot_url": "/xiaoqu/156594.html"}, "青年路小区(北区)": {"plot_name": "青年路小区(北区)", "plot_url": "/xiaoqu/156160.html"}, "芍药居北里小区": {"plot_name": "芍药居北里小区", "plot_url": "/xiaoqu/156088.html"}, "京华豪园": {"plot_name": "京华豪园", "plot_url": "/xiaoqu/155731.html"}, "观澜湖别墅": {"plot_name": "观澜湖别墅", "plot_url": "/xiaoqu/155633.html"}, "姚家园东里八号院": {"plot_name": "姚家园东里八号院", "plot_url": "/xiaoqu/155456.html"}, "六北联建小区": {"plot_name": "六北联建小区", "plot_url": "/xiaoqu/155127.html"}, "润枫德尚国际公寓": {"plot_name": "润枫德尚国际公寓", "plot_url": "/xiaoqu/155116.html"}, "幸福三村": {"plot_name": "幸福三村", "plot_url": "/xiaoqu/154999.html"}, "碧水星阁": {"plot_name": "碧水星阁", "plot_url": "/xiaoqu/154925.html"}, "裘马都": {"plot_name": "裘马都", "plot_url": "/xiaoqu/154905.html"}, "惠新西街33号院": {"plot_name": "惠新西街33号院", "plot_url": "/xiaoqu/154902.html"}, "大禹南湖首府": {"plot_name": "大禹南湖首府", "plot_url": "/xiaoqu/154874.html"}, "国信南湖别墅": {"plot_name": "国信南湖别墅", "plot_url": "/xiaoqu/154772.html"}, "宝星园": {"plot_name": "宝星园", "plot_url": "/xiaoqu/154547.html"}, "新源里小区": {"plot_name": "新源里小区", "plot_url": "/xiaoqu/154302.html"}, "天怡家园": {"plot_name": "天怡家园", "plot_url": "/xiaoqu/154290.html"}, "北三里社区": {"plot_name": "北三里社区", "plot_url": "/xiaoqu/154196.html"}, "佳运园三区": {"plot_name": "佳运园三区", "plot_url": "/xiaoqu/153962.html"}, "煤科院南小区": {"plot_name": "煤科院南小区", "plot_url": "/xiaoqu/153624.html"}, "定福庄南里1号院": {"plot_name": "定福庄南里1号院", "plot_url": "/xiaoqu/153097.html"}, "建工动力港": {"plot_name": "建工动力港", "plot_url": "/xiaoqu/153017.html"}, "豆各庄1号院": {"plot_name": "豆各庄1号院", "plot_url": "/xiaoqu/152442.html"}, "丽水嘉园": {"plot_name": "丽水嘉园", "plot_url": "/xiaoqu/152435.html"}, "28号商品楼": {"plot_name": "28号商品楼", "plot_url": "/xiaoqu/152046.html"}, "马房寺路398号楼": {"plot_name": "马房寺路398号楼", "plot_url": "/xiaoqu/151385.html"}, "伟业富强天玺": {"plot_name": "伟业富强天玺", "plot_url": "/xiaoqu/150435.html"}, "胡家园社区西区": {"plot_name": "胡家园社区西区", "plot_url": "/xiaoqu/150241.html"}, "管庄新村C区": {"plot_name": "管庄新村C区", "plot_url": "/xiaoqu/149923.html"}, "上康城公寓": {"plot_name": "上康城公寓", "plot_url": "/xiaoqu/149627.html"}, "水碓子十五号院": {"plot_name": "水碓子十五号院", "plot_url": "/xiaoqu/149318.html"}, "来北家园": {"plot_name": "来北家园", "plot_url": "/xiaoqu/149113.html"}, "磨房南里小区": {"plot_name": "磨房南里小区", "plot_url": "/xiaoqu/148681.html"}, "祁家豁子社区": {"plot_name": "祁家豁子社区", "plot_url": "/xiaoqu/148594.html"}, "后现代城A区": {"plot_name": "后现代城A区", "plot_url": "/xiaoqu/148568.html"}, "公安家属楼": {"plot_name": "公安家属楼", "plot_url": "/xiaoqu/148497.html"}, "时间国际中心": {"plot_name": "时间国际中心", "plot_url": "/xiaoqu/148108.html"}, "利泽西园": {"plot_name": "利泽西园", "plot_url": "/xiaoqu/148094.html"}, "百子湾家园(B区)": {"plot_name": "百子湾家园(B区)", "plot_url": "/xiaoqu/148038.html"}, "潘家园路9号院": {"plot_name": "潘家园路9号院", "plot_url": "/xiaoqu/147950.html"}, "垡头翠城盛园社区": {"plot_name": "垡头翠城盛园社区", "plot_url": "/xiaoqu/147595.html"}, "百菊小区": {"plot_name": "百菊小区", "plot_url": "/xiaoqu/147534.html"}, "东方东路小区": {"plot_name": "东方东路小区", "plot_url": "/xiaoqu/147514.html"}, "双花园南里二区": {"plot_name": "双花园南里二区", "plot_url": "/xiaoqu/146764.html"}, "蓝色家园": {"plot_name": "蓝色家园", "plot_url": "/xiaoqu/146233.html"}, "天天朝阳": {"plot_name": "天天朝阳", "plot_url": "/xiaoqu/145695.html"}, "拂林园": {"plot_name": "拂林园", "plot_url": "/xiaoqu/145199.html"}, "林奥嘉园": {"plot_name": "林奥嘉园", "plot_url": "/xiaoqu/144893.html"}, "慧谷金色家园二期": {"plot_name": "慧谷金色家园二期", "plot_url": "/xiaoqu/144664.html"}, "苹果派": {"plot_name": "苹果派", "plot_url": "/xiaoqu/144600.html"}, "远洋万和城B区": {"plot_name": "远洋万和城B区", "plot_url": "/xiaoqu/144288.html"}, "首城珑玺(别墅)": {"plot_name": "首城珑玺(别墅)", "plot_url": "/xiaoqu/144075.html"}, "新星宇左岸小区": {"plot_name": "新星宇左岸小区", "plot_url": "/xiaoqu/143937.html"}, "长影世纪村": {"plot_name": "长影世纪村", "plot_url": "/xiaoqu/143616.html"}, "西坝河西里": {"plot_name": "西坝河西里", "plot_url": "/xiaoqu/143342.html"}, "朝阳捷座": {"plot_name": "朝阳捷座", "plot_url": "/xiaoqu/143103.html"}, "小关北里24号院": {"plot_name": "小关北里24号院", "plot_url": "/xiaoqu/142997.html"}, "芳草苑小区": {"plot_name": "芳草苑小区", "plot_url": "/xiaoqu/142960.html"}, "安华里五区": {"plot_name": "安华里五区", "plot_url": "/xiaoqu/142420.html"}, "水碓子北里": {"plot_name": "水碓子北里", "plot_url": "/xiaoqu/141506.html"}, "锦绣园公寓": {"plot_name": "锦绣园公寓", "plot_url": "/xiaoqu/141266.html"}, "得易居": {"plot_name": "得易居", "plot_url": "/xiaoqu/141257.html"}, "京达国际公寓": {"plot_name": "京达国际公寓", "plot_url": "/xiaoqu/141220.html"}, "建工双合家园B区": {"plot_name": "建工双合家园B区", "plot_url": "/xiaoqu/141046.html"}, "东洲家园": {"plot_name": "东洲家园", "plot_url": "/xiaoqu/140505.html"}, "都市心海岸雅园": {"plot_name": "都市心海岸雅园", "plot_url": "/xiaoqu/140163.html"}, "巢东家园": {"plot_name": "巢东家园", "plot_url": "/xiaoqu/139972.html"}, "花家地南里": {"plot_name": "花家地南里", "plot_url": "/xiaoqu/139574.html"}, "试验机研究所宿舍": {"plot_name": "试验机研究所宿舍", "plot_url": "/xiaoqu/139484.html"}, "万科大都会": {"plot_name": "万科大都会", "plot_url": "/xiaoqu/139126.html"}, "垡头西里三区": {"plot_name": "垡头西里三区", "plot_url": "/xiaoqu/138991.html"}, "砖角楼北里": {"plot_name": "砖角楼北里", "plot_url": "/xiaoqu/138492.html"}, "凯景铭座大厦": {"plot_name": "凯景铭座大厦", "plot_url": "/xiaoqu/138478.html"}, "咖啡小镇": {"plot_name": "咖啡小镇", "plot_url": "/xiaoqu/138161.html"}, "呼家楼北里": {"plot_name": "呼家楼北里", "plot_url": "/xiaoqu/137762.html"}, "华亭嘉园": {"plot_name": "华亭嘉园", "plot_url": "/xiaoqu/137753.html"}, "逸翠园(2号院)": {"plot_name": "逸翠园(2号院)", "plot_url": "/xiaoqu/137513.html"}, "健翔山庄": {"plot_name": "健翔山庄", "plot_url": "/xiaoqu/137061.html"}, "首创天禧": {"plot_name": "首创天禧", "plot_url": "/xiaoqu/137005.html"}, "劲松南路小区": {"plot_name": "劲松南路小区", "plot_url": "/xiaoqu/136363.html"}, "太阳星城火星园": {"plot_name": "太阳星城火星园", "plot_url": "/xiaoqu/136003.html"}, "金隅可乐": {"plot_name": "金隅可乐", "plot_url": "/xiaoqu/135794.html"}, "民航医院宿舍": {"plot_name": "民航医院宿舍", "plot_url": "/xiaoqu/135744.html"}, "双桥中路10号南院": {"plot_name": "双桥中路10号南院", "plot_url": "/xiaoqu/135685.html"}, "远洋万和城C区": {"plot_name": "远洋万和城C区", "plot_url": "/xiaoqu/135649.html"}, "惠新西街5号院": {"plot_name": "惠新西街5号院", "plot_url": "/xiaoqu/135623.html"}, "十里堡甲3号院": {"plot_name": "十里堡甲3号院", "plot_url": "/xiaoqu/135619.html"}, "芍药居南区": {"plot_name": "芍药居南区", "plot_url": "/xiaoqu/135563.html"}, "小关东里10号院": {"plot_name": "小关东里10号院", "plot_url": "/xiaoqu/135366.html"}, "华严北里4号院": {"plot_name": "华严北里4号院", "plot_url": "/xiaoqu/135257.html"}, "金融家苑": {"plot_name": "金融家苑", "plot_url": "/xiaoqu/135149.html"}, "东区国际公寓": {"plot_name": "东区国际公寓", "plot_url": "/xiaoqu/134877.html"}, "珠江罗马嘉园": {"plot_name": "珠江罗马嘉园", "plot_url": "/xiaoqu/134666.html"}, "蒋府家园": {"plot_name": "蒋府家园", "plot_url": "/xiaoqu/133268.html"}, "小关东街小区": {"plot_name": "小关东街小区", "plot_url": "/xiaoqu/132918.html"}, "裕民东里": {"plot_name": "裕民东里", "plot_url": "/xiaoqu/131907.html"}, "华威北里": {"plot_name": "华威北里", "plot_url": "/xiaoqu/131902.html"}, "大山子南里": {"plot_name": "大山子南里", "plot_url": "/xiaoqu/131901.html"}, "平安嘉苑": {"plot_name": "平安嘉苑", "plot_url": "/xiaoqu/131715.html"}, "西昌小区西区": {"plot_name": "西昌小区西区", "plot_url": "/xiaoqu/131637.html"}, "中国铁建乐想汇": {"plot_name": "中国铁建乐想汇", "plot_url": "/xiaoqu/131348.html"}, "广渠门内8号院": {"plot_name": "广渠门内8号院", "plot_url": "/xiaoqu/130878.html"}, "康营家园25期": {"plot_name": "康营家园25期", "plot_url": "/xiaoqu/130861.html"}, "国际城乐想汇": {"plot_name": "国际城乐想汇", "plot_url": "/xiaoqu/130724.html"}, "SOHO北京公馆": {"plot_name": "SOHO北京公馆", "plot_url": "/xiaoqu/130557.html"}, "上东别墅玉林山水花园": {"plot_name": "上东别墅玉林山水花园", "plot_url": "/xiaoqu/130042.html"}, "东恒时代(二期)": {"plot_name": "东恒时代(二期)", "plot_url": "/xiaoqu/130009.html"}, "世茂宫园": {"plot_name": "世茂宫园", "plot_url": "/xiaoqu/130007.html"}, "惠新南里1号院": {"plot_name": "惠新南里1号院", "plot_url": "/xiaoqu/129595.html"}, "同建小区": {"plot_name": "同建小区", "plot_url": "/xiaoqu/129522.html"}, "黄木厂小区": {"plot_name": "黄木厂小区", "plot_url": "/xiaoqu/129256.html"}, "官悦欣园(B区)": {"plot_name": "官悦欣园(B区)", "plot_url": "/xiaoqu/128626.html"}, "轻铁湖光花园(三期)": {"plot_name": "轻铁湖光花园(三期)", "plot_url": "/xiaoqu/128426.html"}, "新发路小区": {"plot_name": "新发路小区", "plot_url": "/xiaoqu/128122.html"}, "铖裕香榭湾": {"plot_name": "铖裕香榭湾", "plot_url": "/xiaoqu/127999.html"}, "道家园小区": {"plot_name": "道家园小区", "plot_url": "/xiaoqu/127961.html"}, "东直门外大街18号小区": {"plot_name": "东直门外大街18号小区", "plot_url": "/xiaoqu/127478.html"}, "新金山国际公寓": {"plot_name": "新金山国际公寓", "plot_url": "/xiaoqu/127123.html"}, "杨闸新村": {"plot_name": "杨闸新村", "plot_url": "/xiaoqu/126962.html"}, "管庄北二里小区": {"plot_name": "管庄北二里小区", "plot_url": "/xiaoqu/126953.html"}, "西大望路甲27号院": {"plot_name": "西大望路甲27号院", "plot_url": "/xiaoqu/126924.html"}, "瞰都": {"plot_name": "瞰都", "plot_url": "/xiaoqu/126845.html"}, "亮马桥路9号院": {"plot_name": "亮马桥路9号院", "plot_url": "/xiaoqu/126642.html"}, "日月东华": {"plot_name": "日月东华", "plot_url": "/xiaoqu/126510.html"}, "嘉铭桐城C区": {"plot_name": "嘉铭桐城C区", "plot_url": "/xiaoqu/126004.html"}, "远洋一方花语苑": {"plot_name": "远洋一方花语苑", "plot_url": "/xiaoqu/125883.html"}, "都城心屿": {"plot_name": "都城心屿", "plot_url": "/xiaoqu/125604.html"}, "碧水园社区": {"plot_name": "碧水园社区", "plot_url": "/xiaoqu/124936.html"}, "新华联丽港(商住楼)": {"plot_name": "新华联丽港(商住楼)", "plot_url": "/xiaoqu/124171.html"}, "马泉营二区": {"plot_name": "马泉营二区", "plot_url": "/xiaoqu/124162.html"}, "华纺易城": {"plot_name": "华纺易城", "plot_url": "/xiaoqu/123796.html"}, "延静里中街3号院": {"plot_name": "延静里中街3号院", "plot_url": "/xiaoqu/123347.html"}, "慧忠里小区": {"plot_name": "慧忠里小区", "plot_url": "/xiaoqu/123166.html"}, "大通花园B区": {"plot_name": "大通花园B区", "plot_url": "/xiaoqu/122606.html"}, "兆维小区": {"plot_name": "兆维小区", "plot_url": "/xiaoqu/122331.html"}, "柏阳景园C区": {"plot_name": "柏阳景园C区", "plot_url": "/xiaoqu/122308.html"}, "原国际合作宿舍": {"plot_name": "原国际合作宿舍", "plot_url": "/xiaoqu/122136.html"}, "锐城国际": {"plot_name": "锐城国际", "plot_url": "/xiaoqu/122105.html"}, "阳光100国际公寓": {"plot_name": "阳光100国际公寓", "plot_url": "/xiaoqu/121729.html"}, "五五一四小区": {"plot_name": "五五一四小区", "plot_url": "/xiaoqu/121668.html"}, "麦子店街小区": {"plot_name": "麦子店街小区", "plot_url": "/xiaoqu/121663.html"}, "延静里中街小区": {"plot_name": "延静里中街小区", "plot_url": "/xiaoqu/121638.html"}, "花家地西里一区": {"plot_name": "花家地西里一区", "plot_url": "/xiaoqu/121459.html"}, "建业苑": {"plot_name": "建业苑", "plot_url": "/xiaoqu/121362.html"}, "康营家园11期": {"plot_name": "康营家园11期", "plot_url": "/xiaoqu/121327.html"}, "沿海赛洛城南区": {"plot_name": "沿海赛洛城南区", "plot_url": "/xiaoqu/121051.html"}, "芳北巷小区": {"plot_name": "芳北巷小区", "plot_url": "/xiaoqu/120934.html"}, "广渠路46号小区": {"plot_name": "广渠路46号小区", "plot_url": "/xiaoqu/120733.html"}, "育慧里二区": {"plot_name": "育慧里二区", "plot_url": "/xiaoqu/120631.html"}, "陶家湾小区": {"plot_name": "陶家湾小区", "plot_url": "/xiaoqu/120355.html"}, "康城暖山": {"plot_name": "康城暖山", "plot_url": "/xiaoqu/120218.html"}, "高原街4号院": {"plot_name": "高原街4号院", "plot_url": "/xiaoqu/120217.html"}, "窝趣轻社区": {"plot_name": "窝趣轻社区", "plot_url": "/xiaoqu/120085.html"}, "管庄南街3号小区": {"plot_name": "管庄南街3号小区", "plot_url": "/xiaoqu/120039.html"}, "首开国风北京": {"plot_name": "首开国风北京", "plot_url": "/xiaoqu/120020.html"}, "丽苑小区(马泉营四区)": {"plot_name": "丽苑小区(马泉营四区)", "plot_url": "/xiaoqu/119642.html"}, "金蝉欢乐园": {"plot_name": "金蝉欢乐园", "plot_url": "/xiaoqu/119599.html"}, "康营家园6期": {"plot_name": "康营家园6期", "plot_url": "/xiaoqu/119167.html"}, "胜古北里": {"plot_name": "胜古北里", "plot_url": "/xiaoqu/118993.html"}, "大郊亭北街16号院": {"plot_name": "大郊亭北街16号院", "plot_url": "/xiaoqu/118957.html"}, "嘉多丽园(北区)": {"plot_name": "嘉多丽园(北区)", "plot_url": "/xiaoqu/117397.html"}, "扬州水乡(别墅)": {"plot_name": "扬州水乡(别墅)", "plot_url": "/xiaoqu/117284.html"}, "光辉里小区": {"plot_name": "光辉里小区", "plot_url": "/xiaoqu/117243.html"}, "水星园": {"plot_name": "水星园", "plot_url": "/xiaoqu/117169.html"}, "品元": {"plot_name": "品元", "plot_url": "/xiaoqu/116973.html"}, "塞纳维拉水景别墅": {"plot_name": "塞纳维拉水景别墅", "plot_url": "/xiaoqu/116830.html"}, "酒仙桥东路18号院": {"plot_name": "酒仙桥东路18号院", "plot_url": "/xiaoqu/116739.html"}, "领地OFFICE": {"plot_name": "领地OFFICE", "plot_url": "/xiaoqu/116353.html"}, "西大望路北小区": {"plot_name": "西大望路北小区", "plot_url": "/xiaoqu/116324.html"}, "芳园里西区": {"plot_name": "芳园里西区", "plot_url": "/xiaoqu/116115.html"}, "大西洋新城D区": {"plot_name": "大西洋新城D区", "plot_url": "/xiaoqu/116045.html"}, "民旺园19号院": {"plot_name": "民旺园19号院", "plot_url": "/xiaoqu/115982.html"}, "金驹家园F区": {"plot_name": "金驹家园F区", "plot_url": "/xiaoqu/115978.html"}, "通盛园区": {"plot_name": "通盛园区", "plot_url": "/xiaoqu/115944.html"}, "金茂府东区(商住楼)": {"plot_name": "金茂府东区(商住楼)", "plot_url": "/xiaoqu/115521.html"}, "观音惠园": {"plot_name": "观音惠园", "plot_url": "/xiaoqu/115348.html"}, "高杨树南里": {"plot_name": "高杨树南里", "plot_url": "/xiaoqu/115269.html"}, "科学园南里七区": {"plot_name": "科学园南里七区", "plot_url": "/xiaoqu/115193.html"}, "金徽公寓": {"plot_name": "金徽公寓", "plot_url": "/xiaoqu/115162.html"}, "湖光社区": {"plot_name": "湖光社区", "plot_url": "/xiaoqu/114962.html"}, "山水文园西园": {"plot_name": "山水文园西园", "plot_url": "/xiaoqu/114500.html"}, "优士阁": {"plot_name": "优士阁", "plot_url": "/xiaoqu/114369.html"}, "双花园西里小区": {"plot_name": "双花园西里小区", "plot_url": "/xiaoqu/114362.html"}, "香克林": {"plot_name": "香克林", "plot_url": "/xiaoqu/114319.html"}, "首开东都汇公寓": {"plot_name": "首开东都汇公寓", "plot_url": "/xiaoqu/113893.html"}, "京烟宿舍小区": {"plot_name": "京烟宿舍小区", "plot_url": "/xiaoqu/113647.html"}, "上东三角洲": {"plot_name": "上东三角洲", "plot_url": "/xiaoqu/113554.html"}, "和平西街1号院": {"plot_name": "和平西街1号院", "plot_url": "/xiaoqu/113290.html"}, "汉森香榭里": {"plot_name": "汉森香榭里", "plot_url": "/xiaoqu/113157.html"}, "捷强花园": {"plot_name": "捷强花园", "plot_url": "/xiaoqu/112682.html"}, "百子湾家园(C区)": {"plot_name": "百子湾家园(C区)", "plot_url": "/xiaoqu/111980.html"}, "建外SOHO(东区别墅)": {"plot_name": "建外SOHO(东区别墅)", "plot_url": "/xiaoqu/111958.html"}, "大悦公寓": {"plot_name": "大悦公寓", "plot_url": "/xiaoqu/111898.html"}, "花虎沟11号院": {"plot_name": "花虎沟11号院", "plot_url": "/xiaoqu/111855.html"}, "坝鑫家园": {"plot_name": "坝鑫家园", "plot_url": "/xiaoqu/111618.html"}, "金隅汇景苑四区": {"plot_name": "金隅汇景苑四区", "plot_url": "/xiaoqu/111559.html"}, "北苑路4号小区": {"plot_name": "北苑路4号小区", "plot_url": "/xiaoqu/111268.html"}, "科技家园": {"plot_name": "科技家园", "plot_url": "/xiaoqu/111118.html"}, "长庆花园二期": {"plot_name": "长庆花园二期", "plot_url": "/xiaoqu/110918.html"}, "海悦名门国际公寓": {"plot_name": "海悦名门国际公寓", "plot_url": "/xiaoqu/110788.html"}, "东坝家园B区": {"plot_name": "东坝家园B区", "plot_url": "/xiaoqu/110781.html"}, "建东苑东区": {"plot_name": "建东苑东区", "plot_url": "/xiaoqu/110320.html"}, "大禹城邦": {"plot_name": "大禹城邦", "plot_url": "/xiaoqu/110132.html"}, "奥林匹克花园(四期)": {"plot_name": "奥林匹克花园(四期)", "plot_url": "/xiaoqu/110070.html"}, "中环南路5号院": {"plot_name": "中环南路5号院", "plot_url": "/xiaoqu/110053.html"}, "天鹅湾南区": {"plot_name": "天鹅湾南区", "plot_url": "/xiaoqu/110022.html"}, "东安开运福里": {"plot_name": "东安开运福里", "plot_url": "/xiaoqu/110021.html"}, "上东8号(商住楼)": {"plot_name": "上东8号(商住楼)", "plot_url": "/xiaoqu/109981.html"}, "金隅国际": {"plot_name": "金隅国际", "plot_url": "/xiaoqu/109974.html"}, "向军南里": {"plot_name": "向军南里", "plot_url": "/xiaoqu/109680.html"}, "金港国际": {"plot_name": "金港国际", "plot_url": "/xiaoqu/109532.html"}, "金泽家园A区": {"plot_name": "金泽家园A区", "plot_url": "/xiaoqu/109443.html"}, "芍药居14号院": {"plot_name": "芍药居14号院", "plot_url": "/xiaoqu/108784.html"}, "炫彩嘉轩": {"plot_name": "炫彩嘉轩", "plot_url": "/xiaoqu/108415.html"}, "四和名居": {"plot_name": "四和名居", "plot_url": "/xiaoqu/108403.html"}, "小营北路主场": {"plot_name": "小营北路主场", "plot_url": "/xiaoqu/107954.html"}, "六里屯西里": {"plot_name": "六里屯西里", "plot_url": "/xiaoqu/107923.html"}, "金隅康惠园": {"plot_name": "金隅康惠园", "plot_url": "/xiaoqu/107850.html"}, "文化厅宿舍": {"plot_name": "文化厅宿舍", "plot_url": "/xiaoqu/106946.html"}, "福怡苑小区(北区)": {"plot_name": "福怡苑小区(北区)", "plot_url": "/xiaoqu/106856.html"}, "长铁新华路物业小区": {"plot_name": "长铁新华路物业小区", "plot_url": "/xiaoqu/106658.html"}, "康营家园12期": {"plot_name": "康营家园12期", "plot_url": "/xiaoqu/106148.html"}, "新源里东小区": {"plot_name": "新源里东小区", "plot_url": "/xiaoqu/105950.html"}, "巴赫丽舍": {"plot_name": "巴赫丽舍", "plot_url": "/xiaoqu/105889.html"}, "地矿宿舍": {"plot_name": "地矿宿舍", "plot_url": "/xiaoqu/105565.html"}, "迎新综合楼": {"plot_name": "迎新综合楼", "plot_url": "/xiaoqu/104980.html"}, "金隅丽港城": {"plot_name": "金隅丽港城", "plot_url": "/xiaoqu/104899.html"}, "南湖湾": {"plot_name": "南湖湾", "plot_url": "/xiaoqu/104592.html"}, "鸿博家园六区": {"plot_name": "鸿博家园六区", "plot_url": "/xiaoqu/104570.html"}, "易构空间": {"plot_name": "易构空间", "plot_url": "/xiaoqu/104116.html"}, "日坛晶华": {"plot_name": "日坛晶华", "plot_url": "/xiaoqu/104082.html"}, "宜家小区": {"plot_name": "宜家小区", "plot_url": "/xiaoqu/104021.html"}, "美丽舍": {"plot_name": "美丽舍", "plot_url": "/xiaoqu/104010.html"}, "长春光机与物理研究所第八小区": {"plot_name": "长春光机与物理研究所第八小区", "plot_url": "/xiaoqu/103925.html"}, "小关北里45号院": {"plot_name": "小关北里45号院", "plot_url": "/xiaoqu/103602.html"}, "中吉小区": {"plot_name": "中吉小区", "plot_url": "/xiaoqu/103225.html"}, "有色金属宿舍": {"plot_name": "有色金属宿舍", "plot_url": "/xiaoqu/102953.html"}, "科技新村(卫星路)": {"plot_name": "科技新村(卫星路)", "plot_url": "/xiaoqu/102904.html"}, "都会大厦": {"plot_name": "都会大厦", "plot_url": "/xiaoqu/102688.html"}, "鹿港嘉苑": {"plot_name": "鹿港嘉苑", "plot_url": "/xiaoqu/102478.html"}, "PARK北京": {"plot_name": "PARK北京", "plot_url": "/xiaoqu/102444.html"}, "天旺名都": {"plot_name": "天旺名都", "plot_url": "/xiaoqu/102243.html"}, "双旭花园": {"plot_name": "双旭花园", "plot_url": "/xiaoqu/101927.html"}, "观音景园": {"plot_name": "观音景园", "plot_url": "/xiaoqu/101798.html"}, "保利东郡": {"plot_name": "保利东郡", "plot_url": "/xiaoqu/101685.html"}, "三丰里": {"plot_name": "三丰里", "plot_url": "/xiaoqu/101683.html"}, "大西洋新城E区": {"plot_name": "大西洋新城E区", "plot_url": "/xiaoqu/101456.html"}, "双桥嘉园": {"plot_name": "双桥嘉园", "plot_url": "/xiaoqu/101293.html"}, "双花园南里一区": {"plot_name": "双花园南里一区", "plot_url": "/xiaoqu/100984.html"}, "管庄西里": {"plot_name": "管庄西里", "plot_url": "/xiaoqu/100746.html"}, "清友园": {"plot_name": "清友园", "plot_url": "/xiaoqu/100483.html"}, "华亿红府": {"plot_name": "华亿红府", "plot_url": "/xiaoqu/100279.html"}, "听涛雅居": {"plot_name": "听涛雅居", "plot_url": "/xiaoqu/100220.html"}, "翡翠花溪": {"plot_name": "翡翠花溪", "plot_url": "/xiaoqu/100001.html"}, "南十里居10号院": {"plot_name": "南十里居10号院", "plot_url": "/xiaoqu/99750.html"}, "剑桥园西区": {"plot_name": "剑桥园西区", "plot_url": "/xiaoqu/99511.html"}, "辰芳园": {"plot_name": "辰芳园", "plot_url": "/xiaoqu/99231.html"}, "合生麒麟社": {"plot_name": "合生麒麟社", "plot_url": "/xiaoqu/99103.html"}, "博世祥园": {"plot_name": "博世祥园", "plot_url": "/xiaoqu/98336.html"}, "紫南家园北区": {"plot_name": "紫南家园北区", "plot_url": "/xiaoqu/98311.html"}, "金隅凤麟洲": {"plot_name": "金隅凤麟洲", "plot_url": "/xiaoqu/97871.html"}, "仰山路4号院": {"plot_name": "仰山路4号院", "plot_url": "/xiaoqu/97674.html"}, "天筑零点": {"plot_name": "天筑零点", "plot_url": "/xiaoqu/97653.html"}, "松榆里社区": {"plot_name": "松榆里社区", "plot_url": "/xiaoqu/97407.html"}, "华严北里9号院": {"plot_name": "华严北里9号院", "plot_url": "/xiaoqu/97161.html"}, "优点社区": {"plot_name": "优点社区", "plot_url": "/xiaoqu/96771.html"}, "劲松七区": {"plot_name": "劲松七区", "plot_url": "/xiaoqu/96573.html"}, "潘道庙小区": {"plot_name": "潘道庙小区", "plot_url": "/xiaoqu/96534.html"}, "富临中心": {"plot_name": "富临中心", "plot_url": "/xiaoqu/96398.html"}, "新都市计划": {"plot_name": "新都市计划", "plot_url": "/xiaoqu/96388.html"}, "姚家园东里七号院": {"plot_name": "姚家园东里七号院", "plot_url": "/xiaoqu/95975.html"}, "南新园小区": {"plot_name": "南新园小区", "plot_url": "/xiaoqu/95845.html"}, "石佛营东里小区": {"plot_name": "石佛营东里小区", "plot_url": "/xiaoqu/95832.html"}, "惠新苑": {"plot_name": "惠新苑", "plot_url": "/xiaoqu/95758.html"}, "朝阳无限芳菁苑": {"plot_name": "朝阳无限芳菁苑", "plot_url": "/xiaoqu/95736.html"}, "龙湖长楹天街": {"plot_name": "龙湖长楹天街", "plot_url": "/xiaoqu/95541.html"}, "省直系文化宿舍": {"plot_name": "省直系文化宿舍", "plot_url": "/xiaoqu/95273.html"}, "安慧里五区": {"plot_name": "安慧里五区", "plot_url": "/xiaoqu/95114.html"}, "英郡": {"plot_name": "英郡", "plot_url": "/xiaoqu/95057.html"}, "朝丰家园(15号院)": {"plot_name": "朝丰家园(15号院)", "plot_url": "/xiaoqu/94926.html"}, "加利大厦": {"plot_name": "加利大厦", "plot_url": "/xiaoqu/94678.html"}, "尚科办公社区": {"plot_name": "尚科办公社区", "plot_url": "/xiaoqu/94341.html"}, "康营家园15期": {"plot_name": "康营家园15期", "plot_url": "/xiaoqu/94317.html"}, "和平里西街23号院": {"plot_name": "和平里西街23号院", "plot_url": "/xiaoqu/94312.html"}, "姚家园西里五号院": {"plot_name": "姚家园西里五号院", "plot_url": "/xiaoqu/94169.html"}, "万方景轩": {"plot_name": "万方景轩", "plot_url": "/xiaoqu/92895.html"}, "双桥铁路小区北二区": {"plot_name": "双桥铁路小区北二区", "plot_url": "/xiaoqu/92880.html"}, "垂杨柳北里": {"plot_name": "垂杨柳北里", "plot_url": "/xiaoqu/92764.html"}, "中海安德鲁斯庄园东区": {"plot_name": "中海安德鲁斯庄园东区", "plot_url": "/xiaoqu/92554.html"}, "望京西园三区": {"plot_name": "望京西园三区", "plot_url": "/xiaoqu/92336.html"}, "中油管道长春矿区工农大路小区": {"plot_name": "中油管道长春矿区工农大路小区", "plot_url": "/xiaoqu/92141.html"}, "澳林春天三期": {"plot_name": "澳林春天三期", "plot_url": "/xiaoqu/91649.html"}, "长庆花园": {"plot_name": "长庆花园", "plot_url": "/xiaoqu/91639.html"}, "大西洋新城(C区)": {"plot_name": "大西洋新城(C区)", "plot_url": "/xiaoqu/91336.html"}, "吉林大学朝阳校区住宅区": {"plot_name": "吉林大学朝阳校区住宅区", "plot_url": "/xiaoqu/91165.html"}, "武圣西里": {"plot_name": "武圣西里", "plot_url": "/xiaoqu/91100.html"}, "垡头翠成馨园(E区)": {"plot_name": "垡头翠成馨园(E区)", "plot_url": "/xiaoqu/90908.html"}, "省二建宿舍": {"plot_name": "省二建宿舍", "plot_url": "/xiaoqu/90702.html"}, "金隅汇星苑": {"plot_name": "金隅汇星苑", "plot_url": "/xiaoqu/90693.html"}, "绿荫芳邻": {"plot_name": "绿荫芳邻", "plot_url": "/xiaoqu/90047.html"}, "广渠门外大街6号院": {"plot_name": "广渠门外大街6号院", "plot_url": "/xiaoqu/89753.html"}, "东方郁金香": {"plot_name": "东方郁金香", "plot_url": "/xiaoqu/89170.html"}}